Workbook
Name RefUnitTest: 'Input Data'!$B$5
Name RefIntegrationTest: 'Input Data'!$B$6
Name RefCodeReview: 'Input Data'!$B$7
Name RefManualQA: 'Input Data'!$B$8
Name RefAQA: 'Input Data'!$B$9
Name RefBugFix: 'Input Data'!$B$10
Name RefDocumentation: 'Input Data'!$B$11
Name RefCommunication: 'Input Data'!$B$12
Name RefRate: 'Input Data'!$B$13
Name EnumRoles: 'Input Data'!$F$17:$F$29
Name EnumSeniorities: 'Input Data'!$H$17:$H$23
Name EnumPhase: 'Input Data'!$J$17:$J$22
Name EnumLocations: 'Input Data'!$L$17:$L$21
Name EnumYesNo: 'Input Data'!$N$17:$N$18
Name EnumInclude: 'Input Data'!$P$17:$P$18

Sheet Usage Manual
A1: WBS and Estimates v1.5 — Usage Manual
A2: A presale/delivery estimation pack. PERT 3-point estimation per discipline, reconciled into one resource and cost model with profitability and a maintenance run-rate.
A4: Document conventions
B5: Color coding | C5: GRAY = hardcoded input (do not edit). BLUE = computed (do not edit). GREEN = editable (estimator inputs go here). YELLOW = epic / section / guidance row. ORANGE = validation warning (P/O ratio > 5 or O>ML>P).
B6: Per-tab guidance | C6: Every tab has a yellow guidance block at the top with Purpose / How to use / Inputs / Outputs / Linked tabs. Read it before editing.
B7: Named ranges | C7: Coefficients and enums are named ranges (RefBugFix, RefRate, EnumRoles, ...). Edit them on the Input Data tab; references update everywhere.
A8: Methodology
B9: PERT formulas | C9: Expected = (O + 4*ML + P)/6. StdDev = (P - O)/6. Variance = StdDev^2. Project Buffer on the Buffers tab = Subtotal + Z * sqrt(Sum(Variance)). Z = 0 (50%) / 1 (84%) / 2 (97%) confidence.
B10: Two layers of risk | C10: (1) Per-line Contingency on every Est tab (Apply = Yes => add ML * default_contingency to Expected). Use this for SPECIFIC uncertain items (KYC, blockchain, vendor APIs). (2) Project-wide PERT Z-score buffer on the Buffers tab. Use this for OVERALL confidence interval on the SOW.
B11: Augmentation coefficients | C11: On the WBS tab, Augmented = Base * (1 + UnitTest + IntegrationTest + CodeReview). Bugfix / Documentation / Communication are added on the Buffers tab as % of Buffered total.
B12: QA derivation | C12: Manual QA = (BE + FE) * RefManualQA. AQA = (BE + FE) * RefAQA. v1.5 fixes the v1.4 bug where QA variance was not propagated — Z-score buffer now applies to QA too. Alternative: use the QA Estimation tab for a per-stream QA WBS and override these coefficients.
B13: Cost layering | C13: (a) FTE cost from Headcount and Cost (rate looked up by Role x Seniority x Location on Rates tab; falls back to RefRate if no match). (b) Fixed Costs tab adds lump sums (pen test, audit, ...). (c) Maintenance tab models post go-live monthly run rate. (d) Internal Cost & Profitability gives margin.
A14: Workflow — order of operations
B15: Step 1 — Set context | C15: Fill Check-list (estimator names + reviews). Fill Solution Context & Sizing (#products, channels, integrations, durations, risks). Without these the number is unfalsifiable.
B16: Step 2 — Build WBS | C16: On WBS and Estimates, replace seed rows with your epics and user stories. Use stable IDs (E-1, US-1.3). Per row: enter O/ML/P for BE and FE, set Include / Phase / Milestone, write Assumptions / Description / Out of Scope / Jira link. Validation will flag P/O > 5 or O>ML>P in orange.
B17: Step 3 — Apply per-line contingency | C17: For HIGH-UNCERTAINTY rows set Apply Contingency = Yes. The default contingency is per-discipline (BA 20%, Arch 30%, QA 15%, DevOps 30%, PM 20%, UIUX 20%); on WBS the contingency is entered manually per row.
B18: Step 4 — Fill discipline tabs | C18: BA / Arch / QA / DevOps / PM / UIUX. Same column shape on each tab. Mark Include / Phase per item. Items left at zero hours are still in the catalogue but excluded from totals.
B19: Step 5 — Set Z-score | C19: On Buffers & Non-Dev Activities choose Z (0..2). Higher = more buffer = more conservative SOW. Default 1.0 (84% CI).
B20: Step 6 — Maintain Rates | C20: Edit Rates tab: rows are (Role x Seniority x Location => $/h). Headcount and Cost looks up rate via INDEX/MATCH. If no row matches the resource's (Role, Seniority, Location), the formula falls back to RefRate.
B21: Step 7 — Allocate resources | C21: On Headcount and Cost, add a row per resource with Role / Seniority / Location / Headcount / Allocation / Start Week / End Week. The right-hand 'Estimated vs Allocated' panel computes Delta Hours per role; minimize the absolute value.
B22: Step 8 — Add fixed costs | C22: On Fixed Costs add 3rd-party items (pen test, audit, perf test, KYC vendor licenses, cloud cost). Set Include = Included / Not included / Post-MVP.
B23: Step 9 — Verify margin | C23: On Internal Cost & Profitability check 'Project Profitability (build)' is at or above the desired threshold. If not, revisit Rates / seniority mix / scope.
B24: Step 10 — Plan maintenance | C24: Fill the Maintenance tab. Annual Run-rate is exposed; quote it separately in the SOW.
B25: Step 11 — Use reports | C25: Epic Weight ranks epics by cost (sponsor view). Monthly Cost Roll-out shows cash-flow profile. WBS Comparison stores snapshots so scope creep between versions is visible.
B26: Step 12 — Peer review & sign-off | C26: Update Check-list reviews to 'Yes' once Architecture / Design / BA / QA / DevOps / Estimation peer reviews complete. DM/PM final sign-off last.
A27: Tab index
B28: Check-list | C28: WHO estimated and WHAT was reviewed. Use it as the audit trail.
B29: Solution Context & Sizing | C29: WHY the number is what it is. Records the assumptions the estimate is conditioned on.
B30: WBS and Estimates | C30: Hierarchical Epic > User Story with BE/FE PERT estimates and per-row metadata.
B31: BA / Arch / QA / DevOps / PM / UIUX Estimation | C31: Per-discipline WBS. Replace the catalogue with reality and toggle Include/Phase per item.
B32: Buffers & Non-Dev Activities | C32: Applies PERT Z-score, Bugfix/Doc/Communication coefficients, derives MQA/AQA, adds discipline roll-ups.
B33: Rates | C33: Role x Seniority x Location rate card.
B34: Headcount and Cost | C34: Resource allocation grid with rate lookup; reconciles allocated vs estimated.
B35: Internal Cost & Profitability | C35: Salary + tax + overhead per resource; project profitability.
B36: Monthly Cost Roll-out | C36: Spreads allocated cost across months for cash-flow.
B37: Fixed Costs | C37: Lump-sum / 3rd-party costs included or excluded from the proposal.
B38: Maintenance | C38: Post go-live monthly + annual run-rate.
B39: Epic Weight | C39: Cost-by-epic ranking for sponsor conversations.
... B41: Input Data | C41: Global coefficients, blended-rate fallback, enums for dropdowns.
A42: Field glossary
B43: Include | C43: Included = goes into totals & SOW. Not included = stays in catalogue but excluded. Post-MVP = parked. Select = decision pending.
B44: Project Phase | C44: Discovery / Implementation / Post-MVP Enhancement / Maintenance. Drives where the row's hours land in the cost roll-out.
B45: Apply Contingency | C45: Yes/No per row. When Yes, default contingency % multiplies Most Likely and is added to Expected to form Final Expected.
B46: Final Expected | C46: Expected + Contingency. This is what feeds totals and downstream tabs.
B47: Seniority Index | C47: Roughly: average external rate divided by RefRate. > 1 means the team is more senior than the blended baseline; < 1 means more junior.
B48: Delta Hours | C48: Allocated Hours minus Estimated Hours per role. Negative = under-staffed (project will run long). Positive = over-staffed (cost waste).
A49: Defensibility checklist
B50: Before sending the estimate | C50: (1) Check-list filled. (2) Solution Context filled. (3) No orange validation warnings on WBS. (4) Discipline tabs reviewed by their respective leads. (5) Profitability >= threshold. (6) Peer review done. (7) Sponsor view (Epic Weight) sanity-checked. (8) Maintenance discussed even if not in scope.

Sheet Check-list
A1: Check-list — Estimator team & reviews
A2: Purpose: | B2: Audit trail for the estimate. Records WHO contributed each role's number and WHICH reviews have been completed. Without it, the workbook is anonymous and undefendable.
A3: How to use: | B3: Fill the names per role. As each review (Architecture / Design / BA / QA / DevOps / Peer / DM-PM sign-off) completes, set State = Yes and add Date + Reviewer. Mandatory calculations at the bottom point to where each KPI lives so a reviewer can verify them.
A4: Inputs: | B4: Names (manual). Review states / dates / reviewers (manual). KPI values can be linked from other tabs.
A5: Outputs: | B5: A single-page record that proves who estimated and who signed off.
A6: Linked tabs: | B6: Mandatory calculations point to: Internal Cost & Profitability, Headcount and Cost, Maintenance.
B8: Role / responsibility | C8: Last name, First name
B9: DM responsible for estimation
B10: PM responsible for estimation (if any)
A12: Estimation Team
B13: Role | C13: Last name, First name
B14: Solution Architect
B15: Software Architect
B16: Data Architect
B17: Lead BA / BA
B18: Lead QA / QA
B19: DevOps
B20: Designer (UI/UX)
B21: Front-end Web Developer
B22: Front-end Mobile Developer
B23: Back-end Developer
B24: Other
A26: Reviews
B27: Review type | C27: State | D27: Date | E27: Reviewer
B28: Architecture Review | C28: Yes
B29: Design Review (if any)
B30: BA / Requirements Review
B31: QA Strategy Review | C31: In progress
B32: DevOps / Infra Review
B33: Estimation Peer Review
B34: Final Sign-off (DM/PM)
A36: Mandatory calculations
B37: Calculation | C37: Value | D37: Source
B38: Discovery Phase Profitability (if any) | D38: Internal Cost & Profitability
B39: Proposed solution price profitability | D39: Internal Cost & Profitability
B40: Seniority Index | D40: Internal Cost & Profitability
B41: Total Hours (Build) | D41: Headcount and Cost
B42: Total Hours (Maintenance, monthly) | D42: Maintenance
B43: Total Cost (Build) | D43: Headcount and Cost
B44: Project Duration (weeks) | D44: Headcount and Cost
B45: Peak FTE | D45: Headcount and Cost

Sheet Solution Context & Sizing
A1: Solution Context & Sizing
A2: Purpose: | B2: Records the assumptions the estimate is conditioned on. If any of these change materially after the SOW is signed, the estimate must be revisited.
A3: How to use: | B3: Fill the Value column for each parameter. Discuss with the client; if a parameter is unknown, mark it 'TBD' and add it to the top risks. Use this tab as the cover sheet of the estimate when sharing externally.
A4: Inputs: | B4: Manual values from estimator + client conversations.
A5: Outputs: | B5: An immutable record of the scoping context at the moment the estimate was made.
A6: Linked tabs: | B6: Drives Apply Contingency = Yes decisions on every Est tab. Top risks here become the contingency drivers there.
A8: Section | B8: Parameter | C8: Value / description | D8: Notes
A9: Scope | B9: Products | D9: e.g. 1 product (eWallet, marketplace, ...)
A10: Scope | B10: Customers / customer categories | D10: B2C / B2B / Internal
A11: Scope | B11: User roles | D11: e.g. End-user, Business user, Admin
A12: Scope | B12: Channels | D12: Web, iOS, Android, integrations
A13: Scope | B13: Domain logic complexity | D13: Simple CRUD / Domain heavy / Regulated
A14: Scope | B14: Integrations (count) | D14: 5-15 integrations, list known ones
A15: Scope | B15: Vendor / 3rd-party products | D15: Set up by vendor or by us?
A16: Scope | B16: Major features (epics) | D16: 10-15 epics typical
A17: Infra | B17: Infrastructure model | D17: Public cloud / On-prem / Hybrid / Multi-region
A18: Infra | B18: Data residency / compliance | D18: GDPR, HIPAA, PCI-DSS, SoX, ...
A19: Infra | B19: Expected load | D19: users, RPS, data volume
A20: Infra | B20: Availability target | D20: SLA, RTO, RPO
... A24: Risks | B24: Top 3 estimation risks | D24: drives per-line Apply Contingency = Yes
A25: Risks | B25: Known unknowns
A26: Risks | B26: Hard assumptions | D26: things we believe but did not verify

Sheet WBS and Estimates
A1: WBS and Estimates
A2: Purpose: | B2: The product WBS — Epic > User Story hierarchy with PERT 3-point estimates for Back-End and Front-End. Per-row metadata makes the estimate defensible: every row carries an Include flag, Project Phase, Milestone, Assumptions, Description, Out of Scope, Dependencies, Comments and Jira link.
A3: How to use: | B3: (1) Add Section / Epic / User Story rows. Use stable IDs (E-1, US-1.3) — Epic Weight and WBS Comparison match by ID prefix. (2) Per US row, enter O / ML / P in hours for BE and FE. Augmented columns auto-add UnitTest+IntegrationTest+CodeReview. Expected, StdDev and Variance are PERT-derived. (3) Set Apply Contingency = Yes only on rows where you want to load extra hours; enter Contingency BE / FE manually. (4) Pick Include (Included / Not included / Post-MVP / Select), Phase, Milestone. (5) Fill Assumptions / Description / Out of Scope / Dependencies / Comments / Jira link. (6) Validation will highlight rows in ORANGE if P/O > 5 or O>ML>P — fix or comment.
A4: Inputs: | B4: O / ML / P per row (hours). Include / Phase / Milestone / Apply Contingency / Contingency BE/FE / metadata.
A5: Outputs: | B5: Expected BE / FE per row, StdDev/Variance per row. Sums of P (col P, BE Expected) and Q (FE Expected), and S/U (variance) feed Buffers & Non-Dev Activities.
A6: Linked tabs: | B6: Buffers & Non-Dev Activities (consumes Expected and Variance). Epic Weight (groups by ID prefix). WBS Comparison (joins by ID). Headcount and Cost (via Buffers totals).
A7: Hierarchy | B7: ID | C7: Decomposition Item | D7: Backend, h | G7: Frontend, h | J7: Augmented Backend, h | M7: Augmented Frontend, h | P7: Expected Implementation Back-End (man/h) | Q7: Expected Implementation Front-End (man/h) | R7: StdDev BE | S7: Variance BE | T7: StdDev FE | U7: Variance FE | V7: Apply Contingency | W7: Contingency, h (BE) | X7: Contingency, h (FE) | Y7: Include | Z7: Project Phase | AA7: Milestone | AB7: Assumptions | AC7: Description / Scope | AD7: Out of Scope | AE7: Dependencies | AF7: Comments | AG7: Jira / Ticket Link
A8: Hierarchy | B8: ID | C8: Decomposition Item | D8: O | E8: ML | F8: P | G8: O | H8: ML | I8: P | J8: Augmented O | K8: Augmented ML | L8: Augmented P | M8: Augmented O | N8: Augmented ML | O8: Augmented P | P8: Expected BE | Q8: Expected FE | R8: StdDev BE | S8: Variance BE | T8: StdDev FE | U8: Variance FE | V8: Apply Contingency | W8: Contingency BE | X8: Contingency FE | Y8: Include | Z8: Phase | AA8: Milestone | AB8: Assumptions | AC8: Description / Scope | AD8: Out of Scope | AE8: Dependencies | AF8: Comments | AG8: Jira / Ticket Link
A9: Section | C9: Infrastructure & Foundations
A10: UserStory | B10: INF-1.1 | C10: Solution setup (repos, project templates) | D10: 8 | E10: 16 | F10: 32 | G10: 6 | H10: 12 | I10: 20 | J10: =D10*(1+RefUnitTest+RefIntegrationTest+RefCodeReview) | K10: =E10*(1+RefUnitTest+RefIntegrationTest+RefCodeReview) | L10: =F10*(1+RefUnitTest+RefIntegrationTest+RefCodeReview) | M10: =G10*(1+RefUnitTest+RefIntegrationTest+RefCodeReview) | N10: =H10*(1+RefUnitTest+RefIntegrationTest+RefCodeReview) | O10: =I10*(1+RefUnitTest+RefIntegrationTest+RefCodeReview) | P10: =(J10+4*K10+L10)/6 | Q10: =(M10+4*N10+O10)/6 | R10: =(L10-J10)/6 | S10: =R10^2 | T10: =(O10-M10)/6 | U10: =T10^2 | V10: No | W10: 0 | X10: 0 | Y10: Included | Z10: Implementation | AA10: M1 | AC10: Bootstrap repositories, project templates, CI seed
A11: UserStory | B11: INF-1.2 | C11: Local infrastructure setup | D11: 0 | E11: 0 | F11: 0 | G11: 0 | H11: 0 | I11: 0 | J11: =D11*(1+RefUnitTest+RefIntegrationTest+RefCodeReview) | K11: =E11*(1+RefUnitTest+RefIntegrationTest+RefCodeReview) | L11: =F11*(1+RefUnitTest+RefIntegrationTest+RefCodeReview) | M11: =G11*(1+RefUnitTest+RefIntegrationTest+RefCodeReview) | N11: =H11*(1+RefUnitTest+RefIntegrationTest+RefCodeReview) | O11: =I11*(1+RefUnitTest+RefIntegrationTest+RefCodeReview) | P11: =(J11+4*K11+L11)/6 | Q11: =(M11+4*N11+O11)/6 | R11: =(L11-J11)/6 | S11: =R11^2 | T11: =(O11-M11)/6 | U11: =T11^2 | V11: No | W11: 0 | X11: 0 | Y11: Not included | Z11: Implementation | AA11: M1 | AF11: Covered in DevOps tab
A12: UserStory | B12: INF-1.3 | C12: CI/CD setup | D12: 0 | E12: 0 | F12: 0 | G12: 0 | H12: 0 | I12: 0 | J12: =D12*(1+RefUnitTest+RefIntegrationTest+RefCodeReview) | K12: =E12*(1+RefUnitTest+RefIntegrationTest+RefCodeReview) | L12: =F12*(1+RefUnitTest+RefIntegrationTest+RefCodeReview) | M12: =G12*(1+RefUnitTest+RefIntegrationTest+RefCodeReview) | N12: =H12*(1+RefUnitTest+RefIntegrationTest+RefCodeReview) | O12: =I12*(1+RefUnitTest+RefIntegrationTest+RefCodeReview) | P12: =(J12+4*K12+L12)/6 | Q12: =(M12+4*N12+O12)/6 | R12: =(L12-J12)/6 | S12: =R12^2 | T12: =(O12-M12)/6 | U12: =T12^2 | V12: No | W12: 0 | X12: 0 | Y12: Not included | Z12: Implementation | AA12: M1 | AE12: DevOps | AF12: Covered in DevOps tab
A13: UserStory | B13: INF-1.4 | C13: Static code analysis | D13: 0 | E13: 0 | F13: 0 | G13: 0 | H13: 0 | I13: 0 | J13: =D13*(1+RefUnitTest+RefIntegrationTest+RefCodeReview) | K13: =E13*(1+RefUnitTest+RefIntegrationTest+RefCodeReview) | L13: =F13*(1+RefUnitTest+RefIntegrationTest+RefCodeReview) | M13: =G13*(1+RefUnitTest+RefIntegrationTest+RefCodeReview) | N13: =H13*(1+RefUnitTest+RefIntegrationTest+RefCodeReview) | O13: =I13*(1+RefUnitTest+RefIntegrationTest+RefCodeReview) | P13: =(J13+4*K13+L13)/6 | Q13: =(M13+4*N13+O13)/6 | R13: =(L13-J13)/6 | S13: =R13^2 | T13: =(O13-M13)/6 | U13: =T13^2 | V13: No | W13: 0 | X13: 0 | Y13: Not included | Z13: Implementation | AA13: M1 | AF13: Covered in DevOps tab
A14: Section | C14: Product Scope
A15: Epic | B15: E-1 | C15: Authorization
A16: UserStory | B16: US-1.1 | C16: Onboarding | D16: 0 | E16: 0 | F16: 0 | G16: 2 | H16: 8 | I16: 16 | J16: =D16*(1+RefUnitTest+RefIntegrationTest+RefCodeReview) | K16: =E16*(1+RefUnitTest+RefIntegrationTest+RefCodeReview) | L16: =F16*(1+RefUnitTest+RefIntegrationTest+RefCodeReview) | M16: =G16*(1+RefUnitTest+RefIntegrationTest+RefCodeReview) | N16: =H16*(1+RefUnitTest+RefIntegrationTest+RefCodeReview) | O16: =I16*(1+RefUnitTest+RefIntegrationTest+RefCodeReview) | P16: =(J16+4*K16+L16)/6 | Q16: =(M16+4*N16+O16)/6 | R16: =(L16-J16)/6 | S16: =R16^2 | T16: =(O16-M16)/6 | U16: =T16^2 | V16: No | W16: 0 | X16: 0 | Y16: Included | Z16: Implementation | AA16: M1
A17: UserStory | B17: US-1.2 | C17: Accept Terms of Use | D17: 0 | E17: 0 | F17: 0 | G17: 1 | H17: 3 | I17: 4 | J17: =D17*(1+RefUnitTest+RefIntegrationTest+RefCodeReview) | K17: =E17*(1+RefUnitTest+RefIntegrationTest+RefCodeReview) | L17: =F17*(1+RefUnitTest+RefIntegrationTest+RefCodeReview) | M17: =G17*(1+RefUnitTest+RefIntegrationTest+RefCodeReview) | N17: =H17*(1+RefUnitTest+RefIntegrationTest+RefCodeReview) | O17: =I17*(1+RefUnitTest+RefIntegrationTest+RefCodeReview) | P17: =(J17+4*K17+L17)/6 | Q17: =(M17+4*N17+O17)/6 | R17: =(L17-J17)/6 | S17: =R17^2 | T17: =(O17-M17)/6 | U17: =T17^2 | V17: No | W17: 0 | X17: 0 | Y17: Included | Z17: Implementation | AA17: M1
A18: UserStory | B18: US-1.3 | C18: Sign Up (email/phone/SSO) | D18: 16 | E18: 24 | F18: 32 | G18: 16 | H18: 24 | I18: 32 | J18: =D18*(1+RefUnitTest+RefIntegrationTest+RefCodeReview) | K18: =E18*(1+RefUnitTest+RefIntegrationTest+RefCodeReview) | L18: =F18*(1+RefUnitTest+RefIntegrationTest+RefCodeReview) | M18: =G18*(1+RefUnitTest+RefIntegrationTest+RefCodeReview) | N18: =H18*(1+RefUnitTest+RefIntegrationTest+RefCodeReview) | O18: =I18*(1+RefUnitTest+RefIntegrationTest+RefCodeReview) | P18: =(J18+4*K18+L18)/6 | Q18: =(M18+4*N18+O18)/6 | R18: =(L18-J18)/6 | S18: =R18^2 | T18: =(O18-M18)/6 | U18: =T18^2 | V18: No | W18: 0 | X18: 0 | Y18: Included | Z18: Implementation | AA18: M1 | AB18: Google/Microsoft/Apple SSO
A19: UserStory | B19: US-1.4 | C19: Login | D19: 8 | E19: 16 | F19: 24 | G19: 8 | H19: 16 | I19: 24 | J19: =D19*(1+RefUnitTest+RefIntegrationTest+RefCodeReview) | K19: =E19*(1+RefUnitTest+RefIntegrationTest+RefCodeReview) | L19: =F19*(1+RefUnitTest+RefIntegrationTest+RefCodeReview) | M19: =G19*(1+RefUnitTest+RefIntegrationTest+RefCodeReview) | N19: =H19*(1+RefUnitTest+RefIntegrationTest+RefCodeReview) | O19: =I19*(1+RefUnitTest+RefIntegrationTest+RefCodeReview) | P19: =(J19+4*K19+L19)/6 | Q19: =(M19+4*N19+O19)/6 | R19: =(L19-J19)/6 | S19: =R19^2 | T19: =(O19-M19)/6 | U19: =T19^2 | V19: No | W19: 0 | X19: 0 | Y19: Included | Z19: Implementation | AA19: M1
A20: UserStory | B20: US-1.5 | C20: Reset password | D20: 8 | E20: 16 | F20: 24 | G20: 4 | H20: 8 | I20: 16 | J20: =D20*(1+RefUnitTest+RefIntegrationTest+RefCodeReview) | K20: =E20*(1+RefUnitTest+RefIntegrationTest+RefCodeReview) | L20: =F20*(1+RefUnitTest+RefIntegrationTest+RefCodeReview) | M20: =G20*(1+RefUnitTest+RefIntegrationTest+RefCodeReview) | N20: =H20*(1+RefUnitTest+RefIntegrationTest+RefCodeReview) | O20: =I20*(1+RefUnitTest+RefIntegrationTest+RefCodeReview) | P20: =(J20+4*K20+L20)/6 | Q20: =(M20+4*N20+O20)/6 | R20: =(L20-J20)/6 | S20: =R20^2 | T20: =(O20-M20)/6 | U20: =T20^2 | V20: No | W20: 0 | X20: 0 | Y20: Included | Z20: Implementation | AA20: M1
A21: UserStory | B21: US-1.6 | C21: Logout | D21: 2 | E21: 4 | F21: 8 | G21: 2 | H21: 4 | I21: 8 | J21: =D21*(1+RefUnitTest+RefIntegrationTest+RefCodeReview) | K21: =E21*(1+RefUnitTest+RefIntegrationTest+RefCodeReview) | L21: =F21*(1+RefUnitTest+RefIntegrationTest+RefCodeReview) | M21: =G21*(1+RefUnitTest+RefIntegrationTest+RefCodeReview) | N21: =H21*(1+RefUnitTest+RefIntegrationTest+RefCodeReview) | O21: =I21*(1+RefUnitTest+RefIntegrationTest+RefCodeReview) | P21: =(J21+4*K21+L21)/6 | Q21: =(M21+4*N21+O21)/6 | R21: =(L21-J21)/6 | S21: =R21^2 | T21: =(O21-M21)/6 | U21: =T21^2 | V21: No | W21: 0 | X21: 0 | Y21: Included | Z21: Implementation | AA21: M1
A22: UserStory | B22: US-1.7 | C22: 2FA setup | D22: 16 | E22: 32 | F22: 48 | G22: 8 | H22: 16 | I22: 24 | J22: =D22*(1+RefUnitTest+RefIntegrationTest+RefCodeReview) | K22: =E22*(1+RefUnitTest+RefIntegrationTest+RefCodeReview) | L22: =F22*(1+RefUnitTest+RefIntegrationTest+RefCodeReview) | M22: =G22*(1+RefUnitTest+RefIntegrationTest+RefCodeReview) | N22: =H22*(1+RefUnitTest+RefIntegrationTest+RefCodeReview) | O22: =I22*(1+RefUnitTest+RefIntegrationTest+RefCodeReview) | P22: =(J22+4*K22+L22)/6 | Q22: =(M22+4*N22+O22)/6 | R22: =(L22-J22)/6 | S22: =R22^2 | T22: =(O22-M22)/6 | U22: =T22^2 | V22: No | W22: 0 | X22: 0 | Y22: Included | Z22: Implementation | AA22: M2 | AB22: TOTP via authenticator + SMS fallback
A23: Epic | B23: E-2 | C23: Profile Management
A24: UserStory | B24: US-2.1 | C24: View profile info | D24: 4 | E24: 8 | F24: 16 | G24: 4 | H24: 8 | I24: 12 | J24: =D24*(1+RefUnitTest+RefIntegrationTest+RefCodeReview) | K24: =E24*(1+RefUnitTest+RefIntegrationTest+RefCodeReview) | L24: =F24*(1+RefUnitTest+RefIntegrationTest+RefCodeReview) | M24: =G24*(1+RefUnitTest+RefIntegrationTest+RefCodeReview) | N24: =H24*(1+RefUnitTest+RefIntegrationTest+RefCodeReview) | O24: =I24*(1+RefUnitTest+RefIntegrationTest+RefCodeReview) | P24: =(J24+4*K24+L24)/6 | Q24: =(M24+4*N24+O24)/6 | R24: =(L24-J24)/6 | S24: =R24^2 | T24: =(O24-M24)/6 | U24: =T24^2 | V24: No | W24: 0 | X24: 0 | Y24: Included | Z24: Implementation | AA24: M1
A25: UserStory | B25: US-2.2 | C25: Edit personal details | D25: 8 | E25: 16 | F25: 24 | G25: 12 | H25: 20 | I25: 32 | J25: =D25*(1+RefUnitTest+RefIntegrationTest+RefCodeReview) | K25: =E25*(1+RefUnitTest+RefIntegrationTest+RefCodeReview) | L25: =F25*(1+RefUnitTest+RefIntegrationTest+RefCodeReview) | M25: =G25*(1+RefUnitTest+RefIntegrationTest+RefCodeReview) | N25: =H25*(1+RefUnitTest+RefIntegrationTest+RefCodeReview) | O25: =I25*(1+RefUnitTest+RefIntegrationTest+RefCodeReview) | P25: =(J25+4*K25+L25)/6 | Q25: =(M25+4*N25+O25)/6 | R25: =(L25-J25)/6 | S25: =R25^2 | T25: =(O25-M25)/6 | U25: =T25^2 | V25: No | W25: 0 | X25: 0 | Y25: Included | Z25: Implementation | AA25: M1
A26: UserStory | B26: US-2.3 | C26: Change password | D26: 4 | E26: 8 | F26: 16 | G26: 4 | H26: 8 | I26: 12 | J26: =D26*(1+RefUnitTest+RefIntegrationTest+RefCodeReview) | K26: =E26*(1+RefUnitTest+RefIntegrationTest+RefCodeReview) | L26: =F26*(1+RefUnitTest+RefIntegrationTest+RefCodeReview) | M26: =G26*(1+RefUnitTest+RefIntegrationTest+RefCodeReview) | N26: =H26*(1+RefUnitTest+RefIntegrationTest+RefCodeReview) | O26: =I26*(1+RefUnitTest+RefIntegrationTest+RefCodeReview) | P26: =(J26+4*K26+L26)/6 | Q26: =(M26+4*N26+O26)/6 | R26: =(L26-J26)/6 | S26: =R26^2 | T26: =(O26-M26)/6 | U26: =T26^2 | V26: No | W26: 0 | X26: 0 | Y26: Included | Z26: Implementation | AA26: M1
A27: UserStory | B27: US-2.4 | C27: Manage notification preferences | D27: 8 | E27: 16 | F27: 24 | G27: 4 | H27: 8 | I27: 12 | J27: =D27*(1+RefUnitTest+RefIntegrationTest+RefCodeReview) | K27: =E27*(1+RefUnitTest+RefIntegrationTest+RefCodeReview) | L27: =F27*(1+RefUnitTest+RefIntegrationTest+RefCodeReview) | M27: =G27*(1+RefUnitTest+RefIntegrationTest+RefCodeReview) | N27: =H27*(1+RefUnitTest+RefIntegrationTest+RefCodeReview) | O27: =I27*(1+RefUnitTest+RefIntegrationTest+RefCodeReview) | P27: =(J27+4*K27+L27)/6 | Q27: =(M27+4*N27+O27)/6 | R27: =(L27-J27)/6 | S27: =R27^2 | T27: =(O27-M27)/6 | U27: =T27^2 | V27: No | W27: 0 | X27: 0 | Y27: Included | Z27: Implementation | AA27: M2
A28: UserStory | B28: US-2.5 | C28: Delete account | D28: 8 | E28: 16 | F28: 24 | G28: 4 | H28: 8 | I28: 12 | J28: =D28*(1+RefUnitTest+RefIntegrationTest+RefCodeReview) | K28: =E28*(1+RefUnitTest+RefIntegrationTest+RefCodeReview) | L28: =F28*(1+RefUnitTest+RefIntegrationTest+RefCodeReview) | M28: =G28*(1+RefUnitTest+RefIntegrationTest+RefCodeReview) | N28: =H28*(1+RefUnitTest+RefIntegrationTest+RefCodeReview) | O28: =I28*(1+RefUnitTest+RefIntegrationTest+RefCodeReview) | P28: =(J28+4*K28+L28)/6 | Q28: =(M28+4*N28+O28)/6 | R28: =(L28-J28)/6 | S28: =R28^2 | T28: =(O28-M28)/6 | U28: =T28^2 | V28: No | W28: 0 | X28: 0 | Y28: Included | Z28: Implementation | AA28: M2
A29: Epic | B29: E-3 | C29: Wallet (sample regulated/financial epic)
A30: UserStory | B30: US-3.1 | C30: Setup wallet | D30: 16 | E30: 24 | F30: 40 | G30: 24 | H30: 40 | I30: 60 | J30: =D30*(1+RefUnitTest+RefIntegrationTest+RefCodeReview) | K30: =E30*(1+RefUnitTest+RefIntegrationTest+RefCodeReview) | L30: =F30*(1+RefUnitTest+RefIntegrationTest+RefCodeReview) | M30: =G30*(1+RefUnitTest+RefIntegrationTest+RefCodeReview) | N30: =H30*(1+RefUnitTest+RefIntegrationTest+RefCodeReview) | O30: =I30*(1+RefUnitTest+RefIntegrationTest+RefCodeReview) | P30: =(J30+4*K30+L30)/6 | Q30: =(M30+4*N30+O30)/6 | R30: =(L30-J30)/6 | S30: =R30^2 | T30: =(O30-M30)/6 | U30: =T30^2 | V30: No | W30: 0 | X30: 0 | Y30: Included | Z30: Implementation | AA30: M2 | AB30: custodial wallet, KMS-backed
A31: UserStory | B31: US-3.2 | C31: Buy tokens | D31: 16 | E31: 24 | F31: 40 | G31: 12 | H31: 20 | I31: 32 | J31: =D31*(1+RefUnitTest+RefIntegrationTest+RefCodeReview) | K31: =E31*(1+RefUnitTest+RefIntegrationTest+RefCodeReview) | L31: =F31*(1+RefUnitTest+RefIntegrationTest+RefCodeReview) | M31: =G31*(1+RefUnitTest+RefIntegrationTest+RefCodeReview) | N31: =H31*(1+RefUnitTest+RefIntegrationTest+RefCodeReview) | O31: =I31*(1+RefUnitTest+RefIntegrationTest+RefCodeReview) | P31: =(J31+4*K31+L31)/6 | Q31: =(M31+4*N31+O31)/6 | R31: =(L31-J31)/6 | S31: =R31^2 | T31: =(O31-M31)/6 | U31: =T31^2 | V31: No | W31: 0 | X31: 0 | Y31: Included | Z31: Implementation | AA31: M2 | AB31: Stripe + crypto on-ramp
A32: UserStory | B32: US-3.3 | C32: Sell tokens | D32: 16 | E32: 24 | F32: 40 | G32: 8 | H32: 12 | I32: 24 | J32: =D32*(1+RefUnitTest+RefIntegrationTest+RefCodeReview) | K32: =E32*(1+RefUnitTest+RefIntegrationTest+RefCodeReview) | L32: =F32*(1+RefUnitTest+RefIntegrationTest+RefCodeReview) | M32: =G32*(1+RefUnitTest+RefIntegrationTest+RefCodeReview) | N32: =H32*(1+RefUnitTest+RefIntegrationTest+RefCodeReview) | O32: =I32*(1+RefUnitTest+RefIntegrationTest+RefCodeReview) | P32: =(J32+4*K32+L32)/6 | Q32: =(M32+4*N32+O32)/6 | R32: =(L32-J32)/6 | S32: =R32^2 | T32: =(O32-M32)/6 | U32: =T32^2 | V32: No | W32: 0 | X32: 0 | Y32: Included | Z32: Implementation | AA32: M3
A33: UserStory | B33: US-3.4 | C33: View transactions | D33: 12 | E33: 20 | F33: 32 | G33: 12 | H33: 16 | I33: 24 | J33: =D33*(1+RefUnitTest+RefIntegrationTest+RefCodeReview) | K33: =E33*(1+RefUnitTest+RefIntegrationTest+RefCodeReview) | L33: =F33*(1+RefUnitTest+RefIntegrationTest+RefCodeReview) | M33: =G33*(1+RefUnitTest+RefIntegrationTest+RefCodeReview) | N33: =H33*(1+RefUnitTest+RefIntegrationTest+RefCodeReview) | O33: =I33*(1+RefUnitTest+RefIntegrationTest+RefCodeReview) | P33: =(J33+4*K33+L33)/6 | Q33: =(M33+4*N33+O33)/6 | R33: =(L33-J33)/6 | S33: =R33^2 | T33: =(O33-M33)/6 | U33: =T33^2 | V33: No | W33: 0 | X33: 0 | Y33: Included | Z33: Implementation | AA33: M2
A34: UserStory | B34: US-3.5 | C34: KYC initiate / upload ID / verify | D34: 16 | E34: 32 | F34: 64 | G34: 8 | H34: 16 | I34: 24 | J34: =D34*(1+RefUnitTest+RefIntegrationTest+RefCodeReview) | K34: =E34*(1+RefUnitTest+RefIntegrationTest+RefCodeReview) | L34: =F34*(1+RefUnitTest+RefIntegrationTest+RefCodeReview) | M34: =G34*(1+RefUnitTest+RefIntegrationTest+RefCodeReview) | N34: =H34*(1+RefUnitTest+RefIntegrationTest+RefCodeReview) | O34: =I34*(1+RefUnitTest+RefIntegrationTest+RefCodeReview) | P34: =(J34+4*K34+L34)/6 | Q34: =(M34+4*N34+O34)/6 | R34: =(L34-J34)/6 | S34: =R34^2 | T34: =(O34-M34)/6 | U34: =T34^2 | V34: No | W34: 0 | X34: 0 | Y34: Included | Z34: Implementation | AA34: M3 | AB34: 3rd-party KYC vendor (Onfido/SumSub)

Sheet BA Estimation
A1: Business Analysis Estimation
A2: Purpose: | B2: Catalogue of BA deliverables (Vision & Scope, USM, RACI, BPMN, Class diagrams, prototypes, benchmarking, ...) with PERT estimates per item. Replaces the v1.4 assumption that BA effort equals 0.25 FTE.
A3: How to use: | B3: (1) Walk down the catalogue. (2) Set O/ML/P for items you'll deliver, leave others at 0. (3) Set Include = Not included for items the client did not buy (they stay in the catalogue but excluded from totals). (4) Use Apply Contingency = Yes on items with vague requirements (typical 20% default). (5) Mark Phase = Discovery / Implementation / Post-MVP / Maintenance.
A4: Inputs: | B4: O/ML/P per row, Apply Contingency Y/N, Include, Phase, Deliverable, Description, Assumptions, Notes.
A5: Outputs: | B5: Final Expected per row. Included sum (col I where Include=Included) flows to Buffers & Non-Dev Activities and from there to Headcount and Cost as the BA estimated hours.
A6: Linked tabs: | B6: Buffers & Non-Dev Activities (BA roll-up). Headcount and Cost (BA estimated hours).
A7: Default contingency: | B7: 0.2 | C7: (used when Apply Contingency = Yes; multiplied by Most Likely)
A8: Per-line PERT estimate for BA deliverables. Default contingency 20% applied when Apply Contingency = Yes.
A10: ID | B10: Service / Activity | C10: Optimistic | D10: Most Likely | E10: Pessimistic | F10: Expected | G10: Apply Contingency | H10: Contingency | I10: Final Expected | J10: Include | K10: Project Phase | L10: Deliverable | M10: Description / Scope | N10: Assumptions | O10: Notes
B11: TOTALS | C11: =SUM(C12:C29) | D11: =SUM(D12:D29) | E11: =SUM(E12:E29) | F11: =SUM(F12:F29) | H11: =SUM(H12:H29) | I11: =SUMIF(J12:J29,"Included",I12:I29) | J11: (only Included counted at right)
A12: BA-1 | B12: Discovery deliverables
A13: BA-1.1 | B13: Vision & Scope document | C13: 8 | D13: 16 | E13: 24 | F13: =IF(AND(C13<>"",D13<>"",E13<>""),(C13+4*D13+E13)/6,0) | G13: Yes | H13: =IF(G13="Yes",ROUND(D13*$B$7,1),0) | I13: =F13+H13 | J13: Included | K13: Discovery | L13: Vision & Scope doc | M13: Background, Business Opportunity, Objectives, Risks, Vision Statement, Major Features, Assumptions, Stakeholder Profiles, Operating Environment, Glossary
A14: BA-1.2 | B14: User Story Map (USM) | C14: 16 | D14: 32 | E14: 48 | F14: =IF(AND(C14<>"",D14<>"",E14<>""),(C14+4*D14+E14)/6,0) | G14: Yes | H14: =IF(G14="Yes",ROUND(D14*$B$7,1),0) | I14: =F14+H14 | J14: Included | K14: Discovery | L14: USM | M14: Visualization of the product backbone across user journey
A15: BA-1.3 | B15: Roles & Permissions Matrix | C15: 8 | D15: 12 | E15: 20 | F15: =IF(AND(C15<>"",D15<>"",E15<>""),(C15+4*D15+E15)/6,0) | G15: Yes | H15: =IF(G15="Yes",ROUND(D15*$B$7,1),0) | I15: =F15+H15 | J15: Included | K15: Discovery | L15: RBAC matrix | M15: Roles, role-related features, permission grid
A16: BA-1.4 | B16: WBS / Feature list adjustment | C16: 4 | D16: 8 | E16: 16 | F16: =IF(AND(C16<>"",D16<>"",E16<>""),(C16+4*D16+E16)/6,0) | G16: No | H16: =IF(G16="Yes",ROUND(D16*$B$7,1),0) | I16: =F16+H16 | J16: Included | K16: Discovery | L16: MVP / Post-MVP feature list
A17: BA-1.5 | B17: Initial Sprint Backlog | C17: 16 | D17: 24 | E17: 40 | F17: =IF(AND(C17<>"",D17<>"",E17<>""),(C17+4*D17+E17)/6,0) | G17: Yes | H17: =IF(G17="Yes",ROUND(D17*$B$7,1),0) | I17: =F17+H17 | J17: Included | K17: Discovery | L17: Initial Backlog | M17: Prioritized, DoR-ready USs for first sprints
A18: BA-1.6 | B18: BPMN diagrams (key processes) | C18: 16 | D18: 32 | E18: 48 | F18: =IF(AND(C18<>"",D18<>"",E18<>""),(C18+4*D18+E18)/6,0) | G18: Yes | H18: =IF(G18="Yes",ROUND(D18*$B$7,1),0) | I18: =F18+H18 | J18: Included | K18: Discovery | L18: BPMN diagrams
A19: BA-1.7 | B19: Interactive prototypes (key flows) | C19: 16 | D19: 24 | E19: 40 | F19: =IF(AND(C19<>"",D19<>"",E19<>""),(C19+4*D19+E19)/6,0) | G19: No | H19: =IF(G19="Yes",ROUND(D19*$B$7,1),0) | I19: =F19+H19 | J19: Not included | K19: Discovery | L19: Figma prototypes | M19: Coordinated with UI/UX tab
A20: BA-1.8 | B20: Context Diagram | C20: 8 | D20: 12 | E20: 24 | F20: =IF(AND(C20<>"",D20<>"",E20<>""),(C20+4*D20+E20)/6,0) | G20: No | H20: =IF(G20="Yes",ROUND(D20*$B$7,1),0) | I20: =F20+H20 | J20: Included | K20: Discovery | L20: Context diagram
A21: BA-1.9 | B21: Class diagram (high level) | C21: 8 | D21: 12 | E21: 24 | F21: =IF(AND(C21<>"",D21<>"",E21<>""),(C21+4*D21+E21)/6,0) | G21: No | H21: =IF(G21="Yes",ROUND(D21*$B$7,1),0) | I21: =F21+H21 | J21: Included | K21: Discovery | L21: Class diagram
A22: BA-1.10 | B22: State machine diagram | C22: 8 | D22: 16 | E22: 32 | F22: =IF(AND(C22<>"",D22<>"",E22<>""),(C22+4*D22+E22)/6,0) | G22: No | H22: =IF(G22="Yes",ROUND(D22*$B$7,1),0) | I22: =F22+H22 | J22: Included | K22: Discovery | L22: State machine
A23: BA-1.11 | B23: Benchmarking / competitor analysis | C23: 16 | D23: 32 | E23: 48 | F23: =IF(AND(C23<>"",D23<>"",E23<>""),(C23+4*D23+E23)/6,0) | G23: No | H23: =IF(G23="Yes",ROUND(D23*$B$7,1),0) | I23: =F23+H23 | J23: Not included | K23: Discovery
A24: BA-1.12 | B24: Stakeholder Matrix / Glossary / Communication plan | C24: 4 | D24: 8 | E24: 12 | F24: =IF(AND(C24<>"",D24<>"",E24<>""),(C24+4*D24+E24)/6,0) | G24: No | H24: =IF(G24="Yes",ROUND(D24*$B$7,1),0) | I24: =F24+H24 | J24: Included | K24: Discovery
A25: BA-2 | B25: Implementation deliverables
A26: BA-2.1 | B26: Refining backlog (per sprint) | C26: 4 | D26: 8 | E26: 12 | F26: =IF(AND(C26<>"",D26<>"",E26<>""),(C26+4*D26+E26)/6,0) | G26: No | H26: =IF(G26="Yes",ROUND(D26*$B$7,1),0) | I26: =F26+H26 | J26: Included | K26: Implementation | L26: Refined backlog | M26: Per sprint over implementation duration
A27: BA-2.2 | B27: Acceptance criteria authoring | C27: 4 | D27: 8 | E27: 12 | F27: =IF(AND(C27<>"",D27<>"",E27<>""),(C27+4*D27+E27)/6,0) | G27: No | H27: =IF(G27="Yes",ROUND(D27*$B$7,1),0) | I27: =F27+H27 | J27: Included | K27: Implementation
A28: BA-2.3 | B28: Change request analysis | C28: 4 | D28: 8 | E28: 16 | F28: =IF(AND(C28<>"",D28<>"",E28<>""),(C28+4*D28+E28)/6,0) | G28: Yes | H28: =IF(G28="Yes",ROUND(D28*$B$7,1),0) | I28: =F28+H28 | J28: Included | K28: Implementation
A29: BA-2.4 | B29: Demo support / UAT support | C29: 4 | D29: 8 | E29: 16 | F29: =IF(AND(C29<>"",D29<>"",E29<>""),(C29+4*D29+E29)/6,0) | G29: No | H29: =IF(G29="Yes",ROUND(D29*$B$7,1),0) | I29: =F29+H29 | J29: Included | K29: Implementation

Sheet Arch Estimation
A1: Architecture Estimation (SA + Software A)
A2: Purpose: | B2: Catalogue of architecture deliverables — Architectural Drivers (AVD), Solution Architecture views (Context/Container/Component/Deployment), Decision/Risk records, Operation plan, Implementation roadmap. 30% contingency reflects design uncertainty.
A3: How to use: | B3: (1) Per item, set O/ML/P. (2) Items left empty stay in the catalogue as a checklist of what was considered but not estimated (mark Include = Not included). (3) Use Apply Contingency = Yes for items requiring discovery workshops or third-party APIs. (4) Compliance items (OWASP, GDPR, PCI-DSS, HIPAA, SoX) are off by default — switch on if applicable.
A4: Inputs: | B4: O/ML/P per row, Apply Contingency Y/N, Include, Phase, Deliverable, Description, Assumptions.
A5: Outputs: | B5: Architecture roll-up flows to Buffers tab and then Headcount and Cost as 'Architecture (SA+SwA)' estimated hours.
A6: Linked tabs: | B6: Buffers & Non-Dev Activities (Architecture roll-up). Headcount and Cost.
A7: Default contingency: | B7: 0.3 | C7: (used when Apply Contingency = Yes; multiplied by Most Likely)
A8: Solution & Software Architecture deliverables. Higher 30% contingency reflects design uncertainty.
A10: ID | B10: Service / Activity | C10: Optimistic | D10: Most Likely | E10: Pessimistic | F10: Expected | G10: Apply Contingency | H10: Contingency | I10: Final Expected | J10: Include | K10: Project Phase | L10: Deliverable | M10: Description / Scope | N10: Assumptions | O10: Notes
B11: TOTALS | C11: =SUM(C12:C46) | D11: =SUM(D12:D46) | E11: =SUM(E12:E46) | F11: =SUM(F12:F46) | H11: =SUM(H12:H46) | I11: =SUMIF(J12:J46,"Included",I12:I46) | J11: (only Included counted at right)
A12: ARC-1 | B12: Architectural Drivers (AVD)
A13: ARC-1.1 | B13: Business Goals | C13: 2 | D13: 2.5 | E13: 3 | F13: =IF(AND(C13<>"",D13<>"",E13<>""),(C13+4*D13+E13)/6,0) | G13: No | H13: =IF(G13="Yes",ROUND(D13*$B$7,1),0) | I13: =F13+H13 | J13: Included | K13: Discovery | L13: AVD: Business Goals
A14: ARC-1.2 | B14: Major Features | C14: 2 | D14: 2.5 | E14: 3 | F14: =IF(AND(C14<>"",D14<>"",E14<>""),(C14+4*D14+E14)/6,0) | G14: No | H14: =IF(G14="Yes",ROUND(D14*$B$7,1),0) | I14: =F14+H14 | J14: Included | K14: Discovery
A15: ARC-1.3 | B15: Design Constraints | C15: 2 | D15: 2.5 | E15: 3 | F15: =IF(AND(C15<>"",D15<>"",E15<>""),(C15+4*D15+E15)/6,0) | G15: No | H15: =IF(G15="Yes",ROUND(D15*$B$7,1),0) | I15: =F15+H15 | J15: Included | K15: Discovery
A16: ARC-1.4 | B16: Architectural Concerns | C16: 2 | D16: 2.5 | E16: 3 | F16: =IF(AND(C16<>"",D16<>"",E16<>""),(C16+4*D16+E16)/6,0) | G16: No | H16: =IF(G16="Yes",ROUND(D16*$B$7,1),0) | I16: =F16+H16 | J16: Included | K16: Discovery
A17: ARC-1.5 | B17: Quality Attributes (cross-cutting) | C17: 8 | D17: 10 | E17: 12 | F17: =IF(AND(C17<>"",D17<>"",E17<>""),(C17+4*D17+E17)/6,0) | G17: Yes | H17: =IF(G17="Yes",ROUND(D17*$B$7,1),0) | I17: =F17+H17 | J17: Included | K17: Discovery | M17: Availability, Performance, Observability, Scalability, Localization, Fault Tolerance, Recoverability, Security (App + Code), Extendability, Maintainability
A18: ARC-1.6 | B18: Compliance scope (OWASP/GDPR/PCI/HIPAA/SoX) | C18: 0 | D18: 0 | E18: 0 | F18: =IF(AND(C18<>"",D18<>"",E18<>""),(C18+4*D18+E18)/6,0) | G18: No | H18: =IF(G18="Yes",ROUND(D18*$B$7,1),0) | I18: =F18+H18 | J18: Not included | K18: Discovery | M18: Estimated separately per applicable regulation
A19: ARC-2 | B19: Solution Architecture
A20: ARC-2.1 | B20: System Context View | C20: 2 | D20: 4 | E20: 6 | F20: =IF(AND(C20<>"",D20<>"",E20<>""),(C20+4*D20+E20)/6,0) | G20: No | H20: =IF(G20="Yes",ROUND(D20*$B$7,1),0) | I20: =F20+H20 | J20: Included | K20: Discovery
A21: ARC-2.2 | B21: Container View | C21: 4 | D21: 6 | E21: 8 | F21: =IF(AND(C21<>"",D21<>"",E21<>""),(C21+4*D21+E21)/6,0) | G21: No | H21: =IF(G21="Yes",ROUND(D21*$B$7,1),0) | I21: =F21+H21 | J21: Included | K21: Discovery
A22: ARC-2.3 | B22: Component View — Front-end | C22: 1 | D22: 3 | E22: 4 | F22: =IF(AND(C22<>"",D22<>"",E22<>""),(C22+4*D22+E22)/6,0) | G22: No | H22: =IF(G22="Yes",ROUND(D22*$B$7,1),0) | I22: =F22+H22 | J22: Not included | K22: Discovery
A23: ARC-2.4 | B23: Component View — Back-end | C23: 3 | D23: 6 | E23: 8 | F23: =IF(AND(C23<>"",D23<>"",E23<>""),(C23+4*D23+E23)/6,0) | G23: Yes | H23: =IF(G23="Yes",ROUND(D23*$B$7,1),0) | I23: =F23+H23 | J23: Included | K23: Discovery
A24: ARC-2.5 | B24: Epic-level architectural design | C24: 16 | D24: 18 | E24: 20 | F24: =IF(AND(C24<>"",D24<>"",E24<>""),(C24+4*D24+E24)/6,0) | G24: Yes | H24: =IF(G24="Yes",ROUND(D24*$B$7,1),0) | I24: =F24+H24 | J24: Included | K24: Discovery
A25: ARC-2.6 | B25: Deployment View | C25: 4 | D25: 8 | E25: 10 | F25: =IF(AND(C25<>"",D25<>"",E25<>""),(C25+4*D25+E25)/6,0) | G25: Yes | H25: =IF(G25="Yes",ROUND(D25*$B$7,1),0) | I25: =F25+H25 | J25: Included | K25: Discovery
A26: ARC-2.7 | B26: Decision View / ADRs | C26: 4 | D26: 6 | E26: 8 | F26: =IF(AND(C26<>"",D26<>"",E26<>""),(C26+4*D26+E26)/6,0) | G26: No | H26: =IF(G26="Yes",ROUND(D26*$B$7,1),0) | I26: =F26+H26 | J26: Not included | K26: Discovery
A27: ARC-2.8 | B27: Risk View / Risk Record | C27: 4 | D27: 6 | E27: 8 | F27: =IF(AND(C27<>"",D27<>"",E27<>""),(C27+4*D27+E27)/6,0) | G27: No | H27: =IF(G27="Yes",ROUND(D27*$B$7,1),0) | I27: =F27+H27 | J27: Included | K27: Discovery
A28: ARC-3 | B28: Operation plan
A29: ARC-3.1 | B29: Infrastructure model | C29: 2 | D29: 5 | E29: 4 | F29: =IF(AND(C29<>"",D29<>"",E29<>""),(C29+4*D29+E29)/6,0) | G29: Yes | H29: =IF(G29="Yes",ROUND(D29*$B$7,1),0) | I29: =F29+H29 | J29: Included | K29: Discovery
A30: ARC-3.2 | B30: Continuous integration / continuous delivery | C30: 2 | D30: 5 | E30: 4 | F30: =IF(AND(C30<>"",D30<>"",E30<>""),(C30+4*D30+E30)/6,0) | G30: Yes | H30: =IF(G30="Yes",ROUND(D30*$B$7,1),0) | I30: =F30+H30 | J30: Included | K30: Discovery
A31: ARC-3.3 | B31: Monitoring / Observability | C31: 2 | D31: 5 | E31: 4 | F31: =IF(AND(C31<>"",D31<>"",E31<>""),(C31+4*D31+E31)/6,0) | G31: Yes | H31: =IF(G31="Yes",ROUND(D31*$B$7,1),0) | I31: =F31+H31 | J31: Included | K31: Discovery
A32: ARC-3.4 | B32: Secure SDLC concepts | C32: 2 | D32: 5 | E32: 4 | F32: =IF(AND(C32<>"",D32<>"",E32<>""),(C32+4*D32+E32)/6,0) | G32: No | H32: =IF(G32="Yes",ROUND(D32*$B$7,1),0) | I32: =F32+H32 | J32: Included | K32: Discovery
A33: ARC-3.5 | B33: Backup & restore | C33: 2 | D33: 5 | E33: 4 | F33: =IF(AND(C33<>"",D33<>"",E33<>""),(C33+4*D33+E33)/6,0) | G33: No | H33: =IF(G33="Yes",ROUND(D33*$B$7,1),0) | I33: =F33+H33 | J33: Included | K33: Discovery
A34: ARC-4 | B34: Implementation Roadmap
A35: ARC-4.1 | B35: Implementation Milestones | C35: 2 | D35: 3 | E35: 4 | F35: =IF(AND(C35<>"",D35<>"",E35<>""),(C35+4*D35+E35)/6,0) | G35: No | H35: =IF(G35="Yes",ROUND(D35*$B$7,1),0) | I35: =F35+H35 | J35: Included | K35: Discovery
A36: ARC-4.2 | B36: Development technology stack | C36: 1 | D36: 1.5 | E36: 2 | F36: =IF(AND(C36<>"",D36<>"",E36<>""),(C36+4*D36+E36)/6,0) | G36: No | H36: =IF(G36="Yes",ROUND(D36*$B$7,1),0) | I36: =F36+H36 | J36: Included | K36: Discovery
A37: ARC-4.3 | B37: Estimation: structure & validation | C37: 8 | D37: 11 | E37: 10 | F37: =IF(AND(C37<>"",D37<>"",E37<>""),(C37+4*D37+E37)/6,0) | G37: No | H37: =IF(G37="Yes",ROUND(D37*$B$7,1),0) | I37: =F37+H37 | J37: Included | K37: Discovery
A38: ARC-4.4 | B38: Development team skillset | C38: 1 | D38: 1.5 | E38: 2 | F38: =IF(AND(C38<>"",D38<>"",E38<>""),(C38+4*D38+E38)/6,0) | G38: No | H38: =IF(G38="Yes",ROUND(D38*$B$7,1),0) | I38: =F38+H38 | J38: Included | K38: Discovery
A39: ARC-5 | B39: Discovery workshops
A40: ARC-5.1 | B40: Discovery questions preparation | C40: 8 | D40: 12 | E40: 16 | F40: =IF(AND(C40<>"",D40<>"",E40<>""),(C40+4*D40+E40)/6,0) | G40: Yes | H40: =IF(G40="Yes",ROUND(D40*$B$7,1),0) | I40: =F40+H40 | J40: Included | K40: Discovery
A41: ARC-5.2 | B41: AVD draft / 1st review | C41: 8 | D41: 12 | E41: 16 | F41: =IF(AND(C41<>"",D41<>"",E41<>""),(C41+4*D41+E41)/6,0) | G41: No | H41: =IF(G41="Yes",ROUND(D41*$B$7,1),0) | I41: =F41+H41 | J41: Included | K41: Discovery
A42: ARC-5.3 | B42: Internal peer review | C42: 4 | D42: 6 | E42: 8 | F42: =IF(AND(C42<>"",D42<>"",E42<>""),(C42+4*D42+E42)/6,0) | G42: No | H42: =IF(G42="Yes",ROUND(D42*$B$7,1),0) | I42: =F42+H42 | J42: Included | K42: Discovery
A43: ARC-6 | B43: Implementation phase support
A44: ARC-6.1 | B44: Architecture governance & ADRs | C44: 8 | D44: 16 | E44: 24 | F44: =IF(AND(C44<>"",D44<>"",E44<>""),(C44+4*D44+E44)/6,0) | G44: No | H44: =IF(G44="Yes",ROUND(D44*$B$7,1),0) | I44: =F44+H44 | J44: Included | K44: Implementation
A45: ARC-6.2 | B45: Tech debt review / risks reassessment | C45: 4 | D45: 8 | E45: 16 | F45: =IF(AND(C45<>"",D45<>"",E45<>""),(C45+4*D45+E45)/6,0) | G45: No | H45: =IF(G45="Yes",ROUND(D45*$B$7,1),0) | I45: =F45+H45 | J45: Included | K45: Implementation
A46: ARC-6.3 | B46: Sprint architecture support | C46: 4 | D46: 8 | E46: 12 | F46: =IF(AND(C46<>"",D46<>"",E46<>""),(C46+4*D46+E46)/6,0) | G46: No | H46: =IF(G46="Yes",ROUND(D46*$B$7,1),0) | I46: =F46+H46 | J46: Included | K46: Implementation

Sheet QA Estimation
A1: QA Estimation (per stream)
A2: Purpose: | B2: Defensible QA WBS split by stream: Front-end / Back-end / Mobile / Automation. Each stream covers System Config, Test Env, Strategy, Test Data, Test Case Design, Functional, Non-functional, Database, Change-related (Smoke/Regression), Test Closure.
A3: How to use: | B3: (1) Per stream, fill O/ML/P for activities relevant to your project. (2) Disable streams that don't apply by setting Include = Not included on every row of that stream. (3) Automation block defaults to Post-MVP — switch to Included if AQA is in scope for build. (4) The Buffers tab pulls the QA Estimation Included sum and uses it instead of the 15% MQA coefficient when populated; otherwise it falls back to the coefficient-based MQA/AQA derivation.
A4: Inputs: | B4: O/ML/P per row, Apply Contingency Y/N, Include, Phase, Deliverable, Description.
A5: Outputs: | B5: QA roll-up (per-stream and total). Feeds Buffers tab QA row.
A6: Linked tabs: | B6: Buffers & Non-Dev Activities (QA from this tab vs MQA/AQA coefficient). Headcount and Cost (Manual QA / AQA estimated hours).
A7: Default contingency: | B7: 0.15 | C7: (used when Apply Contingency = Yes; multiplied by Most Likely)
A8: Streams: FE / BE / Mobile / Automation. Use this tab for a defensible per-stream QA WBS in addition to (or in place of) the flat 15% coefficient from v1.4.
A10: ID | B10: Service / Activity | C10: Optimistic | D10: Most Likely | E10: Pessimistic | F10: Expected | G10: Apply Contingency | H10: Contingency | I10: Final Expected | J10: Include | K10: Project Phase | L10: Deliverable | M10: Description / Scope | N10: Assumptions | O10: Notes
B11: TOTALS | C11: =SUM(C12:C49) | D11: =SUM(D12:D49) | E11: =SUM(E12:E49) | F11: =SUM(F12:F49) | H11: =SUM(H12:H49) | I11: =SUMIF(J12:J49,"Included",I12:I49) | J11: (only Included counted at right)
A12: QA-FE | B12: QA — Front-end stream
A13: QA-FE.1 | B13: System Configuration | C13: 5 | D13: 6 | E13: 7 | F13: =IF(AND(C13<>"",D13<>"",E13<>""),(C13+4*D13+E13)/6,0) | G13: No | H13: =IF(G13="Yes",ROUND(D13*$B$7,1),0) | I13: =F13+H13 | J13: Included | K13: Discovery | L13: Task / bug-tracking config
A14: QA-FE.2 | B14: Test Environment Setup | C14: 6 | D14: 8 | E14: 12 | F14: =IF(AND(C14<>"",D14<>"",E14<>""),(C14+4*D14+E14)/6,0) | G14: No | H14: =IF(G14="Yes",ROUND(D14*$B$7,1),0) | I14: =F14+H14 | J14: Included | K14: Discovery
A15: QA-FE.3 | B15: Test Strategy & Test Plan | C15: 10 | D15: 14 | E15: 18 | F15: =IF(AND(C15<>"",D15<>"",E15<>""),(C15+4*D15+E15)/6,0) | G15: Yes | H15: =IF(G15="Yes",ROUND(D15*$B$7,1),0) | I15: =F15+H15 | J15: Included | K15: Discovery | L15: Test Strategy + Test Plan
A16: QA-FE.4 | B16: Documentation Investigation | C16: 50 | D16: 60 | E16: 70 | F16: =IF(AND(C16<>"",D16<>"",E16<>""),(C16+4*D16+E16)/6,0) | G16: No | H16: =IF(G16="Yes",ROUND(D16*$B$7,1),0) | I16: =F16+H16 | J16: Included | K16: Implementation
A17: QA-FE.5 | B17: Test Data preparation | C17: 70 | D17: 90 | E17: 120 | F17: =IF(AND(C17<>"",D17<>"",E17<>""),(C17+4*D17+E17)/6,0) | G17: No | H17: =IF(G17="Yes",ROUND(D17*$B$7,1),0) | I17: =F17+H17 | J17: Included | K17: Implementation
A18: QA-FE.6 | B18: Test Case design | C18: 110 | D18: 140 | E18: 170 | F18: =IF(AND(C18<>"",D18<>"",E18<>""),(C18+4*D18+E18)/6,0) | G18: No | H18: =IF(G18="Yes",ROUND(D18*$B$7,1),0) | I18: =F18+H18 | J18: Included | K18: Implementation
A19: QA-FE.7 | B19: Functional Testing (E2E) | C19: 90 | D19: 120 | E19: 140 | F19: =IF(AND(C19<>"",D19<>"",E19<>""),(C19+4*D19+E19)/6,0) | G19: Yes | H19: =IF(G19="Yes",ROUND(D19*$B$7,1),0) | I19: =F19+H19 | J19: Included | K19: Implementation
A20: QA-FE.8 | B20: Non-functional Testing (UI/UX, Docs) | C20: 120 | D20: 130 | E20: 160 | F20: =IF(AND(C20<>"",D20<>"",E20<>""),(C20+4*D20+E20)/6,0) | G20: No | H20: =IF(G20="Yes",ROUND(D20*$B$7,1),0) | I20: =F20+H20 | J20: Included | K20: Implementation
A21: QA-FE.9 | B21: Change-related (Smoke/Regression/Critical Path) | C21: 110 | D21: 140 | E21: 160 | F21: =IF(AND(C21<>"",D21<>"",E21<>""),(C21+4*D21+E21)/6,0) | G21: Yes | H21: =IF(G21="Yes",ROUND(D21*$B$7,1),0) | I21: =F21+H21 | J21: Included | K21: Implementation
A22: QA-FE.10 | B22: Test Closure | C22: 40 | D22: 50 | E22: 65 | F22: =IF(AND(C22<>"",D22<>"",E22<>""),(C22+4*D22+E22)/6,0) | G22: No | H22: =IF(G22="Yes",ROUND(D22*$B$7,1),0) | I22: =F22+H22 | J22: Included | K22: Implementation
A23: QA-BE | B23: QA — Back-end stream
A24: QA-BE.1 | B24: System Configuration | C24: 8 | D24: 14 | E24: 16 | F24: =IF(AND(C24<>"",D24<>"",E24<>""),(C24+4*D24+E24)/6,0) | G24: No | H24: =IF(G24="Yes",ROUND(D24*$B$7,1),0) | I24: =F24+H24 | J24: Not included | K24: Discovery
A25: QA-BE.2 | B25: Test Environment Setup | C25: 8 | D25: 14 | E25: 16 | F25: =IF(AND(C25<>"",D25<>"",E25<>""),(C25+4*D25+E25)/6,0) | G25: No | H25: =IF(G25="Yes",ROUND(D25*$B$7,1),0) | I25: =F25+H25 | J25: Not included | K25: Discovery
A26: QA-BE.3 | B26: Database (data integrity, migrations) | C26: 8 | D26: 12 | E26: 14 | F26: =IF(AND(C26<>"",D26<>"",E26<>""),(C26+4*D26+E26)/6,0) | G26: No | H26: =IF(G26="Yes",ROUND(D26*$B$7,1),0) | I26: =F26+H26 | J26: Not included | K26: Discovery
A27: QA-BE.4 | B27: Documentation Investigation | C27: 160 | D27: 180 | E27: 190 | F27: =IF(AND(C27<>"",D27<>"",E27<>""),(C27+4*D27+E27)/6,0) | G27: No | H27: =IF(G27="Yes",ROUND(D27*$B$7,1),0) | I27: =F27+H27 | J27: Included | K27: Implementation
A28: QA-BE.5 | B28: Test Data preparation | C28: 140 | D28: 170 | E28: 180 | F28: =IF(AND(C28<>"",D28<>"",E28<>""),(C28+4*D28+E28)/6,0) | G28: No | H28: =IF(G28="Yes",ROUND(D28*$B$7,1),0) | I28: =F28+H28 | J28: Included | K28: Implementation
A29: QA-BE.6 | B29: Test Case design | C29: 270 | D29: 290 | E29: 330 | F29: =IF(AND(C29<>"",D29<>"",E29<>""),(C29+4*D29+E29)/6,0) | G29: No | H29: =IF(G29="Yes",ROUND(D29*$B$7,1),0) | I29: =F29+H29 | J29: Included | K29: Implementation
A30: QA-BE.7 | B30: Database Testing | C30: 190 | D30: 230 | E30: 250 | F30: =IF(AND(C30<>"",D30<>"",E30<>""),(C30+4*D30+E30)/6,0) | G30: No | H30: =IF(G30="Yes",ROUND(D30*$B$7,1),0) | I30: =F30+H30 | J30: Included | K30: Implementation
A31: QA-BE.8 | B31: Functional Testing (Integration / API) | C31: 280 | D31: 300 | E31: 320 | F31: =IF(AND(C31<>"",D31<>"",E31<>""),(C31+4*D31+E31)/6,0) | G31: Yes | H31: =IF(G31="Yes",ROUND(D31*$B$7,1),0) | I31: =F31+H31 | J31: Included | K31: Implementation
A32: QA-BE.9 | B32: Non-functional Testing (Docs) | C32: 200 | D32: 240 | E32: 260 | F32: =IF(AND(C32<>"",D32<>"",E32<>""),(C32+4*D32+E32)/6,0) | G32: No | H32: =IF(G32="Yes",ROUND(D32*$B$7,1),0) | I32: =F32+H32 | J32: Included | K32: Implementation
A33: QA-BE.10 | B33: Change-related (Smoke/Regression) | C33: 280 | D33: 320 | E33: 350 | F33: =IF(AND(C33<>"",D33<>"",E33<>""),(C33+4*D33+E33)/6,0) | G33: Yes | H33: =IF(G33="Yes",ROUND(D33*$B$7,1),0) | I33: =F33+H33 | J33: Included | K33: Implementation
A34: QA-BE.11 | B34: Test Closure | C34: 110 | D34: 120 | E34: 140 | F34: =IF(AND(C34<>"",D34<>"",E34<>""),(C34+4*D34+E34)/6,0) | G34: No | H34: =IF(G34="Yes",ROUND(D34*$B$7,1),0) | I34: =F34+H34 | J34: Included | K34: Implementation
A35: QA-MOB | B35: QA — Mobile stream
A36: QA-M.1 | B36: System Configuration | C36: 8 | D36: 14 | E36: 18 | F36: =IF(AND(C36<>"",D36<>"",E36<>""),(C36+4*D36+E36)/6,0) | G36: No | H36: =IF(G36="Yes",ROUND(D36*$B$7,1),0) | I36: =F36+H36 | J36: Not included | K36: Discovery
A37: QA-M.2 | B37: Test Environment Setup | C37: 6 | D37: 8 | E37: 10 | F37: =IF(AND(C37<>"",D37<>"",E37<>""),(C37+4*D37+E37)/6,0) | G37: No | H37: =IF(G37="Yes",ROUND(D37*$B$7,1),0) | I37: =F37+H37 | J37: Not included | K37: Discovery
A38: QA-M.3 | B38: Documentation Investigation | C38: 70 | D38: 90 | E38: 110 | F38: =IF(AND(C38<>"",D38<>"",E38<>""),(C38+4*D38+E38)/6,0) | G38: No | H38: =IF(G38="Yes",ROUND(D38*$B$7,1),0) | I38: =F38+H38 | J38: Included | K38: Implementation
A39: QA-M.4 | B39: Test Data | C39: 50 | D39: 60 | E39: 90 | F39: =IF(AND(C39<>"",D39<>"",E39<>""),(C39+4*D39+E39)/6,0) | G39: No | H39: =IF(G39="Yes",ROUND(D39*$B$7,1),0) | I39: =F39+H39 | J39: Included | K39: Implementation
A40: QA-M.5 | B40: Test Case design | C40: 180 | D40: 210 | E40: 230 | F40: =IF(AND(C40<>"",D40<>"",E40<>""),(C40+4*D40+E40)/6,0) | G40: No | H40: =IF(G40="Yes",ROUND(D40*$B$7,1),0) | I40: =F40+H40 | J40: Included | K40: Implementation
A41: QA-M.6 | B41: Functional Testing | C41: 150 | D41: 180 | E41: 220 | F41: =IF(AND(C41<>"",D41<>"",E41<>""),(C41+4*D41+E41)/6,0) | G41: Yes | H41: =IF(G41="Yes",ROUND(D41*$B$7,1),0) | I41: =F41+H41 | J41: Included | K41: Implementation
A42: QA-M.7 | B42: Non-functional Testing (devices, OS, install) | C42: 80 | D42: 100 | E42: 130 | F42: =IF(AND(C42<>"",D42<>"",E42<>""),(C42+4*D42+E42)/6,0) | G42: No | H42: =IF(G42="Yes",ROUND(D42*$B$7,1),0) | I42: =F42+H42 | J42: Included | K42: Implementation
A43: QA-M.8 | B43: Change-related (Smoke/Regression) | C43: 230 | D43: 260 | E43: 290 | F43: =IF(AND(C43<>"",D43<>"",E43<>""),(C43+4*D43+E43)/6,0) | G43: Yes | H43: =IF(G43="Yes",ROUND(D43*$B$7,1),0) | I43: =F43+H43 | J43: Included | K43: Implementation
A44: QA-M.9 | B44: Test Closure | C44: 60 | D44: 75 | E44: 90 | F44: =IF(AND(C44<>"",D44<>"",E44<>""),(C44+4*D44+E44)/6,0) | G44: No | H44: =IF(G44="Yes",ROUND(D44*$B$7,1),0) | I44: =F44+H44 | J44: Included | K44: Implementation
A45: QA-AUT | B45: QA — Automation (optional)
A46: QA-A.1 | B46: Framework design & setup | C46: 0 | D46: 0 | E46: 0 | F46: =IF(AND(C46<>"",D46<>"",E46<>""),(C46+4*D46+E46)/6,0) | G46: No | H46: =IF(G46="Yes",ROUND(D46*$B$7,1),0) | I46: =F46+H46 | J46: Post-MVP | K46: Post-MVP Enhancement
A47: QA-A.2 | B47: Environment Setup | C47: 0 | D47: 0 | E47: 0 | F47: =IF(AND(C47<>"",D47<>"",E47<>""),(C47+4*D47+E47)/6,0) | G47: No | H47: =IF(G47="Yes",ROUND(D47*$B$7,1),0) | I47: =F47+H47 | J47: Post-MVP | K47: Post-MVP Enhancement
A48: QA-A.3 | B48: CI/CD integration | C48: 0 | D48: 0 | E48: 0 | F48: =IF(AND(C48<>"",D48<>"",E48<>""),(C48+4*D48+E48)/6,0) | G48: No | H48: =IF(G48="Yes",ROUND(D48*$B$7,1),0) | I48: =F48+H48 | J48: Post-MVP | K48: Post-MVP Enhancement
A49: QA-A.4 | B49: Test development & execution | C49: 0 | D49: 0 | E49: 0 | F49: =IF(AND(C49<>"",D49<>"",E49<>""),(C49+4*D49+E49)/6,0) | G49: No | H49: =IF(G49="Yes",ROUND(D49*$B$7,1),0) | I49: =F49+H49 | J49: Post-MVP | K49: Post-MVP Enhancement

Sheet DevOps Estimation
A1: DevOps Estimation
A2: Purpose: | B2: Cloud-agnostic DevOps WBS: cost modelling, repo/IAM/CI tooling, environment build (Dev/Test/Stage/Prod), SSDLC pipelines, monitoring, backup/DR. Replaces the v1.4 single 'DevOps' role line with no hours.
A3: How to use: | B3: (1) Estimate Discovery cost-modelling activities first — they shape the cloud bill. (2) For environment rows, repeat the block per environment (Dev/Test/Stage/Prod). (3) Apply Contingency = Yes on cloud-vendor-dependent items (DNS, SSL, KMS, networking) where vendor surprises bite. (4) Toggle iOS/Android pipelines off if not applicable.
A4: Inputs: | B4: O/ML/P per row, Apply Contingency Y/N, Include, Phase, Deliverable.
A5: Outputs: | B5: DevOps roll-up flows to Buffers and Headcount and Cost.
A6: Linked tabs: | B6: Buffers & Non-Dev Activities (DevOps roll-up). Headcount and Cost (DevOps estimated hours). Fixed Costs (cloud bill — typically reflected as separate line items).
A7: Default contingency: | B7: 0.3 | C7: (used when Apply Contingency = Yes; multiplied by Most Likely)
A8: Cloud-agnostic DevOps catalogue. 30% default contingency reflects environment / vendor uncertainty.
A10: ID | B10: Service / Activity | C10: Optimistic | D10: Most Likely | E10: Pessimistic | F10: Expected | G10: Apply Contingency | H10: Contingency | I10: Final Expected | J10: Include | K10: Project Phase | L10: Deliverable | M10: Description / Scope | N10: Assumptions | O10: Notes
B11: TOTALS | C11: =SUM(C12:C54) | D11: =SUM(D12:D54) | E11: =SUM(E12:E54) | F11: =SUM(F12:F54) | H11: =SUM(H12:H54) | I11: =SUMIF(J12:J54,"Included",I12:I54) | J11: (only Included counted at right)
A12: DO-1 | B12: Discovery — cost / sizing
A13: DO-1.1 | B13: Estimation of infra cost (10k MAU baseline) | C13: 10 | D13: 10 | E13: 8 | F13: =IF(AND(C13<>"",D13<>"",E13<>""),(C13+4*D13+E13)/6,0) | G13: Yes | H13: =IF(G13="Yes",ROUND(D13*$B$7,1),0) | I13: =F13+H13 | J13: Included | K13: Discovery | L13: Infra cost model
A14: DO-1.2 | B14: Additional services costs | C14: 5 | D14: 5 | E14: 4 | F14: =IF(AND(C14<>"",D14<>"",E14<>""),(C14+4*D14+E14)/6,0) | G14: Yes | H14: =IF(G14="Yes",ROUND(D14*$B$7,1),0) | I14: =F14+H14 | J14: Included | K14: Discovery
A15: DO-1.3 | B15: Cost optimization options | C15: 8 | D15: 11 | E15: 11 | F15: =IF(AND(C15<>"",D15<>"",E15<>""),(C15+4*D15+E15)/6,0) | G15: Yes | H15: =IF(G15="Yes",ROUND(D15*$B$7,1),0) | I15: =F15+H15 | J15: Included | K15: Discovery
A16: DO-1.4 | B16: Customer presentation of cost model | C16: 3 | D16: 4 | E16: 4 | F16: =IF(AND(C16<>"",D16<>"",E16<>""),(C16+4*D16+E16)/6,0) | G16: Yes | H16: =IF(G16="Yes",ROUND(D16*$B$7,1),0) | I16: =F16+H16 | J16: Included | K16: Discovery
A17: DO-2 | B17: Implementation — preparing tooling
A18: DO-2.1 | B18: Pre-flight artefact check | C18: 2 | D18: 3 | E18: 2 | F18: =IF(AND(C18<>"",D18<>"",E18<>""),(C18+4*D18+E18)/6,0) | G18: No | H18: =IF(G18="Yes",ROUND(D18*$B$7,1),0) | I18: =F18+H18 | J18: Included | K18: Implementation
A19: DO-2.2 | B19: Setup repositories (VCS) | C19: 2 | D19: 3 | E19: 2 | F19: =IF(AND(C19<>"",D19<>"",E19<>""),(C19+4*D19+E19)/6,0) | G19: No | H19: =IF(G19="Yes",ROUND(D19*$B$7,1),0) | I19: =F19+H19 | J19: Included | K19: Implementation
A20: DO-2.3 | B20: Setup domain names & DNS | C20: 2 | D20: 3 | E20: 2 | F20: =IF(AND(C20<>"",D20<>"",E20<>""),(C20+4*D20+E20)/6,0) | G20: Yes | H20: =IF(G20="Yes",ROUND(D20*$B$7,1),0) | I20: =F20+H20 | J20: Included | K20: Implementation
A21: DO-2.4 | B21: IAM roles for team members | C21: 4 | D21: 6 | E21: 4 | F21: =IF(AND(C21<>"",D21<>"",E21<>""),(C21+4*D21+E21)/6,0) | G21: No | H21: =IF(G21="Yes",ROUND(D21*$B$7,1),0) | I21: =F21+H21 | J21: Included | K21: Implementation
A22: DO-2.5 | B22: Package registry | C22: 2 | D22: 2 | E22: 2 | F22: =IF(AND(C22<>"",D22<>"",E22<>""),(C22+4*D22+E22)/6,0) | G22: No | H22: =IF(G22="Yes",ROUND(D22*$B$7,1),0) | I22: =F22+H22 | J22: Included | K22: Implementation
A23: DO-2.6 | B23: CI/CD management system | C23: 8 | D23: 11 | E23: 8 | F23: =IF(AND(C23<>"",D23<>"",E23<>""),(C23+4*D23+E23)/6,0) | G23: No | H23: =IF(G23="Yes",ROUND(D23*$B$7,1),0) | I23: =F23+H23 | J23: Included | K23: Implementation
A24: DO-2.7 | B24: Quality gate analyzer | C24: 3 | D24: 4 | E24: 3 | F24: =IF(AND(C24<>"",D24<>"",E24<>""),(C24+4*D24+E24)/6,0) | G24: Yes | H24: =IF(G24="Yes",ROUND(D24*$B$7,1),0) | I24: =F24+H24 | J24: Included | K24: Implementation
A25: DO-2.8 | B25: OWASP / dependency scanning | C25: 8 | D25: 11 | E25: 8 | F25: =IF(AND(C25<>"",D25<>"",E25<>""),(C25+4*D25+E25)/6,0) | G25: Yes | H25: =IF(G25="Yes",ROUND(D25*$B$7,1),0) | I25: =F25+H25 | J25: Included | K25: Implementation
A26: DO-2.9 | B26: IaC tools setup (Terraform/Pulumi) | C26: 8 | D26: 11 | E26: 8 | F26: =IF(AND(C26<>"",D26<>"",E26<>""),(C26+4*D26+E26)/6,0) | G26: No | H26: =IF(G26="Yes",ROUND(D26*$B$7,1),0) | I26: =F26+H26 | J26: Included | K26: Implementation
A27: DO-2.10 | B27: PaaS framework adaptation | C27: 24 | D27: 24 | E27: 24 | F27: =IF(AND(C27<>"",D27<>"",E27<>""),(C27+4*D27+E27)/6,0) | G27: Yes | H27: =IF(G27="Yes",ROUND(D27*$B$7,1),0) | I27: =F27+H27 | J27: Included | K27: Implementation
A28: DO-3 | B28: Environments — Development
A29: DO-3.1 | B29: Dev account setup | C29: 2 | D29: 3 | E29: 3 | F29: =IF(AND(C29<>"",D29<>"",E29<>""),(C29+4*D29+E29)/6,0) | G29: Yes | H29: =IF(G29="Yes",ROUND(D29*$B$7,1),0) | I29: =F29+H29 | J29: Included | K29: Implementation
A30: DO-3.2 | B30: FE deployment in Dev | C30: 3 | D30: 4 | E30: 4 | F30: =IF(AND(C30<>"",D30<>"",E30<>""),(C30+4*D30+E30)/6,0) | G30: No | H30: =IF(G30="Yes",ROUND(D30*$B$7,1),0) | I30: =F30+H30 | J30: Included | K30: Implementation
A31: DO-3.3 | B31: BE infrastructure (containers/K8s) | C31: 16 | D31: 16 | E31: 24 | F31: =IF(AND(C31<>"",D31<>"",E31<>""),(C31+4*D31+E31)/6,0) | G31: No | H31: =IF(G31="Yes",ROUND(D31*$B$7,1),0) | I31: =F31+H31 | J31: Included | K31: Implementation
A32: DO-3.4 | B32: VPC / subnets / security groups | C32: 2 | D32: 3 | E32: 3 | F32: =IF(AND(C32<>"",D32<>"",E32<>""),(C32+4*D32+E32)/6,0) | G32: No | H32: =IF(G32="Yes",ROUND(D32*$B$7,1),0) | I32: =F32+H32 | J32: Included | K32: Implementation
A33: DO-3.5 | B33: VPN access | C33: 8 | D33: 8 | E33: 10 | F33: =IF(AND(C33<>"",D33<>"",E33<>""),(C33+4*D33+E33)/6,0) | G33: No | H33: =IF(G33="Yes",ROUND(D33*$B$7,1),0) | I33: =F33+H33 | J33: Included | K33: Implementation
A34: DO-3.6 | B34: ALB / target groups / WAF | C34: 6 | D34: 6 | E34: 9 | F34: =IF(AND(C34<>"",D34<>"",E34<>""),(C34+4*D34+E34)/6,0) | G34: No | H34: =IF(G34="Yes",ROUND(D34*$B$7,1),0) | I34: =F34+H34 | J34: Included | K34: Implementation
A35: DO-3.7 | B35: Object storage | C35: 1 | D35: 2 | E35: 2 | F35: =IF(AND(C35<>"",D35<>"",E35<>""),(C35+4*D35+E35)/6,0) | G35: Yes | H35: =IF(G35="Yes",ROUND(D35*$B$7,1),0) | I35: =F35+H35 | J35: Included | K35: Implementation
A36: DO-3.8 | B36: Relational DB | C36: 6 | D36: 6 | E36: 8 | F36: =IF(AND(C36<>"",D36<>"",E36<>""),(C36+4*D36+E36)/6,0) | G36: Yes | H36: =IF(G36="Yes",ROUND(D36*$B$7,1),0) | I36: =F36+H36 | J36: Included | K36: Implementation
A37: DO-3.9 | B37: Non-relational DB | C37: 4 | D37: 4 | E37: 6 | F37: =IF(AND(C37<>"",D37<>"",E37<>""),(C37+4*D37+E37)/6,0) | G37: Yes | H37: =IF(G37="Yes",ROUND(D37*$B$7,1),0) | I37: =F37+H37 | J37: Included | K37: Implementation
A38: DO-3.10 | B38: Cache (ElastiCache/Redis) | C38: 5 | D38: 5 | E38: 7 | F38: =IF(AND(C38<>"",D38<>"",E38<>""),(C38+4*D38+E38)/6,0) | G38: Yes | H38: =IF(G38="Yes",ROUND(D38*$B$7,1),0) | I38: =F38+H38 | J38: Included | K38: Implementation
A39: DO-3.11 | B39: CDN / distribution / cert | C39: 3 | D39: 5 | E39: 5 | F39: =IF(AND(C39<>"",D39<>"",E39<>""),(C39+4*D39+E39)/6,0) | G39: Yes | H39: =IF(G39="Yes",ROUND(D39*$B$7,1),0) | I39: =F39+H39 | J39: Included | K39: Implementation
A40: DO-4 | B40: Environments — Test / Stage / Prod
A41: DO-4.1 | B41: Test environment build | C41: 16 | D41: 24 | E41: 32 | F41: =IF(AND(C41<>"",D41<>"",E41<>""),(C41+4*D41+E41)/6,0) | G41: Yes | H41: =IF(G41="Yes",ROUND(D41*$B$7,1),0) | I41: =F41+H41 | J41: Included | K41: Implementation
A42: DO-4.2 | B42: Stage environment build | C42: 16 | D42: 24 | E42: 32 | F42: =IF(AND(C42<>"",D42<>"",E42<>""),(C42+4*D42+E42)/6,0) | G42: Yes | H42: =IF(G42="Yes",ROUND(D42*$B$7,1),0) | I42: =F42+H42 | J42: Included | K42: Implementation
A43: DO-4.3 | B43: Prod environment build | C43: 24 | D43: 32 | E43: 48 | F43: =IF(AND(C43<>"",D43<>"",E43<>""),(C43+4*D43+E43)/6,0) | G43: Yes | H43: =IF(G43="Yes",ROUND(D43*$B$7,1),0) | I43: =F43+H43 | J43: Included | K43: Implementation
A44: DO-5 | B44: SSDLC pipelines
A45: DO-5.1 | B45: iOS pipeline | C45: 8 | D45: 11 | E45: 8 | F45: =IF(AND(C45<>"",D45<>"",E45<>""),(C45+4*D45+E45)/6,0) | G45: Yes | H45: =IF(G45="Yes",ROUND(D45*$B$7,1),0) | I45: =F45+H45 | J45: Included | K45: Implementation
A46: DO-5.2 | B46: Android pipeline | C46: 8 | D46: 8 | E46: 8 | F46: =IF(AND(C46<>"",D46<>"",E46<>""),(C46+4*D46+E46)/6,0) | G46: No | H46: =IF(G46="Yes",ROUND(D46*$B$7,1),0) | I46: =F46+H46 | J46: Included | K46: Implementation
A47: DO-5.3 | B47: FE web pipeline | C47: 6 | D47: 6 | E47: 8 | F47: =IF(AND(C47<>"",D47<>"",E47<>""),(C47+4*D47+E47)/6,0) | G47: No | H47: =IF(G47="Yes",ROUND(D47*$B$7,1),0) | I47: =F47+H47 | J47: Included | K47: Implementation
A48: DO-5.4 | B48: BE pipelines | C48: 8 | D48: 11 | E48: 11 | F48: =IF(AND(C48<>"",D48<>"",E48<>""),(C48+4*D48+E48)/6,0) | G48: No | H48: =IF(G48="Yes",ROUND(D48*$B$7,1),0) | I48: =F48+H48 | J48: Included | K48: Implementation
A49: DO-5.5 | B49: SAST scanning | C49: 8 | D49: 11 | E49: 11 | F49: =IF(AND(C49<>"",D49<>"",E49<>""),(C49+4*D49+E49)/6,0) | G49: Yes | H49: =IF(G49="Yes",ROUND(D49*$B$7,1),0) | I49: =F49+H49 | J49: Included | K49: Implementation
A50: DO-5.6 | B50: Docker image hardening rules | C50: 6 | D50: 6 | E50: 6 | F50: =IF(AND(C50<>"",D50<>"",E50<>""),(C50+4*D50+E50)/6,0) | G50: Yes | H50: =IF(G50="Yes",ROUND(D50*$B$7,1),0) | I50: =F50+H50 | J50: Included | K50: Implementation
A51: DO-6 | B51: Operations & monitoring
A52: DO-6.1 | B52: Monitoring (metrics/logs/alerts) | C52: 16 | D52: 24 | E52: 32 | F52: =IF(AND(C52<>"",D52<>"",E52<>""),(C52+4*D52+E52)/6,0) | G52: Yes | H52: =IF(G52="Yes",ROUND(D52*$B$7,1),0) | I52: =F52+H52 | J52: Included | K52: Implementation
A53: DO-6.2 | B53: Backup & DR drills | C53: 8 | D53: 12 | E53: 16 | F53: =IF(AND(C53<>"",D53<>"",E53<>""),(C53+4*D53+E53)/6,0) | G53: Yes | H53: =IF(G53="Yes",ROUND(D53*$B$7,1),0) | I53: =F53+H53 | J53: Included | K53: Implementation
A54: DO-6.3 | B54: On-call runbook & paging | C54: 4 | D54: 8 | E54: 12 | F54: =IF(AND(C54<>"",D54<>"",E54<>""),(C54+4*D54+E54)/6,0) | G54: No | H54: =IF(G54="Yes",ROUND(D54*$B$7,1),0) | I54: =F54+H54 | J54: Included | K54: Implementation

Sheet PM Estimation
A1: Project Management Estimation
A2: Purpose: | B2: PM activity catalogue — Discovery prestart, governance (RACI / DoR / DoD / Communication & Escalation matrices), project charter, sprint cadence, reporting, change management, closure. Replaces v1.4's flat 0.25 FTE PM allocation.
A3: How to use: | B3: (1) Routine items can be estimated with Most Likely only — leave O and P blank. (2) For impactful items (estimation oversight, staffing, change requests) provide all three points. (3) Recurring implementation items (PM-4.x) are PER SPRINT — multiply Most Likely by the number of sprints when copying into your project plan. (4) Apply Contingency = Yes on coordination-heavy items.
A4: Inputs: | B4: ML always; O/P optional; Apply Contingency Y/N; Include; Phase.
A5: Outputs: | B5: PM roll-up flows to Buffers and Headcount and Cost.
A6: Linked tabs: | B6: Buffers & Non-Dev Activities (PM roll-up). Headcount and Cost.
A7: Default contingency: | B7: 0.2 | C7: (used when Apply Contingency = Yes; multiplied by Most Likely)
A8: PM activity catalogue replaces the flat 0.25 FTE assumption. Use Pessimistic and Optimistic on impactful items; Most Likely is fine for routine items.
A10: ID | B10: Service / Activity | C10: Optimistic | D10: Most Likely | E10: Pessimistic | F10: Expected | G10: Apply Contingency | H10: Contingency | I10: Final Expected | J10: Include | K10: Project Phase | L10: Deliverable | M10: Description / Scope | N10: Assumptions | O10: Notes
B11: TOTALS | C11: =SUM(C12:C49) | D11: =SUM(D12:D49) | E11: =SUM(E12:E49) | F11: =SUM(F12:F49) | H11: =SUM(H12:H49) | I11: =SUMIF(J12:J49,"Included",I12:I49) | J11: (only Included counted at right)
A12: PM-1 | B12: Discovery prestart
A13: PM-1.1 | B13: Compile input data list | D13: 4 | F13: =IF(AND(C13<>"",D13<>"",E13<>""),(C13+4*D13+E13)/6,0) | G13: Yes | H13: =IF(G13="Yes",ROUND(D13*$B$7,1),0) | I13: =F13+H13 | J13: Included | K13: Discovery
A14: PM-1.2 | B14: Agree final budget / parameters | D14: 8 | F14: =IF(AND(C14<>"",D14<>"",E14<>""),(C14+4*D14+E14)/6,0) | G14: Yes | H14: =IF(G14="Yes",ROUND(D14*$B$7,1),0) | I14: =F14+H14 | J14: Included | K14: Discovery
A15: PM-1.3 | B15: Demands creation | D15: 3 | F15: =IF(AND(C15<>"",D15<>"",E15<>""),(C15+4*D15+E15)/6,0) | G15: Yes | H15: =IF(G15="Yes",ROUND(D15*$B$7,1),0) | I15: =F15+H15 | J15: Included | K15: Discovery
A16: PM-1.4 | B16: Staffing support | D16: 24 | F16: =IF(AND(C16<>"",D16<>"",E16<>""),(C16+4*D16+E16)/6,0) | G16: Yes | H16: =IF(G16="Yes",ROUND(D16*$B$7,1),0) | I16: =F16+H16 | J16: Included | K16: Discovery
A17: PM-1.5 | B17: Internal kickoff meeting | D17: 3 | F17: =IF(AND(C17<>"",D17<>"",E17<>""),(C17+4*D17+E17)/6,0) | G17: Yes | H17: =IF(G17="Yes",ROUND(D17*$B$7,1),0) | I17: =F17+H17 | J17: Included | K17: Discovery
A18: PM-1.6 | B18: 1C / org system entries | D18: 3 | F18: =IF(AND(C18<>"",D18<>"",E18<>""),(C18+4*D18+E18)/6,0) | G18: Yes | H18: =IF(G18="Yes",ROUND(D18*$B$7,1),0) | I18: =F18+H18 | J18: Included | K18: Discovery
A19: PM-1.7 | B19: Jira space creation | D19: 3 | F19: =IF(AND(C19<>"",D19<>"",E19<>""),(C19+4*D19+E19)/6,0) | G19: Yes | H19: =IF(G19="Yes",ROUND(D19*$B$7,1),0) | I19: =F19+H19 | J19: Included | K19: Discovery
A20: PM-1.8 | B20: Confluence space creation | D20: 4 | F20: =IF(AND(C20<>"",D20<>"",E20<>""),(C20+4*D20+E20)/6,0) | G20: Yes | H20: =IF(G20="Yes",ROUND(D20*$B$7,1),0) | I20: =F20+H20 | J20: Included | K20: Discovery
A21: PM-1.9 | B21: Team chat creation | D21: 1 | F21: =IF(AND(C21<>"",D21<>"",E21<>""),(C21+4*D21+E21)/6,0) | G21: Yes | H21: =IF(G21="Yes",ROUND(D21*$B$7,1),0) | I21: =F21+H21 | J21: Included | K21: Discovery
A22: PM-1.10 | B22: Onboarding page (wiki) | D22: 8 | F22: =IF(AND(C22<>"",D22<>"",E22<>""),(C22+4*D22+E22)/6,0) | G22: Yes | H22: =IF(G22="Yes",ROUND(D22*$B$7,1),0) | I22: =F22+H22 | J22: Included | K22: Discovery
A23: PM-2 | B23: Discovery — governance
A24: PM-2.1 | B24: RACI matrix | D24: 2 | F24: =IF(AND(C24<>"",D24<>"",E24<>""),(C24+4*D24+E24)/6,0) | G24: Yes | H24: =IF(G24="Yes",ROUND(D24*$B$7,1),0) | I24: =F24+H24 | J24: Included | K24: Discovery | L24: RACI
A25: PM-2.2 | B25: Communication plan | D25: 2 | F25: =IF(AND(C25<>"",D25<>"",E25<>""),(C25+4*D25+E25)/6,0) | G25: Yes | H25: =IF(G25="Yes",ROUND(D25*$B$7,1),0) | I25: =F25+H25 | J25: Included | K25: Discovery
A26: PM-2.3 | B26: Communication matrix | D26: 1 | F26: =IF(AND(C26<>"",D26<>"",E26<>""),(C26+4*D26+E26)/6,0) | G26: Yes | H26: =IF(G26="Yes",ROUND(D26*$B$7,1),0) | I26: =F26+H26 | J26: Included | K26: Discovery
A27: PM-2.4 | B27: Escalation matrix | D27: 1 | F27: =IF(AND(C27<>"",D27<>"",E27<>""),(C27+4*D27+E27)/6,0) | G27: Yes | H27: =IF(G27="Yes",ROUND(D27*$B$7,1),0) | I27: =F27+H27 | J27: Included | K27: Discovery
A28: PM-2.5 | B28: DoR / DoD | D28: 4 | F28: =IF(AND(C28<>"",D28<>"",E28<>""),(C28+4*D28+E28)/6,0) | G28: Yes | H28: =IF(G28="Yes",ROUND(D28*$B$7,1),0) | I28: =F28+H28 | J28: Included | K28: Discovery
A29: PM-2.6 | B29: Discovery kickoff | D29: 6 | F29: =IF(AND(C29<>"",D29<>"",E29<>""),(C29+4*D29+E29)/6,0) | G29: Yes | H29: =IF(G29="Yes",ROUND(D29*$B$7,1),0) | I29: =F29+H29 | J29: Included | K29: Discovery
A30: PM-3 | B30: Discovery deliverables
A31: PM-3.1 | B31: Project Charter | D31: 6 | F31: =IF(AND(C31<>"",D31<>"",E31<>""),(C31+4*D31+E31)/6,0) | G31: Yes | H31: =IF(G31="Yes",ROUND(D31*$B$7,1),0) | I31: =F31+H31 | J31: Included | K31: Discovery
A32: PM-3.2 | B32: Daily comms with team | D32: 3 | F32: =IF(AND(C32<>"",D32<>"",E32<>""),(C32+4*D32+E32)/6,0) | G32: Yes | H32: =IF(G32="Yes",ROUND(D32*$B$7,1),0) | I32: =F32+H32 | J32: Included | K32: Discovery
A33: PM-3.3 | B33: Discovery metrics setup | D33: 4 | F33: =IF(AND(C33<>"",D33<>"",E33<>""),(C33+4*D33+E33)/6,0) | G33: Yes | H33: =IF(G33="Yes",ROUND(D33*$B$7,1),0) | I33: =F33+H33 | J33: Included | K33: Discovery
A34: PM-3.4 | B34: Vision & Scope review/coordination | D34: 10 | F34: =IF(AND(C34<>"",D34<>"",E34<>""),(C34+4*D34+E34)/6,0) | G34: Yes | H34: =IF(G34="Yes",ROUND(D34*$B$7,1),0) | I34: =F34+H34 | J34: Included | K34: Discovery
A35: PM-3.5 | B35: Initial product backlog support | D35: 8 | F35: =IF(AND(C35<>"",D35<>"",E35<>""),(C35+4*D35+E35)/6,0) | G35: Yes | H35: =IF(G35="Yes",ROUND(D35*$B$7,1),0) | I35: =F35+H35 | J35: Included | K35: Discovery
A36: PM-3.6 | B36: Feature-based estimation oversight | D36: 24 | F36: =IF(AND(C36<>"",D36<>"",E36<>""),(C36+4*D36+E36)/6,0) | G36: Yes | H36: =IF(G36="Yes",ROUND(D36*$B$7,1),0) | I36: =F36+H36 | J36: Included | K36: Discovery
A37: PM-3.7 | B37: Initial budget estimation | D37: 4 | F37: =IF(AND(C37<>"",D37<>"",E37<>""),(C37+4*D37+E37)/6,0) | G37: Yes | H37: =IF(G37="Yes",ROUND(D37*$B$7,1),0) | I37: =F37+H37 | J37: Included | K37: Discovery
A38: PM-3.8 | B38: Initial dev phase plan | D38: 4 | F38: =IF(AND(C38<>"",D38<>"",E38<>""),(C38+4*D38+E38)/6,0) | G38: Yes | H38: =IF(G38="Yes",ROUND(D38*$B$7,1),0) | I38: =F38+H38 | J38: Included | K38: Discovery
A39: PM-3.9 | B39: Resource plan | D39: 2 | F39: =IF(AND(C39<>"",D39<>"",E39<>""),(C39+4*D39+E39)/6,0) | G39: Yes | H39: =IF(G39="Yes",ROUND(D39*$B$7,1),0) | I39: =F39+H39 | J39: Included | K39: Discovery
A40: PM-3.10 | B40: Initial risk matrix | D40: 3 | F40: =IF(AND(C40<>"",D40<>"",E40<>""),(C40+4*D40+E40)/6,0) | G40: Yes | H40: =IF(G40="Yes",ROUND(D40*$B$7,1),0) | I40: =F40+H40 | J40: Included | K40: Discovery
A41: PM-3.11 | B41: Internal demo / proposal review | D41: 4 | F41: =IF(AND(C41<>"",D41<>"",E41<>""),(C41+4*D41+E41)/6,0) | G41: Yes | H41: =IF(G41="Yes",ROUND(D41*$B$7,1),0) | I41: =F41+H41 | J41: Included | K41: Discovery
A42: PM-3.12 | B42: Update proposal for customer | D42: 4 | F42: =IF(AND(C42<>"",D42<>"",E42<>""),(C42+4*D42+E42)/6,0) | G42: Yes | H42: =IF(G42="Yes",ROUND(D42*$B$7,1),0) | I42: =F42+H42 | J42: Included | K42: Discovery
A43: PM-4 | B43: Implementation — recurring
A44: PM-4.1 | B44: Sprint planning / refinement / retro | D44: 8 | F44: =IF(AND(C44<>"",D44<>"",E44<>""),(C44+4*D44+E44)/6,0) | G44: No | H44: =IF(G44="Yes",ROUND(D44*$B$7,1),0) | I44: =F44+H44 | J44: Included | K44: Implementation | M44: Per sprint over implementation duration
A45: PM-4.2 | B45: Status reporting (weekly) | D45: 4 | F45: =IF(AND(C45<>"",D45<>"",E45<>""),(C45+4*D45+E45)/6,0) | G45: No | H45: =IF(G45="Yes",ROUND(D45*$B$7,1),0) | I45: =F45+H45 | J45: Included | K45: Implementation
A46: PM-4.3 | B46: Risk & issue management | D46: 4 | F46: =IF(AND(C46<>"",D46<>"",E46<>""),(C46+4*D46+E46)/6,0) | G46: Yes | H46: =IF(G46="Yes",ROUND(D46*$B$7,1),0) | I46: =F46+H46 | J46: Included | K46: Implementation
A47: PM-4.4 | B47: Change request management | D47: 4 | F47: =IF(AND(C47<>"",D47<>"",E47<>""),(C47+4*D47+E47)/6,0) | G47: Yes | H47: =IF(G47="Yes",ROUND(D47*$B$7,1),0) | I47: =F47+H47 | J47: Included | K47: Implementation
A48: PM-4.5 | B48: Stakeholder demos / acceptance | D48: 4 | F48: =IF(AND(C48<>"",D48<>"",E48<>""),(C48+4*D48+E48)/6,0) | G48: No | H48: =IF(G48="Yes",ROUND(D48*$B$7,1),0) | I48: =F48+H48 | J48: Included | K48: Implementation
A49: PM-4.6 | B49: Project closure | D49: 8 | F49: =IF(AND(C49<>"",D49<>"",E49<>""),(C49+4*D49+E49)/6,0) | G49: No | H49: =IF(G49="Yes",ROUND(D49*$B$7,1),0) | I49: =F49+H49 | J49: Included | K49: Implementation

Sheet UIUX Estimation
A1: UI/UX Estimation
A2: Purpose: | B2: UI/UX WBS — design audit, IA, wireframes, design system, per-epic screens, prototyping iterations, accessibility review, dev hand-off.
A3: How to use: | B3: (1) Front-load Discovery items (audit, IA, wireframes, design system). (2) Add or remove epics from the Implementation block to match WBS and Estimates. (3) Apply Contingency = Yes on items requiring stakeholder reviews (wireframes, design system).
A4: Inputs: | B4: O/ML/P per row, Apply Contingency Y/N, Include, Phase, Deliverable, Description.
A5: Outputs: | B5: UX roll-up flows to Buffers and Headcount and Cost.
A6: Linked tabs: | B6: Buffers & Non-Dev Activities (UI/UX roll-up). Headcount and Cost.
A7: Default contingency: | B7: 0.2 | C7: (used when Apply Contingency = Yes; multiplied by Most Likely)
A8: UI/UX deliverables are typically front-loaded in Discovery; keep an Implementation tail for hand-off and iteration.
A10: ID | B10: Service / Activity | C10: Optimistic | D10: Most Likely | E10: Pessimistic | F10: Expected | G10: Apply Contingency | H10: Contingency | I10: Final Expected | J10: Include | K10: Project Phase | L10: Deliverable | M10: Description / Scope | N10: Assumptions | O10: Notes
B11: TOTALS | C11: =SUM(C12:C26) | D11: =SUM(D12:D26) | E11: =SUM(E12:E26) | F11: =SUM(F12:F26) | H11: =SUM(H12:H26) | I11: =SUMIF(J12:J26,"Included",I12:I26) | J11: (only Included counted at right)
A12: UX-1 | B12: Discovery
A13: UX-1.1 | B13: Design audit / heuristic review | C13: 8 | D13: 16 | E13: 24 | F13: =IF(AND(C13<>"",D13<>"",E13<>""),(C13+4*D13+E13)/6,0) | G13: No | H13: =IF(G13="Yes",ROUND(D13*$B$7,1),0) | I13: =F13+H13 | J13: Included | K13: Discovery
A14: UX-1.2 | B14: User research / personas | C14: 16 | D14: 24 | E14: 40 | F14: =IF(AND(C14<>"",D14<>"",E14<>""),(C14+4*D14+E14)/6,0) | G14: No | H14: =IF(G14="Yes",ROUND(D14*$B$7,1),0) | I14: =F14+H14 | J14: Not included | K14: Discovery
A15: UX-1.3 | B15: Information architecture | C15: 8 | D15: 16 | E15: 24 | F15: =IF(AND(C15<>"",D15<>"",E15<>""),(C15+4*D15+E15)/6,0) | G15: No | H15: =IF(G15="Yes",ROUND(D15*$B$7,1),0) | I15: =F15+H15 | J15: Included | K15: Discovery
A16: UX-1.4 | B16: Wireframes (key flows) | C16: 16 | D16: 32 | E16: 48 | F16: =IF(AND(C16<>"",D16<>"",E16<>""),(C16+4*D16+E16)/6,0) | G16: Yes | H16: =IF(G16="Yes",ROUND(D16*$B$7,1),0) | I16: =F16+H16 | J16: Included | K16: Discovery
A17: UX-1.5 | B17: Design system / tokens | C17: 16 | D17: 32 | E17: 48 | F17: =IF(AND(C17<>"",D17<>"",E17<>""),(C17+4*D17+E17)/6,0) | G17: Yes | H17: =IF(G17="Yes",ROUND(D17*$B$7,1),0) | I17: =F17+H17 | J17: Included | K17: Discovery
A18: UX-2 | B18: Implementation — per epic
A19: UX-2.1 | B19: Authorization screens | C19: 8 | D19: 12 | E19: 20 | F19: =IF(AND(C19<>"",D19<>"",E19<>""),(C19+4*D19+E19)/6,0) | G19: No | H19: =IF(G19="Yes",ROUND(D19*$B$7,1),0) | I19: =F19+H19 | J19: Included | K19: Implementation
A20: UX-2.2 | B20: Profile screens | C20: 8 | D20: 16 | E20: 24 | F20: =IF(AND(C20<>"",D20<>"",E20<>""),(C20+4*D20+E20)/6,0) | G20: No | H20: =IF(G20="Yes",ROUND(D20*$B$7,1),0) | I20: =F20+H20 | J20: Included | K20: Implementation
A21: UX-2.3 | B21: Wallet screens | C21: 16 | D21: 32 | E21: 48 | F21: =IF(AND(C21<>"",D21<>"",E21<>""),(C21+4*D21+E21)/6,0) | G21: Yes | H21: =IF(G21="Yes",ROUND(D21*$B$7,1),0) | I21: =F21+H21 | J21: Included | K21: Implementation
A22: UX-2.4 | B22: Admin panel screens | C22: 8 | D22: 16 | E22: 24 | F22: =IF(AND(C22<>"",D22<>"",E22<>""),(C22+4*D22+E22)/6,0) | G22: No | H22: =IF(G22="Yes",ROUND(D22*$B$7,1),0) | I22: =F22+H22 | J22: Included | K22: Implementation
A23: UX-2.5 | B23: Notifications / feedback states | C23: 4 | D23: 8 | E23: 12 | F23: =IF(AND(C23<>"",D23<>"",E23<>""),(C23+4*D23+E23)/6,0) | G23: No | H23: =IF(G23="Yes",ROUND(D23*$B$7,1),0) | I23: =F23+H23 | J23: Included | K23: Implementation
A24: UX-2.6 | B24: Dev hand-off / specs | C24: 8 | D24: 16 | E24: 24 | F24: =IF(AND(C24<>"",D24<>"",E24<>""),(C24+4*D24+E24)/6,0) | G24: No | H24: =IF(G24="Yes",ROUND(D24*$B$7,1),0) | I24: =F24+H24 | J24: Included | K24: Implementation
A25: UX-2.7 | B25: Prototype iterations | C25: 4 | D25: 8 | E25: 16 | F25: =IF(AND(C25<>"",D25<>"",E25<>""),(C25+4*D25+E25)/6,0) | G25: No | H25: =IF(G25="Yes",ROUND(D25*$B$7,1),0) | I25: =F25+H25 | J25: Included | K25: Implementation
A26: UX-2.8 | B26: Accessibility review | C26: 4 | D26: 8 | E26: 16 | F26: =IF(AND(C26<>"",D26<>"",E26<>""),(C26+4*D26+E26)/6,0) | G26: No | H26: =IF(G26="Yes",ROUND(D26*$B$7,1),0) | I26: =F26+H26 | J26: Included | K26: Implementation

Sheet Buffers & Non-Dev Activities
A1: Buffers & Non-Dev Activities
A2: Purpose: | B2: Applies the project-wide PERT Z-score buffer to dev hours, then adds Bugfix / Documentation / Communication coefficients. Derives Manual QA & AQA from BE+FE (with variance now correctly propagated, fixing a v1.4 bug). Rolls up discipline-tab Final Expected sums (BA / Arch / DevOps / PM / UI-UX / QA-from-tab).
A3: How to use: | B3: (1) Set Z-Score (cell B2) to 0 (50% CI), 1 (84% CI) or 2 (97% CI). Higher = more conservative. (2) The dev rows pull subtotals (Expected) and variance (sum-of-variance per row) from WBS and Estimates. (3) Coefficients (Bugfix 12%, Documentation 5%, Communication 10%, MQA 15%, AQA 15%) come from Input Data named ranges. Edit there. (4) 'Treat BE as FullStack' (cell K6) merges FE into BE if your team is full-stack. (5) Discipline roll-ups at the bottom use SUMIF over each discipline tab's 'Included' rows.
A4: Inputs: | B4: Z-Score, Treat BE as FullStack, Input Data coefficients. WBS Expected & Variance from WBS and Estimates. Discipline tab Final Expected.
A5: Outputs: | B5: Grand Total per role (col L) — feeds the 'Estimated Hours' column on Headcount and Cost.
A6: Linked tabs: | B6: WBS and Estimates (input). Input Data (coefficients). All 6 discipline tabs (roll-ups). Headcount and Cost (consumer).
A7: Z-Score (0..2) | B7: 1 | C7: 0 = 50%, 1 = 84%, 2 = 97% confidence interval
A9: Role | B9: Subtotal, h | C9: Variance, h | D9: StdDev, h | E9: Z-Score | F9: Dev & Test Buffered, h | G9: Bugfix, h | H9: Documentation, h | I9: Communication, h | J9: Total, h | K9: Treat BE as FullStack | L9: Grand Total, h
A10: Back-End | B10: =SUM('WBS and Estimates'!P:P) | C10: =SUM('WBS and Estimates'!S:S) | D10: =SQRT(C10) | E10: =$B$7 | F10: =B10+E10*D10 | G10: =F10*RefBugFix | H10: =F10*RefDocumentation | I10: =F10*RefCommunication | J10: =ROUND(F10+G10+H10+I10,0) | K10: FALSE | L10: =IF($K$10=TRUE,J10+J11,J10)
A11: Front-End | B11: =SUM('WBS and Estimates'!Q:Q) | C11: =SUM('WBS and Estimates'!U:U) | D11: =SQRT(C11) | E11: =$B$7 | F11: =B11+E11*D11 | G11: =F11*RefBugFix | H11: =F11*RefDocumentation | I11: =F11*RefCommunication | J11: =ROUND(F11+G11+H11+I11,0) | L11: =IF($K$10=TRUE,0,J11)
A12: Manual QA | B12: =(B10+B11)*RefManualQA | C12: =(C10+C11)*RefManualQA^2 | D12: =SQRT(C12) | E12: =$B$7 | F12: =B12+E12*D12 | G12: 0 | H12: =F12*RefDocumentation | I12: =F12*RefCommunication | J12: =ROUND(F12+G12+H12+I12,0) | L12: =J12
A13: AQA | B13: =(B10+B11)*RefAQA | C13: =(C10+C11)*RefAQA^2 | D13: =SQRT(C13) | E13: =$B$7 | F13: =B13+E13*D13 | G13: 0 | H13: =F13*RefDocumentation | I13: =F13*RefCommunication | J13: =ROUND(F13+G13+H13+I13,0) | L13: =J13
A15: Pulled from discipline tabs (Final Expected, Included only)
A16: BA | J16: =ROUND(SUMIF('BA Estimation'!J:J,"Included",'BA Estimation'!I:I),0) | L16: =J16
A17: Architecture | J17: =ROUND(SUMIF('Arch Estimation'!J:J,"Included",'Arch Estimation'!I:I),0) | L17: =J17
A18: DevOps | J18: =ROUND(SUMIF('DevOps Estimation'!J:J,"Included",'DevOps Estimation'!I:I),0) | L18: =J18
A19: PM | J19: =ROUND(SUMIF('PM Estimation'!J:J,"Included",'PM Estimation'!I:I),0) | L19: =J19
A20: UI/UX | J20: =ROUND(SUMIF('UIUX Estimation'!J:J,"Included",'UIUX Estimation'!I:I),0) | L20: =J20
A21: QA (alt: from QA tab) | J21: =ROUND(SUMIF('QA Estimation'!J:J,"Included",'QA Estimation'!I:I),0) | L21: =J21

Sheet Rates
A1: Rates — Role x Seniority x Location rate card
A2: Purpose: | B2: External rate card. Headcount and Cost and Maintenance look up the per-hour rate by matching a resource's (Role, Seniority, Location) triple here.
A3: How to use: | B3: (1) Add rows by INSERTING between existing rows (do not append at the bottom — formulas reference whole columns; appending is fine but inserting keeps things tidy). (2) The triple (Role, Seniority, Location) is the key — keep names IDENTICAL to those used on Headcount and Cost. (3) If a resource's triple does not match any row, the cost formula falls back to RefRate ($/h) on Input Data.
A4: Inputs: | B4: Manual rate entries.
A5: Outputs: | B5: Rate, $/h consumed by Headcount and Cost and Maintenance via INDEX/MATCH.
A6: Linked tabs: | B6: Headcount and Cost. Maintenance. Internal Cost & Profitability (informational).
A8: Role | B8: Seniority | C8: Location | D8: Rate, $/h
A9: DM | B9: M2 | C9: Poland | D9: 62
A10: PM | B10: M1 | C10: Poland | D10: 55
A11: Solution Architect | B11: S1 | C11: Poland | D11: 95
A12: Software Architect | B12: S1 | C12: Poland | D12: 85
A13: BA | B13: S1 | C13: Poland | D13: 53
A14: UI/UX | B14: M3 | C14: Poland | D14: 50
A15: Front-End Web | B15: Lead | C15: Poland | D15: 72
A16: Front-End Web | B16: M1 | C16: Poland | D16: 50
A17: Front-End Mobile | B17: S1 | C17: Poland | D17: 55
A18: Back-End | B18: S1 | C18: Poland | D18: 75
A19: Back-End | B19: M2 | C19: Poland | D19: 55
A20: Back-End | B20: J2 | C20: Poland | D20: 48
... A26: DevOps | B26: S1 | C26: Poland | D26: 70

Sheet Input Data
A1: Input Data — global coefficients, blended-rate fallback, enums
A2: Edit the values in column B. The whole workbook references these named cells.
A4: Coefficients
A5: RefUnitTest | B5: 0.2 | C5: WBS augmentation: unit-test overhead as fraction of base hours
A6: RefIntegrationTest | B6: 0.1 | C6: WBS augmentation: integration-test overhead
A7: RefCodeReview | B7: 0.1 | C7: WBS augmentation: code review overhead
A8: RefManualQA | B8: 0.3 | C8: Manual QA hours = (BE+FE) * this
A9: RefAQA | B9: 0.15 | C9: Automation QA hours = (BE+FE) * this
A10: RefBugFix | B10: 0.1 | C10: Buffer: bugfix hours = Dev * this
A11: RefDocumentation | B11: 0.07 | C11: Buffer: documentation hours = Dev * this
A12: RefCommunication | B12: 0.08 | C12: Buffer: communication hours = Dev * this
A13: RefRate | B13: 60 | C13: Blended-rate fallback used when role lookup misses
A15: Enums (data-validation source lists)
F16: EnumRoles | H16: EnumSeniorities | J16: EnumPhase | L16: EnumLocations | N16: EnumYesNo | P16: EnumInclude
F17: DM | H17: J1 | J17: Discovery | L17: Poland | N17: Yes | P17: Included
F18: PM | H18: J2 | J18: Design | L18: Ukraine | N18: No | P18: Excluded
F19: Solution Architect | H19: M1 | J19: Build | L19: USA
F20: Software Architect | H20: M2 | J20: Test | L20: EU
F21: BA | H21: M3 | J21: Launch | L21: Remote
F22: UI/UX | H22: S1 | J22: Stabilization
F23: Front-End Web | H23: Lead
F24: Front-End Mobile
F25: Back-End
F26: Blockchain / Crypto
F27: Manual QA
F28: AQA
F29: DevOps

Sheet Internal Cost & Profitability
A1: Internal Cost & Profitability
A2: Purpose: | B2: Margin model. Per resource, computes Internal Cost / month (salary + social tax + overhead) and Profit / month (External Rate * Hours/mo - Internal Cost). Project Profitability rolls up against Headcount and Cost Total Cost.
A3: How to use: | B3: (1) Edit per row: Role / Seniority / External Rate / Avg Salary (gross monthly) / Internal Rate (informational) / Social Tax % / Overhead. Hours/mo defaults to 168 (=21 days * 8h). (2) Project Profitability cell at the bottom = (Headcount and Cost Total Cost - Sum Internal Cost) / Total Cost. Aim for 15-25% on standard work, more on high-risk fixed-price. (3) Seniority Index at the bottom shows team seniority relative to RefRate; > 1 means more senior than the blended baseline.
A4: Inputs: | B4: External rate, avg salary, social tax %, overhead, hours/month per resource (manual). Headcount and Cost Total Cost.
A5: Outputs: | B5: Internal cost per resource, project total internal cost, project profitability %, seniority index. Reported on Check-list mandatory calculations.
A6: Linked tabs: | B6: Rates (cross-check on external rate). Headcount and Cost (Total Cost). Check-list (mandatory KPIs).
A8: Role | B8: Seniority | C8: External Rate, $/h | D8: Avg Salary, $/mo | E8: Internal Rate, $/h | F8: Social Tax % | G8: Overhead, $/mo | H8: Hours/mo | I8: Internal Cost, $/mo | J8: Profit, $/mo | K8: Profit %
A9: DM | B9: M2 | C9: 62 | D9: 6000 | E9: 35.71 | F9: 0.1 | G9: 2542 | H9: 168 | I9: =D9*(1+F9)+G9 | J9: =C9*H9-I9 | K9: =IFERROR(J9/(C9*H9),0)
A10: PM | B10: M1 | C10: 55 | D10: 3000 | E10: 17.86 | F10: 0.1 | G10: 2542 | H10: 168 | I10: =D10*(1+F10)+G10 | J10: =C10*H10-I10 | K10: =IFERROR(J10/(C10*H10),0)
A11: Solution Architect | B11: S1 | C11: 95 | D11: 8414 | E11: 50.08 | F11: 0.1 | G11: 2542 | H11: 168 | I11: =D11*(1+F11)+G11 | J11: =C11*H11-I11 | K11: =IFERROR(J11/(C11*H11),0)
A12: Software Architect | B12: S1 | C12: 85 | D12: 7446 | E12: 44.32 | F12: 0.1 | G12: 2542 | H12: 168 | I12: =D12*(1+F12)+G12 | J12: =C12*H12-I12 | K12: =IFERROR(J12/(C12*H12),0)
A13: BA | B13: S1 | C13: 53 | D13: 5040 | E13: 30 | F13: 0.1 | G13: 2542 | H13: 168 | I13: =D13*(1+F13)+G13 | J13: =C13*H13-I13 | K13: =IFERROR(J13/(C13*H13),0)
A14: UI/UX | B14: M3 | C14: 50 | D14: 2800 | E14: 16.67 | F14: 0.1 | G14: 2542 | H14: 168 | I14: =D14*(1+F14)+G14 | J14: =C14*H14-I14 | K14: =IFERROR(J14/(C14*H14),0)
A15: Front-End Web Lead | B15: Lead | C15: 72 | D15: 4305 | E15: 25.63 | F15: 0.1 | G15: 2542 | H15: 168 | I15: =D15*(1+F15)+G15 | J15: =C15*H15-I15 | K15: =IFERROR(J15/(C15*H15),0)
A16: Front-End Web | B16: M1 | C16: 50 | D16: 1909 | E16: 11.36 | F16: 0.1 | G16: 2542 | H16: 168 | I16: =D16*(1+F16)+G16 | J16: =C16*H16-I16 | K16: =IFERROR(J16/(C16*H16),0)
A17: Front-End Mobile | B17: S1 | C17: 55 | D17: 4334 | E17: 25.8 | F17: 0.1 | G17: 2542 | H17: 168 | I17: =D17*(1+F17)+G17 | J17: =C17*H17-I17 | K17: =IFERROR(J17/(C17*H17),0)
A18: Back-End Lead | B18: S1 | C18: 75 | D18: 5275 | E18: 31.4 | F18: 0.1 | G18: 2542 | H18: 168 | I18: =D18*(1+F18)+G18 | J18: =C18*H18-I18 | K18: =IFERROR(J18/(C18*H18),0)
A19: Back-End | B19: M2 | C19: 55 | D19: 3936 | E19: 23.43 | F19: 0.1 | G19: 2542 | H19: 168 | I19: =D19*(1+F19)+G19 | J19: =C19*H19-I19 | K19: =IFERROR(J19/(C19*H19),0)
A20: Back-End Junior | B20: J2 | C20: 48 | D20: 1500 | E20: 8.93 | F20: 0.1 | G20: 2542 | H20: 168 | I20: =D20*(1+F20)+G20 | J20: =C20*H20-I20 | K20: =IFERROR(J20/(C20*H20),0)
... A25: DevOps | B25: S1 | C25: 70 | D25: 6368 | E25: 37.9 | F25: 0.1 | G25: 2542 | H25: 168 | I25: =D25*(1+F25)+G25 | J25: =C25*H25-I25 | K25: =IFERROR(J25/(C25*H25),0)
A27: Project Totals | I27: =SUM(I9:I25) | J27: =SUM(J9:J25)
A29: Project Profitability (build) | B29: =IFERROR(('Headcount and Cost'!B12-I27)/'Headcount and Cost'!B12,0) | C29: (Total Cost - Sum Internal Cost) / Total Cost
A30: Seniority Index (avg) | B30: =AVERAGEIFS(C9:C25,C9:C25,">0")/RefRate | C30: ratio of avg ext rate to fallback blended rate

Sheet Headcount and Cost
A1: Headcount and Cost — Resource allocation grid
A2: Purpose: | B2: The single source of truth for staffing. Each row is one resource with Role / Seniority / Location / Headcount / Allocation / Start & End Week. Allocated Hours and Allocated Cost are computed; rate is looked up on the Rates tab. The right-hand 'Estimated vs Allocated' panel reconciles allocation against the discipline totals computed on Buffers.
A3: How to use: | B3: (1) For each resource, COPY a sample row and modify. Multiple rows with the same Role are supported (e.g. 5 BE seniors + 3 BE mids). (2) Headcount = number of physical people. Allocation = % of full time (1.0 = 100%). FTE = Headcount * Allocation (computed). (3) Start Week / End Week define when the resource is on the project; Duration = End - Start + 1; Allocated Hours = Duration * FTE * 40. (4) Allocated Cost looks up rate via INDEX/MATCH on (Role, Seniority, Location); falls back to RefRate ($/h on Input Data) if no rate row matches. (5) The 'Delta Hours' column on the right shows over/under allocation per role. Aim to keep |Delta| small relative to Estimated.
A4: Inputs: | B4: Per-resource Role/Seniority/Location/Headcount/Allocation/Start/End. Rates tab. Input Data RefRate fallback. Buffers Grand Total per role (Estimated Hours).
A5: Outputs: | B5: Total Hours, Total Cost, Peak Headcount, Peak FTE, Duration Weeks. Per-row Allocated Cost feeds Monthly Cost Roll-out and Internal Cost & Profitability.
A6: Linked tabs: | B6: Rates (rate lookup). Buffers & Non-Dev Activities (Estimated hours). Monthly Cost Roll-out. Internal Cost & Profitability.
A7: Project Summary | L7: Role | M7: Estimated Hours | N7: Allocated Hours | O7: Allocated FTE | P7: Delta Hours | Q7: Remaining FTE | R7: Remaining Weeks
A8: Peak Headcount | B8: =SUM(B18:B218) | L8: Back-End | M8: =IFERROR(VLOOKUP("Back-End",'Buffers & Non-Dev Activities'!$A:$L,12,FALSE),0) | N8: =SUMIF($A$18:$A$218,L8,$H$18:$H$218) | O8: =SUMIF($A$18:$A$218,L8,$D$18:$D$218) | P8: =N8-M8 | Q8: =IFERROR(MAX(0,(M8-N8)/40),0)
A9: Peak FTE | B9: =SUM(D18:D218) | L9: Front-End | M9: =IFERROR(VLOOKUP("Front-End",'Buffers & Non-Dev Activities'!$A:$L,12,FALSE),0) | N9: =SUMIF($A$18:$A$218,L9,$H$18:$H$218) | O9: =SUMIF($A$18:$A$218,L9,$D$18:$D$218) | P9: =N9-M9 | Q9: =IFERROR(MAX(0,(M9-N9)/40),0)
A10: Duration Weeks | B10: =IFERROR(MAX(F18:F218)-MIN(E18:E218)+1,0) | L10: Manual QA | M10: =IFERROR(VLOOKUP("Manual QA",'Buffers & Non-Dev Activities'!$A:$L,12,FALSE),0) | N10: =SUMIF($A$18:$A$218,L10,$H$18:$H$218) | O10: =SUMIF($A$18:$A$218,L10,$D$18:$D$218) | P10: =N10-M10 | Q10: =IFERROR(MAX(0,(M10-N10)/40),0)
A11: Total Hours | B11: =SUM(H18:H218) | L11: AQA | M11: =IFERROR(VLOOKUP("AQA",'Buffers & Non-Dev Activities'!$A:$L,12,FALSE),0) | N11: =SUMIF($A$18:$A$218,L11,$H$18:$H$218) | O11: =SUMIF($A$18:$A$218,L11,$D$18:$D$218) | P11: =N11-M11 | Q11: =IFERROR(MAX(0,(M11-N11)/40),0)
A12: Total Cost | B12: =SUM(I18:I218) | L12: BA | M12: =IFERROR(VLOOKUP("BA",'Buffers & Non-Dev Activities'!$A:$L,12,FALSE),0) | N12: =SUMIF($A$18:$A$218,L12,$H$18:$H$218) | O12: =SUMIF($A$18:$A$218,L12,$D$18:$D$218) | P12: =N12-M12 | Q12: =IFERROR(MAX(0,(M12-N12)/40),0)
A13: Avg Rate (blended) | B13: =IFERROR(B12/B11,RefRate) | L13: Architecture (SA+SwA) | M13: =IFERROR(VLOOKUP("Architecture",'Buffers & Non-Dev Activities'!$A:$L,12,FALSE),0) | N13: =SUMIF($A$18:$A$218,L13,$H$18:$H$218) | O13: =SUMIF($A$18:$A$218,L13,$D$18:$D$218) | P13: =N13-M13 | Q13: =IFERROR(MAX(0,(M13-N13)/40),0)
L14: DevOps | M14: =IFERROR(VLOOKUP("DevOps",'Buffers & Non-Dev Activities'!$A:$L,12,FALSE),0) | N14: =SUMIF($A$18:$A$218,L14,$H$18:$H$218) | O14: =SUMIF($A$18:$A$218,L14,$D$18:$D$218) | P14: =N14-M14 | Q14: =IFERROR(MAX(0,(M14-N14)/40),0)
L15: PM | M15: =IFERROR(VLOOKUP("PM",'Buffers & Non-Dev Activities'!$A:$L,12,FALSE),0) | N15: =SUMIF($A$18:$A$218,L15,$H$18:$H$218) | O15: =SUMIF($A$18:$A$218,L15,$D$18:$D$218) | P15: =N15-M15 | Q15: =IFERROR(MAX(0,(M15-N15)/40),0)
A16: Resources (enter by copying a row, then edit) | L16: UI/UX | M16: =IFERROR(VLOOKUP("UI/UX",'Buffers & Non-Dev Activities'!$A:$L,12,FALSE),0) | N16: =SUMIF($A$18:$A$218,L16,$H$18:$H$218) | O16: =SUMIF($A$18:$A$218,L16,$D$18:$D$218) | P16: =N16-M16 | Q16: =IFERROR(MAX(0,(M16-N16)/40),0)
A17: Role | B17: Headcount | C17: Allocation | D17: FTE | E17: Start Week | F17: End Week | G17: Duration | H17: Allocated Hours | I17: Allocated Cost | J17: Seniority | K17: Location
A18: Back-End | B18: 5 | C18: 1 | D18: =B18*C18 | E18: 1 | F18: 8 | G18: =F18-E18+1 | H18: =G18*D18*40 | I18: {=H18*IFERROR(INDEX(Rates!$D:$D,MATCH(1,(Rates!$A:$A=A18)*(Rates!$B:$B=J18)*(Rates!$C:$C=K18),0)),RefRate)} | J18: S1 | K18: Poland
A19: Back-End | B19: 3 | C19: 1 | D19: =B19*C19 | E19: 3 | F19: 8 | G19: =F19-E19+1 | H19: =G19*D19*40 | I19: {=H19*IFERROR(INDEX(Rates!$D:$D,MATCH(1,(Rates!$A:$A=A19)*(Rates!$B:$B=J19)*(Rates!$C:$C=K19),0)),RefRate)} | J19: M2 | K19: Poland
A20: Front-End Web | B20: 1 | C20: 1 | D20: =B20*C20 | E20: 1 | F20: 4 | G20: =F20-E20+1 | H20: =G20*D20*40 | I20: {=H20*IFERROR(INDEX(Rates!$D:$D,MATCH(1,(Rates!$A:$A=A20)*(Rates!$B:$B=J20)*(Rates!$C:$C=K20),0)),RefRate)} | J20: Lead | K20: Poland
A21: Front-End Mobile | B21: 1 | C21: 1 | D21: =B21*C21 | E21: 1 | F21: 8 | G21: =F21-E21+1 | H21: =G21*D21*40 | I21: {=H21*IFERROR(INDEX(Rates!$D:$D,MATCH(1,(Rates!$A:$A=A21)*(Rates!$B:$B=J21)*(Rates!$C:$C=K21),0)),RefRate)} | J21: S1 | K21: Poland
A22: Manual QA | B22: 1 | C22: 1 | D22: =B22*C22 | E22: 1 | F22: 8 | G22: =F22-E22+1 | H22: =G22*D22*40 | I22: {=H22*IFERROR(INDEX(Rates!$D:$D,MATCH(1,(Rates!$A:$A=A22)*(Rates!$B:$B=J22)*(Rates!$C:$C=K22),0)),RefRate)} | J22: S1 | K22: Poland
A23: Manual QA | B23: 1 | C23: 0.5 | D23: =B23*C23 | E23: 1 | F23: 8 | G23: =F23-E23+1 | H23: =G23*D23*40 | I23: {=H23*IFERROR(INDEX(Rates!$D:$D,MATCH(1,(Rates!$A:$A=A23)*(Rates!$B:$B=J23)*(Rates!$C:$C=K23),0)),RefRate)} | J23: M1 | K23: Poland
A24: AQA | B24: 1 | C24: 0.5 | D24: =B24*C24 | E24: 1 | F24: 8 | G24: =F24-E24+1 | H24: =G24*D24*40 | I24: {=H24*IFERROR(INDEX(Rates!$D:$D,MATCH(1,(Rates!$A:$A=A24)*(Rates!$B:$B=J24)*(Rates!$C:$C=K24),0)),RefRate)} | J24: M2 | K24: Poland
A25: PM | B25: 1 | C25: 0.5 | D25: =B25*C25 | E25: 1 | F25: 8 | G25: =F25-E25+1 | H25: =G25*D25*40 | I25: {=H25*IFERROR(INDEX(Rates!$D:$D,MATCH(1,(Rates!$A:$A=A25)*(Rates!$B:$B=J25)*(Rates!$C:$C=K25),0)),RefRate)} | J25: M1 | K25: Poland
A26: BA | B26: 1 | C26: 0.5 | D26: =B26*C26 | E26: 1 | F26: 8 | G26: =F26-E26+1 | H26: =G26*D26*40 | I26: {=H26*IFERROR(INDEX(Rates!$D:$D,MATCH(1,(Rates!$A:$A=A26)*(Rates!$B:$B=J26)*(Rates!$C:$C=K26),0)),RefRate)} | J26: S1 | K26: Poland
A27: Solution Architect | B27: 1 | C27: 1 | D27: =B27*C27 | E27: 1 | F27: 8 | G27: =F27-E27+1 | H27: =G27*D27*40 | I27: {=H27*IFERROR(INDEX(Rates!$D:$D,MATCH(1,(Rates!$A:$A=A27)*(Rates!$B:$B=J27)*(Rates!$C:$C=K27),0)),RefRate)} | J27: S1 | K27: Poland
A28: UI/UX | B28: 1 | C28: 1 | D28: =B28*C28 | E28: 1 | F28: 3 | G28: =F28-E28+1 | H28: =G28*D28*40 | I28: {=H28*IFERROR(INDEX(Rates!$D:$D,MATCH(1,(Rates!$A:$A=A28)*(Rates!$B:$B=J28)*(Rates!$C:$C=K28),0)),RefRate)} | J28: M3 | K28: Poland
A29: DevOps | B29: 1 | C29: 1 | D29: =B29*C29 | E29: 1 | F29: 8 | G29: =F29-E29+1 | H29: =G29*D29*40 | I29: {=H29*IFERROR(INDEX(Rates!$D:$D,MATCH(1,(Rates!$A:$A=A29)*(Rates!$B:$B=J29)*(Rates!$C:$C=K29),0)),RefRate)} | J29: S1 | K29: Poland

Sheet Monthly Cost Roll-out
A1: Monthly Cost Roll-out
A2: Purpose: | B2: Cash-flow / spend curve. Spreads each resource's Allocated Cost across calendar months proportional to the weeks of [Start Week, End Week] that fall in each month (month width = 4.33 weeks).
A3: How to use: | B3: (1) The first 12 sample rows mirror the seeded resources on Headcount and Cost. (2) When you add resources there, copy a row here and update the row index in the 'Headcount and Cost' references. (3) The TOTAL row at the bottom gives spend per month — useful for cash-flow conversations and to validate the project duration.
A4: Inputs: | B4: Allocated Cost, Start Week, End Week, Duration from Headcount and Cost.
A5: Outputs: | B5: Per-resource and total spend by month (M1 .. M18).
A6: Linked tabs: | B6: Headcount and Cost (single source of staffing & cost).
A8: Resource (from Headcount and Cost) | B8: Total Allocated, $ | C8: M1 | D8: M2 | E8: M3 | F8: M4 | G8: M5 | H8: M6 | I8: M7 | J8: M8 | K8: M9 | L8: M10 | M8: M11 | N8: M12 | O8: M13 | P8: M14 | Q8: M15 | R8: M16 | S8: M17 | T8: M18
A9: =IF('Headcount and Cost'!A18="","",'Headcount and Cost'!A18&" - "&'Headcount and Cost'!J18) | B9: ='Headcount and Cost'!I18 | C9: =MAX(0,MIN('Headcount and Cost'!F18,4.33)-MAX('Headcount and Cost'!E18-1,0))*IFERROR('Headcount and Cost'!I18/('Headcount and Cost'!G18),0) | D9: =MAX(0,MIN('Headcount and Cost'!F18,8.66)-MAX('Headcount and Cost'!E18-1,4.33))*IFERROR('Headcount and Cost'!I18/('Headcount and Cost'!G18),0) | E9: =MAX(0,MIN('Headcount and Cost'!F18,12.99)-MAX('Headcount and Cost'!E18-1,8.66))*IFERROR('Headcount and Cost'!I18/('Headcount and Cost'!G18),0) | F9: =MAX(0,MIN('Headcount and Cost'!F18,17.32)-MAX('Headcount and Cost'!E18-1,12.99))*IFERROR('Headcount and Cost'!I18/('Headcount and Cost'!G18),0) | G9: =MAX(0,MIN('Headcount and Cost'!F18,21.65)-MAX('Headcount and Cost'!E18-1,17.32))*IFERROR('Headcount and Cost'!I18/('Headcount and Cost'!G18),0) | H9: =MAX(0,MIN('Headcount and Cost'!F18,25.98)-MAX('Headcount and Cost'!E18-1,21.65))*IFERROR('Headcount and Cost'!I18/('Headcount and Cost'!G18),0) | I9: =MAX(0,MIN('Headcount and Cost'!F18,30.31)-MAX('Headcount and Cost'!E18-1,25.98))*IFERROR('Headcount and Cost'!I18/('Headcount and Cost'!G18),0) | J9: =MAX(0,MIN('Headcount and Cost'!F18,34.64)-MAX('Headcount and Cost'!E18-1,30.31))*IFERROR('Headcount and Cost'!I18/('Headcount and Cost'!G18),0) | K9: =MAX(0,MIN('Headcount and Cost'!F18,38.97)-MAX('Headcount and Cost'!E18-1,34.64))*IFERROR('Headcount and Cost'!I18/('Headcount and Cost'!G18),0) | L9: =MAX(0,MIN('Headcount and Cost'!F18,43.3)-MAX('Headcount and Cost'!E18-1,38.97))*IFERROR('Headcount and Cost'!I18/('Headcount and Cost'!G18),0) | M9: =MAX(0,MIN('Headcount and Cost'!F18,47.63)-MAX('Headcount and Cost'!E18-1,43.3))*IFERROR('Headcount and Cost'!I18/('Headcount and Cost'!G18),0) | N9: =MAX(0,MIN('Headcount and Cost'!F18,51.96)-MAX('Headcount and Cost'!E18-1,47.63))*IFERROR('Headcount and Cost'!I18/('Headcount and Cost'!G18),0) | O9: =MAX(0,MIN('Headcount and Cost'!F18,56.29)-MAX('Headcount and Cost'!E18-1,51.96))*IFERROR('Headcount and Cost'!I18/('Headcount and Cost'!G18),0) | P9: =MAX(0,MIN('Headcount and Cost'!F18,60.62)-MAX('Headcount and Cost'!E18-1,56.29))*IFERROR('Headcount and Cost'!I18/('Headcount and Cost'!G18),0) | Q9: =MAX(0,MIN('Headcount and Cost'!F18,64.95)-MAX('Headcount and Cost'!E18-1,60.62))*IFERROR('Headcount and Cost'!I18/('Headcount and Cost'!G18),0) | R9: =MAX(0,MIN('Headcount and Cost'!F18,69.28)-MAX('Headcount and Cost'!E18-1,64.95))*IFERROR('Headcount and Cost'!I18/('Headcount and Cost'!G18),0) | S9: =MAX(0,MIN('Headcount and Cost'!F18,73.61)-MAX('Headcount and Cost'!E18-1,69.28))*IFERROR('Headcount and Cost'!I18/('Headcount and Cost'!G18),0) | T9: =MAX(0,MIN('Headcount and Cost'!F18,77.94)-MAX('Headcount and Cost'!E18-1,73.61))*IFERROR('Headcount and Cost'!I18/('Headcount and Cost'!G18),0)
A10: =IF('Headcount and Cost'!A19="","",'Headcount and Cost'!A19&" - "&'Headcount and Cost'!J19) | B10: ='Headcount and Cost'!I19 | C10: =MAX(0,MIN('Headcount and Cost'!F19,4.33)-MAX('Headcount and Cost'!E19-1,0))*IFERROR('Headcount and Cost'!I19/('Headcount and Cost'!G19),0) | D10: =MAX(0,MIN('Headcount and Cost'!F19,8.66)-MAX('Headcount and Cost'!E19-1,4.33))*IFERROR('Headcount and Cost'!I19/('Headcount and Cost'!G19),0) | E10: =MAX(0,MIN('Headcount and Cost'!F19,12.99)-MAX('Headcount and Cost'!E19-1,8.66))*IFERROR('Headcount and Cost'!I19/('Headcount and Cost'!G19),0) | F10: =MAX(0,MIN('Headcount and Cost'!F19,17.32)-MAX('Headcount and Cost'!E19-1,12.99))*IFERROR('Headcount and Cost'!I19/('Headcount and Cost'!G19),0) | G10: =MAX(0,MIN('Headcount and Cost'!F19,21.65)-MAX('Headcount and Cost'!E19-1,17.32))*IFERROR('Headcount and Cost'!I19/('Headcount and Cost'!G19),0) | H10: =MAX(0,MIN('Headcount and Cost'!F19,25.98)-MAX('Headcount and Cost'!E19-1,21.65))*IFERROR('Headcount and Cost'!I19/('Headcount and Cost'!G19),0) | I10: =MAX(0,MIN('Headcount and Cost'!F19,30.31)-MAX('Headcount and Cost'!E19-1,25.98))*IFERROR('Headcount and Cost'!I19/('Headcount and Cost'!G19),0) | J10: =MAX(0,MIN('Headcount and Cost'!F19,34.64)-MAX('Headcount and Cost'!E19-1,30.31))*IFERROR('Headcount and Cost'!I19/('Headcount and Cost'!G19),0) | K10: =MAX(0,MIN('Headcount and Cost'!F19,38.97)-MAX('Headcount and Cost'!E19-1,34.64))*IFERROR('Headcount and Cost'!I19/('Headcount and Cost'!G19),0) | L10: =MAX(0,MIN('Headcount and Cost'!F19,43.3)-MAX('Headcount and Cost'!E19-1,38.97))*IFERROR('Headcount and Cost'!I19/('Headcount and Cost'!G19),0) | M10: =MAX(0,MIN('Headcount and Cost'!F19,47.63)-MAX('Headcount and Cost'!E19-1,43.3))*IFERROR('Headcount and Cost'!I19/('Headcount and Cost'!G19),0) | N10: =MAX(0,MIN('Headcount and Cost'!F19,51.96)-MAX('Headcount and Cost'!E19-1,47.63))*IFERROR('Headcount and Cost'!I19/('Headcount and Cost'!G19),0) | O10: =MAX(0,MIN('Headcount and Cost'!F19,56.29)-MAX('Headcount and Cost'!E19-1,51.96))*IFERROR('Headcount and Cost'!I19/('Headcount and Cost'!G19),0) | P10: =MAX(0,MIN('Headcount and Cost'!F19,60.62)-MAX('Headcount and Cost'!E19-1,56.29))*IFERROR('Headcount and Cost'!I19/('Headcount and Cost'!G19),0) | Q10: =MAX(0,MIN('Headcount and Cost'!F19,64.95)-MAX('Headcount and Cost'!E19-1,60.62))*IFERROR('Headcount and Cost'!I19/('Headcount and Cost'!G19),0) | R10: =MAX(0,MIN('Headcount and Cost'!F19,69.28)-MAX('Headcount and Cost'!E19-1,64.95))*IFERROR('Headcount and Cost'!I19/('Headcount and Cost'!G19),0) | S10: =MAX(0,MIN('Headcount and Cost'!F19,73.61)-MAX('Headcount and Cost'!E19-1,69.28))*IFERROR('Headcount and Cost'!I19/('Headcount and Cost'!G19),0) | T10: =MAX(0,MIN('Headcount and Cost'!F19,77.94)-MAX('Headcount and Cost'!E19-1,73.61))*IFERROR('Headcount and Cost'!I19/('Headcount and Cost'!G19),0)
A11: =IF('Headcount and Cost'!A20="","",'Headcount and Cost'!A20&" - "&'Headcount and Cost'!J20) | B11: ='Headcount and Cost'!I20 | C11: =MAX(0,MIN('Headcount and Cost'!F20,4.33)-MAX('Headcount and Cost'!E20-1,0))*IFERROR('Headcount and Cost'!I20/('Headcount and Cost'!G20),0) | D11: =MAX(0,MIN('Headcount and Cost'!F20,8.66)-MAX('Headcount and Cost'!E20-1,4.33))*IFERROR('Headcount and Cost'!I20/('Headcount and Cost'!G20),0) | E11: =MAX(0,MIN('Headcount and Cost'!F20,12.99)-MAX('Headcount and Cost'!E20-1,8.66))*IFERROR('Headcount and Cost'!I20/('Headcount and Cost'!G20),0) | F11: =MAX(0,MIN('Headcount and Cost'!F20,17.32)-MAX('Headcount and Cost'!E20-1,12.99))*IFERROR('Headcount and Cost'!I20/('Headcount and Cost'!G20),0) | G11: =MAX(0,MIN('Headcount and Cost'!F20,21.65)-MAX('Headcount and Cost'!E20-1,17.32))*IFERROR('Headcount and Cost'!I20/('Headcount and Cost'!G20),0) | H11: =MAX(0,MIN('Headcount and Cost'!F20,25.98)-MAX('Headcount and Cost'!E20-1,21.65))*IFERROR('Headcount and Cost'!I20/('Headcount and Cost'!G20),0) | I11: =MAX(0,MIN('Headcount and Cost'!F20,30.31)-MAX('Headcount and Cost'!E20-1,25.98))*IFERROR('Headcount and Cost'!I20/('Headcount and Cost'!G20),0) | J11: =MAX(0,MIN('Headcount and Cost'!F20,34.64)-MAX('Headcount and Cost'!E20-1,30.31))*IFERROR('Headcount and Cost'!I20/('Headcount and Cost'!G20),0) | K11: =MAX(0,MIN('Headcount and Cost'!F20,38.97)-MAX('Headcount and Cost'!E20-1,34.64))*IFERROR('Headcount and Cost'!I20/('Headcount and Cost'!G20),0) | L11: =MAX(0,MIN('Headcount and Cost'!F20,43.3)-MAX('Headcount and Cost'!E20-1,38.97))*IFERROR('Headcount and Cost'!I20/('Headcount and Cost'!G20),0) | M11: =MAX(0,MIN('Headcount and Cost'!F20,47.63)-MAX('Headcount and Cost'!E20-1,43.3))*IFERROR('Headcount and Cost'!I20/('Headcount and Cost'!G20),0) | N11: =MAX(0,MIN('Headcount and Cost'!F20,51.96)-MAX('Headcount and Cost'!E20-1,47.63))*IFERROR('Headcount and Cost'!I20/('Headcount and Cost'!G20),0) | O11: =MAX(0,MIN('Headcount and Cost'!F20,56.29)-MAX('Headcount and Cost'!E20-1,51.96))*IFERROR('Headcount and Cost'!I20/('Headcount and Cost'!G20),0) | P11: =MAX(0,MIN('Headcount and Cost'!F20,60.62)-MAX('Headcount and Cost'!E20-1,56.29))*IFERROR('Headcount and Cost'!I20/('Headcount and Cost'!G20),0) | Q11: =MAX(0,MIN('Headcount and Cost'!F20,64.95)-MAX('Headcount and Cost'!E20-1,60.62))*IFERROR('Headcount and Cost'!I20/('Headcount and Cost'!G20),0) | R11: =MAX(0,MIN('Headcount and Cost'!F20,69.28)-MAX('Headcount and Cost'!E20-1,64.95))*IFERROR('Headcount and Cost'!I20/('Headcount and Cost'!G20),0) | S11: =MAX(0,MIN('Headcount and Cost'!F20,73.61)-MAX('Headcount and Cost'!E20-1,69.28))*IFERROR('Headcount and Cost'!I20/('Headcount and Cost'!G20),0) | T11: =MAX(0,MIN('Headcount and Cost'!F20,77.94)-MAX('Headcount and Cost'!E20-1,73.61))*IFERROR('Headcount and Cost'!I20/('Headcount and Cost'!G20),0)
A12: =IF('Headcount and Cost'!A21="","",'Headcount and Cost'!A21&" - "&'Headcount and Cost'!J21) | B12: ='Headcount and Cost'!I21 | C12: =MAX(0,MIN('Headcount and Cost'!F21,4.33)-MAX('Headcount and Cost'!E21-1,0))*IFERROR('Headcount and Cost'!I21/('Headcount and Cost'!G21),0) | D12: =MAX(0,MIN('Headcount and Cost'!F21,8.66)-MAX('Headcount and Cost'!E21-1,4.33))*IFERROR('Headcount and Cost'!I21/('Headcount and Cost'!G21),0) | E12: =MAX(0,MIN('Headcount and Cost'!F21,12.99)-MAX('Headcount and Cost'!E21-1,8.66))*IFERROR('Headcount and Cost'!I21/('Headcount and Cost'!G21),0) | F12: =MAX(0,MIN('Headcount and Cost'!F21,17.32)-MAX('Headcount and Cost'!E21-1,12.99))*IFERROR('Headcount and Cost'!I21/('Headcount and Cost'!G21),0) | G12: =MAX(0,MIN('Headcount and Cost'!F21,21.65)-MAX('Headcount and Cost'!E21-1,17.32))*IFERROR('Headcount and Cost'!I21/('Headcount and Cost'!G21),0) | H12: =MAX(0,MIN('Headcount and Cost'!F21,25.98)-MAX('Headcount and Cost'!E21-1,21.65))*IFERROR('Headcount and Cost'!I21/('Headcount and Cost'!G21),0) | I12: =MAX(0,MIN('Headcount and Cost'!F21,30.31)-MAX('Headcount and Cost'!E21-1,25.98))*IFERROR('Headcount and Cost'!I21/('Headcount and Cost'!G21),0) | J12: =MAX(0,MIN('Headcount and Cost'!F21,34.64)-MAX('Headcount and Cost'!E21-1,30.31))*IFERROR('Headcount and Cost'!I21/('Headcount and Cost'!G21),0) | K12: =MAX(0,MIN('Headcount and Cost'!F21,38.97)-MAX('Headcount and Cost'!E21-1,34.64))*IFERROR('Headcount and Cost'!I21/('Headcount and Cost'!G21),0) | L12: =MAX(0,MIN('Headcount and Cost'!F21,43.3)-MAX('Headcount and Cost'!E21-1,38.97))*IFERROR('Headcount and Cost'!I21/('Headcount and Cost'!G21),0) | M12: =MAX(0,MIN('Headcount and Cost'!F21,47.63)-MAX('Headcount and Cost'!E21-1,43.3))*IFERROR('Headcount and Cost'!I21/('Headcount and Cost'!G21),0) | N12: =MAX(0,MIN('Headcount and Cost'!F21,51.96)-MAX('Headcount and Cost'!E21-1,47.63))*IFERROR('Headcount and Cost'!I21/('Headcount and Cost'!G21),0) | O12: =MAX(0,MIN('Headcount and Cost'!F21,56.29)-MAX('Headcount and Cost'!E21-1,51.96))*IFERROR('Headcount and Cost'!I21/('Headcount and Cost'!G21),0) | P12: =MAX(0,MIN('Headcount and Cost'!F21,60.62)-MAX('Headcount and Cost'!E21-1,56.29))*IFERROR('Headcount and Cost'!I21/('Headcount and Cost'!G21),0) | Q12: =MAX(0,MIN('Headcount and Cost'!F21,64.95)-MAX('Headcount and Cost'!E21-1,60.62))*IFERROR('Headcount and Cost'!I21/('Headcount and Cost'!G21),0) | R12: =MAX(0,MIN('Headcount and Cost'!F21,69.28)-MAX('Headcount and Cost'!E21-1,64.95))*IFERROR('Headcount and Cost'!I21/('Headcount and Cost'!G21),0) | S12: =MAX(0,MIN('Headcount and Cost'!F21,73.61)-MAX('Headcount and Cost'!E21-1,69.28))*IFERROR('Headcount and Cost'!I21/('Headcount and Cost'!G21),0) | T12: =MAX(0,MIN('Headcount and Cost'!F21,77.94)-MAX('Headcount and Cost'!E21-1,73.61))*IFERROR('Headcount and Cost'!I21/('Headcount and Cost'!G21),0)
A13: =IF('Headcount and Cost'!A22="","",'Headcount and Cost'!A22&" - "&'Headcount and Cost'!J22) | B13: ='Headcount and Cost'!I22 | C13: =MAX(0,MIN('Headcount and Cost'!F22,4.33)-MAX('Headcount and Cost'!E22-1,0))*IFERROR('Headcount and Cost'!I22/('Headcount and Cost'!G22),0) | D13: =MAX(0,MIN('Headcount and Cost'!F22,8.66)-MAX('Headcount and Cost'!E22-1,4.33))*IFERROR('Headcount and Cost'!I22/('Headcount and Cost'!G22),0) | E13: =MAX(0,MIN('Headcount and Cost'!F22,12.99)-MAX('Headcount and Cost'!E22-1,8.66))*IFERROR('Headcount and Cost'!I22/('Headcount and Cost'!G22),0) | F13: =MAX(0,MIN('Headcount and Cost'!F22,17.32)-MAX('Headcount and Cost'!E22-1,12.99))*IFERROR('Headcount and Cost'!I22/('Headcount and Cost'!G22),0) | G13: =MAX(0,MIN('Headcount and Cost'!F22,21.65)-MAX('Headcount and Cost'!E22-1,17.32))*IFERROR('Headcount and Cost'!I22/('Headcount and Cost'!G22),0) | H13: =MAX(0,MIN('Headcount and Cost'!F22,25.98)-MAX('Headcount and Cost'!E22-1,21.65))*IFERROR('Headcount and Cost'!I22/('Headcount and Cost'!G22),0) | I13: =MAX(0,MIN('Headcount and Cost'!F22,30.31)-MAX('Headcount and Cost'!E22-1,25.98))*IFERROR('Headcount and Cost'!I22/('Headcount and Cost'!G22),0) | J13: =MAX(0,MIN('Headcount and Cost'!F22,34.64)-MAX('Headcount and Cost'!E22-1,30.31))*IFERROR('Headcount and Cost'!I22/('Headcount and Cost'!G22),0) | K13: =MAX(0,MIN('Headcount and Cost'!F22,38.97)-MAX('Headcount and Cost'!E22-1,34.64))*IFERROR('Headcount and Cost'!I22/('Headcount and Cost'!G22),0) | L13: =MAX(0,MIN('Headcount and Cost'!F22,43.3)-MAX('Headcount and Cost'!E22-1,38.97))*IFERROR('Headcount and Cost'!I22/('Headcount and Cost'!G22),0) | M13: =MAX(0,MIN('Headcount and Cost'!F22,47.63)-MAX('Headcount and Cost'!E22-1,43.3))*IFERROR('Headcount and Cost'!I22/('Headcount and Cost'!G22),0) | N13: =MAX(0,MIN('Headcount and Cost'!F22,51.96)-MAX('Headcount and Cost'!E22-1,47.63))*IFERROR('Headcount and Cost'!I22/('Headcount and Cost'!G22),0) | O13: =MAX(0,MIN('Headcount and Cost'!F22,56.29)-MAX('Headcount and Cost'!E22-1,51.96))*IFERROR('Headcount and Cost'!I22/('Headcount and Cost'!G22),0) | P13: =MAX(0,MIN('Headcount and Cost'!F22,60.62)-MAX('Headcount and Cost'!E22-1,56.29))*IFERROR('Headcount and Cost'!I22/('Headcount and Cost'!G22),0) | Q13: =MAX(0,MIN('Headcount and Cost'!F22,64.95)-MAX('Headcount and Cost'!E22-1,60.62))*IFERROR('Headcount and Cost'!I22/('Headcount and Cost'!G22),0) | R13: =MAX(0,MIN('Headcount and Cost'!F22,69.28)-MAX('Headcount and Cost'!E22-1,64.95))*IFERROR('Headcount and Cost'!I22/('Headcount and Cost'!G22),0) | S13: =MAX(0,MIN('Headcount and Cost'!F22,73.61)-MAX('Headcount and Cost'!E22-1,69.28))*IFERROR('Headcount and Cost'!I22/('Headcount and Cost'!G22),0) | T13: =MAX(0,MIN('Headcount and Cost'!F22,77.94)-MAX('Headcount and Cost'!E22-1,73.61))*IFERROR('Headcount and Cost'!I22/('Headcount and Cost'!G22),0)
A14: =IF('Headcount and Cost'!A23="","",'Headcount and Cost'!A23&" - "&'Headcount and Cost'!J23) | B14: ='Headcount and Cost'!I23 | C14: =MAX(0,MIN('Headcount and Cost'!F23,4.33)-MAX('Headcount and Cost'!E23-1,0))*IFERROR('Headcount and Cost'!I23/('Headcount and Cost'!G23),0) | D14: =MAX(0,MIN('Headcount and Cost'!F23,8.66)-MAX('Headcount and Cost'!E23-1,4.33))*IFERROR('Headcount and Cost'!I23/('Headcount and Cost'!G23),0) | E14: =MAX(0,MIN('Headcount and Cost'!F23,12.99)-MAX('Headcount and Cost'!E23-1,8.66))*IFERROR('Headcount and Cost'!I23/('Headcount and Cost'!G23),0) | F14: =MAX(0,MIN('Headcount and Cost'!F23,17.32)-MAX('Headcount and Cost'!E23-1,12.99))*IFERROR('Headcount and Cost'!I23/('Headcount and Cost'!G23),0) | G14: =MAX(0,MIN('Headcount and Cost'!F23,21.65)-MAX('Headcount and Cost'!E23-1,17.32))*IFERROR('Headcount and Cost'!I23/('Headcount and Cost'!G23),0) | H14: =MAX(0,MIN('Headcount and Cost'!F23,25.98)-MAX('Headcount and Cost'!E23-1,21.65))*IFERROR('Headcount and Cost'!I23/('Headcount and Cost'!G23),0) | I14: =MAX(0,MIN('Headcount and Cost'!F23,30.31)-MAX('Headcount and Cost'!E23-1,25.98))*IFERROR('Headcount and Cost'!I23/('Headcount and Cost'!G23),0) | J14: =MAX(0,MIN('Headcount and Cost'!F23,34.64)-MAX('Headcount and Cost'!E23-1,30.31))*IFERROR('Headcount and Cost'!I23/('Headcount and Cost'!G23),0) | K14: =MAX(0,MIN('Headcount and Cost'!F23,38.97)-MAX('Headcount and Cost'!E23-1,34.64))*IFERROR('Headcount and Cost'!I23/('Headcount and Cost'!G23),0) | L14: =MAX(0,MIN('Headcount and Cost'!F23,43.3)-MAX('Headcount and Cost'!E23-1,38.97))*IFERROR('Headcount and Cost'!I23/('Headcount and Cost'!G23),0) | M14: =MAX(0,MIN('Headcount and Cost'!F23,47.63)-MAX('Headcount and Cost'!E23-1,43.3))*IFERROR('Headcount and Cost'!I23/('Headcount and Cost'!G23),0) | N14: =MAX(0,MIN('Headcount and Cost'!F23,51.96)-MAX('Headcount and Cost'!E23-1,47.63))*IFERROR('Headcount and Cost'!I23/('Headcount and Cost'!G23),0) | O14: =MAX(0,MIN('Headcount and Cost'!F23,56.29)-MAX('Headcount and Cost'!E23-1,51.96))*IFERROR('Headcount and Cost'!I23/('Headcount and Cost'!G23),0) | P14: =MAX(0,MIN('Headcount and Cost'!F23,60.62)-MAX('Headcount and Cost'!E23-1,56.29))*IFERROR('Headcount and Cost'!I23/('Headcount and Cost'!G23),0) | Q14: =MAX(0,MIN('Headcount and Cost'!F23,64.95)-MAX('Headcount and Cost'!E23-1,60.62))*IFERROR('Headcount and Cost'!I23/('Headcount and Cost'!G23),0) | R14: =MAX(0,MIN('Headcount and Cost'!F23,69.28)-MAX('Headcount and Cost'!E23-1,64.95))*IFERROR('Headcount and Cost'!I23/('Headcount and Cost'!G23),0) | S14: =MAX(0,MIN('Headcount and Cost'!F23,73.61)-MAX('Headcount and Cost'!E23-1,69.28))*IFERROR('Headcount and Cost'!I23/('Headcount and Cost'!G23),0) | T14: =MAX(0,MIN('Headcount and Cost'!F23,77.94)-MAX('Headcount and Cost'!E23-1,73.61))*IFERROR('Headcount and Cost'!I23/('Headcount and Cost'!G23),0)
A15: =IF('Headcount and Cost'!A24="","",'Headcount and Cost'!A24&" - "&'Headcount and Cost'!J24) | B15: ='Headcount and Cost'!I24 | C15: =MAX(0,MIN('Headcount and Cost'!F24,4.33)-MAX('Headcount and Cost'!E24-1,0))*IFERROR('Headcount and Cost'!I24/('Headcount and Cost'!G24),0) | D15: =MAX(0,MIN('Headcount and Cost'!F24,8.66)-MAX('Headcount and Cost'!E24-1,4.33))*IFERROR('Headcount and Cost'!I24/('Headcount and Cost'!G24),0) | E15: =MAX(0,MIN('Headcount and Cost'!F24,12.99)-MAX('Headcount and Cost'!E24-1,8.66))*IFERROR('Headcount and Cost'!I24/('Headcount and Cost'!G24),0) | F15: =MAX(0,MIN('Headcount and Cost'!F24,17.32)-MAX('Headcount and Cost'!E24-1,12.99))*IFERROR('Headcount and Cost'!I24/('Headcount and Cost'!G24),0) | G15: =MAX(0,MIN('Headcount and Cost'!F24,21.65)-MAX('Headcount and Cost'!E24-1,17.32))*IFERROR('Headcount and Cost'!I24/('Headcount and Cost'!G24),0) | H15: =MAX(0,MIN('Headcount and Cost'!F24,25.98)-MAX('Headcount and Cost'!E24-1,21.65))*IFERROR('Headcount and Cost'!I24/('Headcount and Cost'!G24),0) | I15: =MAX(0,MIN('Headcount and Cost'!F24,30.31)-MAX('Headcount and Cost'!E24-1,25.98))*IFERROR('Headcount and Cost'!I24/('Headcount and Cost'!G24),0) | J15: =MAX(0,MIN('Headcount and Cost'!F24,34.64)-MAX('Headcount and Cost'!E24-1,30.31))*IFERROR('Headcount and Cost'!I24/('Headcount and Cost'!G24),0) | K15: =MAX(0,MIN('Headcount and Cost'!F24,38.97)-MAX('Headcount and Cost'!E24-1,34.64))*IFERROR('Headcount and Cost'!I24/('Headcount and Cost'!G24),0) | L15: =MAX(0,MIN('Headcount and Cost'!F24,43.3)-MAX('Headcount and Cost'!E24-1,38.97))*IFERROR('Headcount and Cost'!I24/('Headcount and Cost'!G24),0) | M15: =MAX(0,MIN('Headcount and Cost'!F24,47.63)-MAX('Headcount and Cost'!E24-1,43.3))*IFERROR('Headcount and Cost'!I24/('Headcount and Cost'!G24),0) | N15: =MAX(0,MIN('Headcount and Cost'!F24,51.96)-MAX('Headcount and Cost'!E24-1,47.63))*IFERROR('Headcount and Cost'!I24/('Headcount and Cost'!G24),0) | O15: =MAX(0,MIN('Headcount and Cost'!F24,56.29)-MAX('Headcount and Cost'!E24-1,51.96))*IFERROR('Headcount and Cost'!I24/('Headcount and Cost'!G24),0) | P15: =MAX(0,MIN('Headcount and Cost'!F24,60.62)-MAX('Headcount and Cost'!E24-1,56.29))*IFERROR('Headcount and Cost'!I24/('Headcount and Cost'!G24),0) | Q15: =MAX(0,MIN('Headcount and Cost'!F24,64.95)-MAX('Headcount and Cost'!E24-1,60.62))*IFERROR('Headcount and Cost'!I24/('Headcount and Cost'!G24),0) | R15: =MAX(0,MIN('Headcount and Cost'!F24,69.28)-MAX('Headcount and Cost'!E24-1,64.95))*IFERROR('Headcount and Cost'!I24/('Headcount and Cost'!G24),0) | S15: =MAX(0,MIN('Headcount and Cost'!F24,73.61)-MAX('Headcount and Cost'!E24-1,69.28))*IFERROR('Headcount and Cost'!I24/('Headcount and Cost'!G24),0) | T15: =MAX(0,MIN('Headcount and Cost'!F24,77.94)-MAX('Headcount and Cost'!E24-1,73.61))*IFERROR('Headcount and Cost'!I24/('Headcount and Cost'!G24),0)
A16: =IF('Headcount and Cost'!A25="","",'Headcount and Cost'!A25&" - "&'Headcount and Cost'!J25) | B16: ='Headcount and Cost'!I25 | C16: =MAX(0,MIN('Headcount and Cost'!F25,4.33)-MAX('Headcount and Cost'!E25-1,0))*IFERROR('Headcount and Cost'!I25/('Headcount and Cost'!G25),0) | D16: =MAX(0,MIN('Headcount and Cost'!F25,8.66)-MAX('Headcount and Cost'!E25-1,4.33))*IFERROR('Headcount and Cost'!I25/('Headcount and Cost'!G25),0) | E16: =MAX(0,MIN('Headcount and Cost'!F25,12.99)-MAX('Headcount and Cost'!E25-1,8.66))*IFERROR('Headcount and Cost'!I25/('Headcount and Cost'!G25),0) | F16: =MAX(0,MIN('Headcount and Cost'!F25,17.32)-MAX('Headcount and Cost'!E25-1,12.99))*IFERROR('Headcount and Cost'!I25/('Headcount and Cost'!G25),0) | G16: =MAX(0,MIN('Headcount and Cost'!F25,21.65)-MAX('Headcount and Cost'!E25-1,17.32))*IFERROR('Headcount and Cost'!I25/('Headcount and Cost'!G25),0) | H16: =MAX(0,MIN('Headcount and Cost'!F25,25.98)-MAX('Headcount and Cost'!E25-1,21.65))*IFERROR('Headcount and Cost'!I25/('Headcount and Cost'!G25),0) | I16: =MAX(0,MIN('Headcount and Cost'!F25,30.31)-MAX('Headcount and Cost'!E25-1,25.98))*IFERROR('Headcount and Cost'!I25/('Headcount and Cost'!G25),0) | J16: =MAX(0,MIN('Headcount and Cost'!F25,34.64)-MAX('Headcount and Cost'!E25-1,30.31))*IFERROR('Headcount and Cost'!I25/('Headcount and Cost'!G25),0) | K16: =MAX(0,MIN('Headcount and Cost'!F25,38.97)-MAX('Headcount and Cost'!E25-1,34.64))*IFERROR('Headcount and Cost'!I25/('Headcount and Cost'!G25),0) | L16: =MAX(0,MIN('Headcount and Cost'!F25,43.3)-MAX('Headcount and Cost'!E25-1,38.97))*IFERROR('Headcount and Cost'!I25/('Headcount and Cost'!G25),0) | M16: =MAX(0,MIN('Headcount and Cost'!F25,47.63)-MAX('Headcount and Cost'!E25-1,43.3))*IFERROR('Headcount and Cost'!I25/('Headcount and Cost'!G25),0) | N16: =MAX(0,MIN('Headcount and Cost'!F25,51.96)-MAX('Headcount and Cost'!E25-1,47.63))*IFERROR('Headcount and Cost'!I25/('Headcount and Cost'!G25),0) | O16: =MAX(0,MIN('Headcount and Cost'!F25,56.29)-MAX('Headcount and Cost'!E25-1,51.96))*IFERROR('Headcount and Cost'!I25/('Headcount and Cost'!G25),0) | P16: =MAX(0,MIN('Headcount and Cost'!F25,60.62)-MAX('Headcount and Cost'!E25-1,56.29))*IFERROR('Headcount and Cost'!I25/('Headcount and Cost'!G25),0) | Q16: =MAX(0,MIN('Headcount and Cost'!F25,64.95)-MAX('Headcount and Cost'!E25-1,60.62))*IFERROR('Headcount and Cost'!I25/('Headcount and Cost'!G25),0) | R16: =MAX(0,MIN('Headcount and Cost'!F25,69.28)-MAX('Headcount and Cost'!E25-1,64.95))*IFERROR('Headcount and Cost'!I25/('Headcount and Cost'!G25),0) | S16: =MAX(0,MIN('Headcount and Cost'!F25,73.61)-MAX('Headcount and Cost'!E25-1,69.28))*IFERROR('Headcount and Cost'!I25/('Headcount and Cost'!G25),0) | T16: =MAX(0,MIN('Headcount and Cost'!F25,77.94)-MAX('Headcount and Cost'!E25-1,73.61))*IFERROR('Headcount and Cost'!I25/('Headcount and Cost'!G25),0)
A17: =IF('Headcount and Cost'!A26="","",'Headcount and Cost'!A26&" - "&'Headcount and Cost'!J26) | B17: ='Headcount and Cost'!I26 | C17: =MAX(0,MIN('Headcount and Cost'!F26,4.33)-MAX('Headcount and Cost'!E26-1,0))*IFERROR('Headcount and Cost'!I26/('Headcount and Cost'!G26),0) | D17: =MAX(0,MIN('Headcount and Cost'!F26,8.66)-MAX('Headcount and Cost'!E26-1,4.33))*IFERROR('Headcount and Cost'!I26/('Headcount and Cost'!G26),0) | E17: =MAX(0,MIN('Headcount and Cost'!F26,12.99)-MAX('Headcount and Cost'!E26-1,8.66))*IFERROR('Headcount and Cost'!I26/('Headcount and Cost'!G26),0) | F17: =MAX(0,MIN('Headcount and Cost'!F26,17.32)-MAX('Headcount and Cost'!E26-1,12.99))*IFERROR('Headcount and Cost'!I26/('Headcount and Cost'!G26),0) | G17: =MAX(0,MIN('Headcount and Cost'!F26,21.65)-MAX('Headcount and Cost'!E26-1,17.32))*IFERROR('Headcount and Cost'!I26/('Headcount and Cost'!G26),0) | H17: =MAX(0,MIN('Headcount and Cost'!F26,25.98)-MAX('Headcount and Cost'!E26-1,21.65))*IFERROR('Headcount and Cost'!I26/('Headcount and Cost'!G26),0) | I17: =MAX(0,MIN('Headcount and Cost'!F26,30.31)-MAX('Headcount and Cost'!E26-1,25.98))*IFERROR('Headcount and Cost'!I26/('Headcount and Cost'!G26),0) | J17: =MAX(0,MIN('Headcount and Cost'!F26,34.64)-MAX('Headcount and Cost'!E26-1,30.31))*IFERROR('Headcount and Cost'!I26/('Headcount and Cost'!G26),0) | K17: =MAX(0,MIN('Headcount and Cost'!F26,38.97)-MAX('Headcount and Cost'!E26-1,34.64))*IFERROR('Headcount and Cost'!I26/('Headcount and Cost'!G26),0) | L17: =MAX(0,MIN('Headcount and Cost'!F26,43.3)-MAX('Headcount and Cost'!E26-1,38.97))*IFERROR('Headcount and Cost'!I26/('Headcount and Cost'!G26),0) | M17: =MAX(0,MIN('Headcount and Cost'!F26,47.63)-MAX('Headcount and Cost'!E26-1,43.3))*IFERROR('Headcount and Cost'!I26/('Headcount and Cost'!G26),0) | N17: =MAX(0,MIN('Headcount and Cost'!F26,51.96)-MAX('Headcount and Cost'!E26-1,47.63))*IFERROR('Headcount and Cost'!I26/('Headcount and Cost'!G26),0) | O17: =MAX(0,MIN('Headcount and Cost'!F26,56.29)-MAX('Headcount and Cost'!E26-1,51.96))*IFERROR('Headcount and Cost'!I26/('Headcount and Cost'!G26),0) | P17: =MAX(0,MIN('Headcount and Cost'!F26,60.62)-MAX('Headcount and Cost'!E26-1,56.29))*IFERROR('Headcount and Cost'!I26/('Headcount and Cost'!G26),0) | Q17: =MAX(0,MIN('Headcount and Cost'!F26,64.95)-MAX('Headcount and Cost'!E26-1,60.62))*IFERROR('Headcount and Cost'!I26/('Headcount and Cost'!G26),0) | R17: =MAX(0,MIN('Headcount and Cost'!F26,69.28)-MAX('Headcount and Cost'!E26-1,64.95))*IFERROR('Headcount and Cost'!I26/('Headcount and Cost'!G26),0) | S17: =MAX(0,MIN('Headcount and Cost'!F26,73.61)-MAX('Headcount and Cost'!E26-1,69.28))*IFERROR('Headcount and Cost'!I26/('Headcount and Cost'!G26),0) | T17: =MAX(0,MIN('Headcount and Cost'!F26,77.94)-MAX('Headcount and Cost'!E26-1,73.61))*IFERROR('Headcount and Cost'!I26/('Headcount and Cost'!G26),0)
A18: =IF('Headcount and Cost'!A27="","",'Headcount and Cost'!A27&" - "&'Headcount and Cost'!J27) | B18: ='Headcount and Cost'!I27 | C18: =MAX(0,MIN('Headcount and Cost'!F27,4.33)-MAX('Headcount and Cost'!E27-1,0))*IFERROR('Headcount and Cost'!I27/('Headcount and Cost'!G27),0) | D18: =MAX(0,MIN('Headcount and Cost'!F27,8.66)-MAX('Headcount and Cost'!E27-1,4.33))*IFERROR('Headcount and Cost'!I27/('Headcount and Cost'!G27),0) | E18: =MAX(0,MIN('Headcount and Cost'!F27,12.99)-MAX('Headcount and Cost'!E27-1,8.66))*IFERROR('Headcount and Cost'!I27/('Headcount and Cost'!G27),0) | F18: =MAX(0,MIN('Headcount and Cost'!F27,17.32)-MAX('Headcount and Cost'!E27-1,12.99))*IFERROR('Headcount and Cost'!I27/('Headcount and Cost'!G27),0) | G18: =MAX(0,MIN('Headcount and Cost'!F27,21.65)-MAX('Headcount and Cost'!E27-1,17.32))*IFERROR('Headcount and Cost'!I27/('Headcount and Cost'!G27),0) | H18: =MAX(0,MIN('Headcount and Cost'!F27,25.98)-MAX('Headcount and Cost'!E27-1,21.65))*IFERROR('Headcount and Cost'!I27/('Headcount and Cost'!G27),0) | I18: =MAX(0,MIN('Headcount and Cost'!F27,30.31)-MAX('Headcount and Cost'!E27-1,25.98))*IFERROR('Headcount and Cost'!I27/('Headcount and Cost'!G27),0) | J18: =MAX(0,MIN('Headcount and Cost'!F27,34.64)-MAX('Headcount and Cost'!E27-1,30.31))*IFERROR('Headcount and Cost'!I27/('Headcount and Cost'!G27),0) | K18: =MAX(0,MIN('Headcount and Cost'!F27,38.97)-MAX('Headcount and Cost'!E27-1,34.64))*IFERROR('Headcount and Cost'!I27/('Headcount and Cost'!G27),0) | L18: =MAX(0,MIN('Headcount and Cost'!F27,43.3)-MAX('Headcount and Cost'!E27-1,38.97))*IFERROR('Headcount and Cost'!I27/('Headcount and Cost'!G27),0) | M18: =MAX(0,MIN('Headcount and Cost'!F27,47.63)-MAX('Headcount and Cost'!E27-1,43.3))*IFERROR('Headcount and Cost'!I27/('Headcount and Cost'!G27),0) | N18: =MAX(0,MIN('Headcount and Cost'!F27,51.96)-MAX('Headcount and Cost'!E27-1,47.63))*IFERROR('Headcount and Cost'!I27/('Headcount and Cost'!G27),0) | O18: =MAX(0,MIN('Headcount and Cost'!F27,56.29)-MAX('Headcount and Cost'!E27-1,51.96))*IFERROR('Headcount and Cost'!I27/('Headcount and Cost'!G27),0) | P18: =MAX(0,MIN('Headcount and Cost'!F27,60.62)-MAX('Headcount and Cost'!E27-1,56.29))*IFERROR('Headcount and Cost'!I27/('Headcount and Cost'!G27),0) | Q18: =MAX(0,MIN('Headcount and Cost'!F27,64.95)-MAX('Headcount and Cost'!E27-1,60.62))*IFERROR('Headcount and Cost'!I27/('Headcount and Cost'!G27),0) | R18: =MAX(0,MIN('Headcount and Cost'!F27,69.28)-MAX('Headcount and Cost'!E27-1,64.95))*IFERROR('Headcount and Cost'!I27/('Headcount and Cost'!G27),0) | S18: =MAX(0,MIN('Headcount and Cost'!F27,73.61)-MAX('Headcount and Cost'!E27-1,69.28))*IFERROR('Headcount and Cost'!I27/('Headcount and Cost'!G27),0) | T18: =MAX(0,MIN('Headcount and Cost'!F27,77.94)-MAX('Headcount and Cost'!E27-1,73.61))*IFERROR('Headcount and Cost'!I27/('Headcount and Cost'!G27),0)
A19: =IF('Headcount and Cost'!A28="","",'Headcount and Cost'!A28&" - "&'Headcount and Cost'!J28) | B19: ='Headcount and Cost'!I28 | C19: =MAX(0,MIN('Headcount and Cost'!F28,4.33)-MAX('Headcount and Cost'!E28-1,0))*IFERROR('Headcount and Cost'!I28/('Headcount and Cost'!G28),0) | D19: =MAX(0,MIN('Headcount and Cost'!F28,8.66)-MAX('Headcount and Cost'!E28-1,4.33))*IFERROR('Headcount and Cost'!I28/('Headcount and Cost'!G28),0) | E19: =MAX(0,MIN('Headcount and Cost'!F28,12.99)-MAX('Headcount and Cost'!E28-1,8.66))*IFERROR('Headcount and Cost'!I28/('Headcount and Cost'!G28),0) | F19: =MAX(0,MIN('Headcount and Cost'!F28,17.32)-MAX('Headcount and Cost'!E28-1,12.99))*IFERROR('Headcount and Cost'!I28/('Headcount and Cost'!G28),0) | G19: =MAX(0,MIN('Headcount and Cost'!F28,21.65)-MAX('Headcount and Cost'!E28-1,17.32))*IFERROR('Headcount and Cost'!I28/('Headcount and Cost'!G28),0) | H19: =MAX(0,MIN('Headcount and Cost'!F28,25.98)-MAX('Headcount and Cost'!E28-1,21.65))*IFERROR('Headcount and Cost'!I28/('Headcount and Cost'!G28),0) | I19: =MAX(0,MIN('Headcount and Cost'!F28,30.31)-MAX('Headcount and Cost'!E28-1,25.98))*IFERROR('Headcount and Cost'!I28/('Headcount and Cost'!G28),0) | J19: =MAX(0,MIN('Headcount and Cost'!F28,34.64)-MAX('Headcount and Cost'!E28-1,30.31))*IFERROR('Headcount and Cost'!I28/('Headcount and Cost'!G28),0) | K19: =MAX(0,MIN('Headcount and Cost'!F28,38.97)-MAX('Headcount and Cost'!E28-1,34.64))*IFERROR('Headcount and Cost'!I28/('Headcount and Cost'!G28),0) | L19: =MAX(0,MIN('Headcount and Cost'!F28,43.3)-MAX('Headcount and Cost'!E28-1,38.97))*IFERROR('Headcount and Cost'!I28/('Headcount and Cost'!G28),0) | M19: =MAX(0,MIN('Headcount and Cost'!F28,47.63)-MAX('Headcount and Cost'!E28-1,43.3))*IFERROR('Headcount and Cost'!I28/('Headcount and Cost'!G28),0) | N19: =MAX(0,MIN('Headcount and Cost'!F28,51.96)-MAX('Headcount and Cost'!E28-1,47.63))*IFERROR('Headcount and Cost'!I28/('Headcount and Cost'!G28),0) | O19: =MAX(0,MIN('Headcount and Cost'!F28,56.29)-MAX('Headcount and Cost'!E28-1,51.96))*IFERROR('Headcount and Cost'!I28/('Headcount and Cost'!G28),0) | P19: =MAX(0,MIN('Headcount and Cost'!F28,60.62)-MAX('Headcount and Cost'!E28-1,56.29))*IFERROR('Headcount and Cost'!I28/('Headcount and Cost'!G28),0) | Q19: =MAX(0,MIN('Headcount and Cost'!F28,64.95)-MAX('Headcount and Cost'!E28-1,60.62))*IFERROR('Headcount and Cost'!I28/('Headcount and Cost'!G28),0) | R19: =MAX(0,MIN('Headcount and Cost'!F28,69.28)-MAX('Headcount and Cost'!E28-1,64.95))*IFERROR('Headcount and Cost'!I28/('Headcount and Cost'!G28),0) | S19: =MAX(0,MIN('Headcount and Cost'!F28,73.61)-MAX('Headcount and Cost'!E28-1,69.28))*IFERROR('Headcount and Cost'!I28/('Headcount and Cost'!G28),0) | T19: =MAX(0,MIN('Headcount and Cost'!F28,77.94)-MAX('Headcount and Cost'!E28-1,73.61))*IFERROR('Headcount and Cost'!I28/('Headcount and Cost'!G28),0)
A20: =IF('Headcount and Cost'!A29="","",'Headcount and Cost'!A29&" - "&'Headcount and Cost'!J29) | B20: ='Headcount and Cost'!I29 | C20: =MAX(0,MIN('Headcount and Cost'!F29,4.33)-MAX('Headcount and Cost'!E29-1,0))*IFERROR('Headcount and Cost'!I29/('Headcount and Cost'!G29),0) | D20: =MAX(0,MIN('Headcount and Cost'!F29,8.66)-MAX('Headcount and Cost'!E29-1,4.33))*IFERROR('Headcount and Cost'!I29/('Headcount and Cost'!G29),0) | E20: =MAX(0,MIN('Headcount and Cost'!F29,12.99)-MAX('Headcount and Cost'!E29-1,8.66))*IFERROR('Headcount and Cost'!I29/('Headcount and Cost'!G29),0) | F20: =MAX(0,MIN('Headcount and Cost'!F29,17.32)-MAX('Headcount and Cost'!E29-1,12.99))*IFERROR('Headcount and Cost'!I29/('Headcount and Cost'!G29),0) | G20: =MAX(0,MIN('Headcount and Cost'!F29,21.65)-MAX('Headcount and Cost'!E29-1,17.32))*IFERROR('Headcount and Cost'!I29/('Headcount and Cost'!G29),0) | H20: =MAX(0,MIN('Headcount and Cost'!F29,25.98)-MAX('Headcount and Cost'!E29-1,21.65))*IFERROR('Headcount and Cost'!I29/('Headcount and Cost'!G29),0) | I20: =MAX(0,MIN('Headcount and Cost'!F29,30.31)-MAX('Headcount and Cost'!E29-1,25.98))*IFERROR('Headcount and Cost'!I29/('Headcount and Cost'!G29),0) | J20: =MAX(0,MIN('Headcount and Cost'!F29,34.64)-MAX('Headcount and Cost'!E29-1,30.31))*IFERROR('Headcount and Cost'!I29/('Headcount and Cost'!G29),0) | K20: =MAX(0,MIN('Headcount and Cost'!F29,38.97)-MAX('Headcount and Cost'!E29-1,34.64))*IFERROR('Headcount and Cost'!I29/('Headcount and Cost'!G29),0) | L20: =MAX(0,MIN('Headcount and Cost'!F29,43.3)-MAX('Headcount and Cost'!E29-1,38.97))*IFERROR('Headcount and Cost'!I29/('Headcount and Cost'!G29),0) | M20: =MAX(0,MIN('Headcount and Cost'!F29,47.63)-MAX('Headcount and Cost'!E29-1,43.3))*IFERROR('Headcount and Cost'!I29/('Headcount and Cost'!G29),0) | N20: =MAX(0,MIN('Headcount and Cost'!F29,51.96)-MAX('Headcount and Cost'!E29-1,47.63))*IFERROR('Headcount and Cost'!I29/('Headcount and Cost'!G29),0) | O20: =MAX(0,MIN('Headcount and Cost'!F29,56.29)-MAX('Headcount and Cost'!E29-1,51.96))*IFERROR('Headcount and Cost'!I29/('Headcount and Cost'!G29),0) | P20: =MAX(0,MIN('Headcount and Cost'!F29,60.62)-MAX('Headcount and Cost'!E29-1,56.29))*IFERROR('Headcount and Cost'!I29/('Headcount and Cost'!G29),0) | Q20: =MAX(0,MIN('Headcount and Cost'!F29,64.95)-MAX('Headcount and Cost'!E29-1,60.62))*IFERROR('Headcount and Cost'!I29/('Headcount and Cost'!G29),0) | R20: =MAX(0,MIN('Headcount and Cost'!F29,69.28)-MAX('Headcount and Cost'!E29-1,64.95))*IFERROR('Headcount and Cost'!I29/('Headcount and Cost'!G29),0) | S20: =MAX(0,MIN('Headcount and Cost'!F29,73.61)-MAX('Headcount and Cost'!E29-1,69.28))*IFERROR('Headcount and Cost'!I29/('Headcount and Cost'!G29),0) | T20: =MAX(0,MIN('Headcount and Cost'!F29,77.94)-MAX('Headcount and Cost'!E29-1,73.61))*IFERROR('Headcount and Cost'!I29/('Headcount and Cost'!G29),0)
A22: TOTAL | B22: =SUM(B9:B20) | C22: =SUM(C9:C20) | D22: =SUM(D9:D20) | E22: =SUM(E9:E20) | F22: =SUM(F9:F20) | G22: =SUM(G9:G20) | H22: =SUM(H9:H20) | I22: =SUM(I9:I20) | ... T22: =SUM(T9:T20)

Sheet Fixed Costs
A1: Fixed / 3rd-party Costs
A2: Purpose: | B2: Lump-sum costs not modeled per FTE-hour: penetration testing, performance testing, smart contract audit, compliance officer, technical writer, KYC/AML licenses, cloud bill estimates.
A3: How to use: | B3: (1) Add a line per cost. (2) Set Include = Included to add it to the SOW total, Not included to keep it visible but excluded, Post-MVP to defer, Select for decision pending. (3) Use the Notes column to point to the vendor quote. (4) Cloud cost lines: pull values from the DevOps Estimation tab cost-modelling outputs.
A4: Inputs: | B4: Manual entries (item, amount, vendor, notes, include).
A5: Outputs: | B5: 'Total Included' at the bottom — add to SOW external total beside Headcount and Cost Total Cost.
A6: Linked tabs: | B6: DevOps Estimation (cloud cost estimates feed this tab). Headcount and Cost (Total Cost is the FTE side; this tab is the non-FTE side).
A8: Item | B8: Amount, $ | C8: Vendor / supplier | D8: Notes | E8: Include
A9: Penetration testing | B9: 35000 | D9: external pen-test before go-live | E9: Included
A10: Performance / load testing | B10: 20000 | D10: JMeter / k6 partner | E10: Included
A11: Compliance Officer (per audit) | B11: 20000 | D11: GDPR / PCI-DSS sign-off | E11: Not included
A12: Technical Writer | B12: 20000 | D12: user docs + admin guide | E12: Not included
A13: Smart Contract Audit | B13: 15000 | D13: if blockchain components | E13: Not included
A14: 3rd-party KYC / AML licenses | B14: 0 | D14: Onfido, SumSub, Veriff | E14: Select
A15: Cloud cost (Discovery) | B15: 0 | D15: estimate from DevOps tab | E15: Included
A16: Cloud cost (Implementation) | B16: 0 | D16: estimate from DevOps tab | E16: Included
A17: Cloud cost (1st year prod) | B17: 0 | D17: estimate from DevOps tab | E17: Included
A19: Total Included | B19: =SUMIF(E9:E17,"Included",B9:B17)

Sheet Maintenance
A1: Maintenance / Run-rate Cost (post go-live)
A2: Purpose: | B2: Steady-state monthly cost grid for support / minor enhancements after go-live. Same role pattern as Headcount and Cost but with monthly cadence (168 h/mo per FTE).
A3: How to use: | B3: (1) For each role you'll keep on retainer, set Headcount and Allocation. (2) Rate is looked up from the Rates tab. (3) The Annual Run-rate cell at the bottom is what you quote in the SOW maintenance section. (4) If the deal is fixed-price-with-SLA, also discuss Fixed Costs (cloud bill, monitoring, security tooling) — they aren't here.
A4: Inputs: | B4: Per-role Headcount, Allocation, Seniority, Location. Rates tab.
A5: Outputs: | B5: Monthly Run-rate, Annual Run-rate.
A6: Linked tabs: | B6: Rates (rate lookup). Headcount and Cost (build phase counterpart). Fixed Costs (non-FTE recurring costs).
A8: Role | B8: Seniority | C8: Location | D8: Headcount | E8: Allocation | F8: FTE | G8: Hours/Month | H8: Rate, $/h | I8: Monthly Cost, $
A9: PM | B9: M1 | C9: Poland | D9: 1 | E9: 0.25 | F9: =D9*E9 | G9: =F9*168 | H9: {=IFERROR(INDEX(Rates!$D:$D,MATCH(1,(Rates!$A:$A=A9)*(Rates!$B:$B=B9)*(Rates!$C:$C=C9),0)),RefRate)} | I9: =G9*H9
A10: Back-End | B10: S1 | C10: Poland | D10: 1 | E10: 0.5 | F10: =D10*E10 | G10: =F10*168 | H10: {=IFERROR(INDEX(Rates!$D:$D,MATCH(1,(Rates!$A:$A=A10)*(Rates!$B:$B=B10)*(Rates!$C:$C=C10),0)),RefRate)} | I10: =G10*H10
A11: Front-End Web | B11: M1 | C11: Poland | D11: 1 | E11: 0.25 | F11: =D11*E11 | G11: =F11*168 | H11: {=IFERROR(INDEX(Rates!$D:$D,MATCH(1,(Rates!$A:$A=A11)*(Rates!$B:$B=B11)*(Rates!$C:$C=C11),0)),RefRate)} | I11: =G11*H11
A12: Front-End Mobile | B12: S1 | C12: Poland | D12: 1 | E12: 0.25 | F12: =D12*E12 | G12: =F12*168 | H12: {=IFERROR(INDEX(Rates!$D:$D,MATCH(1,(Rates!$A:$A=A12)*(Rates!$B:$B=B12)*(Rates!$C:$C=C12),0)),RefRate)} | I12: =G12*H12
A13: Manual QA | B13: M1 | C13: Poland | D13: 1 | E13: 0.5 | F13: =D13*E13 | G13: =F13*168 | H13: {=IFERROR(INDEX(Rates!$D:$D,MATCH(1,(Rates!$A:$A=A13)*(Rates!$B:$B=B13)*(Rates!$C:$C=C13),0)),RefRate)} | I13: =G13*H13
A14: DevOps | B14: S1 | C14: Poland | D14: 1 | E14: 0.5 | F14: =D14*E14 | G14: =F14*168 | H14: {=IFERROR(INDEX(Rates!$D:$D,MATCH(1,(Rates!$A:$A=A14)*(Rates!$B:$B=B14)*(Rates!$C:$C=C14),0)),RefRate)} | I14: =G14*H14
A15: BA | B15: S1 | C15: Poland | D15: 1 | E15: 0.1 | F15: =D15*E15 | G15: =F15*168 | H15: {=IFERROR(INDEX(Rates!$D:$D,MATCH(1,(Rates!$A:$A=A15)*(Rates!$B:$B=B15)*(Rates!$C:$C=C15),0)),RefRate)} | I15: =G15*H15
A16: Solution Architect | B16: S1 | C16: Poland | D16: 1 | E16: 0.1 | F16: =D16*E16 | G16: =F16*168 | H16: {=IFERROR(INDEX(Rates!$D:$D,MATCH(1,(Rates!$A:$A=A16)*(Rates!$B:$B=B16)*(Rates!$C:$C=C16),0)),RefRate)} | I16: =G16*H16
A18: Monthly Run-rate Total | I18: =SUM(I9:I16)
A19: Annual Run-rate | I19: =I18*12

Sheet Epic Weight
A1: Epic Weight (Build cost ranking)
A2: Purpose: | B2: The 'where does the money go?' view. Sums Expected Implementation BE+FE per epic from WBS and Estimates, multiplied by RefRate, and ranks epics by cost.
A3: How to use: | B3: (1) The Epic ID column matches against the LEFT of WBS column B (ID). Add a row per epic; epic prefix must match the ID format used on WBS (e.g. 'E-1', 'INF'). (2) Cost is blended (BE+FE Expected hours * RefRate). For role-aware cost split, build a custom view from Headcount and Cost. (3) % of build column is share of total — useful in client conversations.
A4: Inputs: | B4: Epic IDs (manual). WBS and Estimates Expected BE/FE columns. RefRate.
A5: Outputs: | B5: Per-epic build cost and % of total. Sort the table after totals are calculated to rank.
A6: Linked tabs: | B6: WBS and Estimates (data source). Input Data (RefRate).
A8: Epic ID | B8: Epic Name | C8: BE Hours | D8: FE Hours | E8: Cost (blended), $ | F8: % of build
A9: INF | B9: Infrastructure & Foundations | C9: =SUMPRODUCT(--(LEFT('WBS and Estimates'!$B$1:$B$500,3)=A9),'WBS and Estimates'!$P$1:$P$500) | D9: =SUMPRODUCT(--(LEFT('WBS and Estimates'!$B$1:$B$500,3)=A9),'WBS and Estimates'!$Q$1:$Q$500) | E9: =(C9+D9)*RefRate | F9: =IFERROR(E9/SUM($E$9:$E$59),0)
A10: E-1 | B10: Authorization | C10: =SUMPRODUCT(--(LEFT('WBS and Estimates'!$B$1:$B$500,3)=A10),'WBS and Estimates'!$P$1:$P$500) | D10: =SUMPRODUCT(--(LEFT('WBS and Estimates'!$B$1:$B$500,3)=A10),'WBS and Estimates'!$Q$1:$Q$500) | E10: =(C10+D10)*RefRate | F10: =IFERROR(E10/SUM($E$9:$E$59),0)
A11: E-2 | B11: Profile Management | C11: =SUMPRODUCT(--(LEFT('WBS and Estimates'!$B$1:$B$500,3)=A11),'WBS and Estimates'!$P$1:$P$500) | D11: =SUMPRODUCT(--(LEFT('WBS and Estimates'!$B$1:$B$500,3)=A11),'WBS and Estimates'!$Q$1:$Q$500) | E11: =(C11+D11)*RefRate | F11: =IFERROR(E11/SUM($E$9:$E$59),0)
A12: E-3 | B12: Wallet | C12: =SUMPRODUCT(--(LEFT('WBS and Estimates'!$B$1:$B$500,3)=A12),'WBS and Estimates'!$P$1:$P$500) | D12: =SUMPRODUCT(--(LEFT('WBS and Estimates'!$B$1:$B$500,3)=A12),'WBS and Estimates'!$Q$1:$Q$500) | E12: =(C12+D12)*RefRate | F12: =IFERROR(E12/SUM($E$9:$E$59),0)
B14: Total | E14: =SUM(E9:E12)

Sheet WBS Comparison
A1: WBS Comparison (snapshot vs current)
A2: Purpose: | B2: Tracks scope creep between estimate versions. Stores up to two snapshots side-by-side and computes deltas vs. the current WBS, joined by ID.
A3: How to use: | B3: (1) PASTE the v1 snapshot BE/FE hours in cols C-D against each ID. (2) Optionally paste a v1.1 snapshot in cols E-F. (3) Current BE/FE columns auto-pull from WBS and Estimates by ID match. (4) Δ columns show the change. (5) When a new version starts, snapshot the current numbers into the v1.1 cols (paste-as-values), then move v1.1 to v1 and clear v1.1.
A4: Inputs: | B4: Snapshot pastes (manual). WBS and Estimates Expected BE/FE.
A5: Outputs: | B5: Δ BE / Δ FE per row.
A6: Linked tabs: | B6: WBS and Estimates.
A8: ID | B8: Decomposition Item | C8: v1 BE | D8: v1 FE | E8: v1.1 BE | F8: v1.1 FE | G8: Current BE | H8: Current FE | I8: Δ (BE) | J8: Δ (FE)
A9: INF-1.1 | B9: Solution setup (repos, project templates) | G9: {=IFERROR(INDEX('WBS and Estimates'!$P:$P,MATCH(A9,'WBS and Estimates'!$B:$B,0)),0)} | H9: {=IFERROR(INDEX('WBS and Estimates'!$Q:$Q,MATCH(A9,'WBS and Estimates'!$B:$B,0)),0)} | I9: =G9-IFERROR(E9,C9) | J9: =H9-IFERROR(F9,D9)
A10: INF-1.2 | B10: Local infrastructure setup | G10: {=IFERROR(INDEX('WBS and Estimates'!$P:$P,MATCH(A10,'WBS and Estimates'!$B:$B,0)),0)} | H10: {=IFERROR(INDEX('WBS and Estimates'!$Q:$Q,MATCH(A10,'WBS and Estimates'!$B:$B,0)),0)} | I10: =G10-IFERROR(E10,C10) | J10: =H10-IFERROR(F10,D10)
A11: INF-1.3 | B11: CI/CD setup | G11: {=IFERROR(INDEX('WBS and Estimates'!$P:$P,MATCH(A11,'WBS and Estimates'!$B:$B,0)),0)} | H11: {=IFERROR(INDEX('WBS and Estimates'!$Q:$Q,MATCH(A11,'WBS and Estimates'!$B:$B,0)),0)} | I11: =G11-IFERROR(E11,C11) | J11: =H11-IFERROR(F11,D11)
A12: INF-1.4 | B12: Static code analysis | G12: {=IFERROR(INDEX('WBS and Estimates'!$P:$P,MATCH(A12,'WBS and Estimates'!$B:$B,0)),0)} | H12: {=IFERROR(INDEX('WBS and Estimates'!$Q:$Q,MATCH(A12,'WBS and Estimates'!$B:$B,0)),0)} | I12: =G12-IFERROR(E12,C12) | J12: =H12-IFERROR(F12,D12)
A13: US-1.1 | B13: Onboarding | G13: {=IFERROR(INDEX('WBS and Estimates'!$P:$P,MATCH(A13,'WBS and Estimates'!$B:$B,0)),0)} | H13: {=IFERROR(INDEX('WBS and Estimates'!$Q:$Q,MATCH(A13,'WBS and Estimates'!$B:$B,0)),0)} | I13: =G13-IFERROR(E13,C13) | J13: =H13-IFERROR(F13,D13)
A14: US-1.2 | B14: Accept Terms of Use | G14: {=IFERROR(INDEX('WBS and Estimates'!$P:$P,MATCH(A14,'WBS and Estimates'!$B:$B,0)),0)} | H14: {=IFERROR(INDEX('WBS and Estimates'!$Q:$Q,MATCH(A14,'WBS and Estimates'!$B:$B,0)),0)} | I14: =G14-IFERROR(E14,C14) | J14: =H14-IFERROR(F14,D14)
A15: US-1.3 | B15: Sign Up (email/phone/SSO) | G15: {=IFERROR(INDEX('WBS and Estimates'!$P:$P,MATCH(A15,'WBS and Estimates'!$B:$B,0)),0)} | H15: {=IFERROR(INDEX('WBS and Estimates'!$Q:$Q,MATCH(A15,'WBS and Estimates'!$B:$B,0)),0)} | I15: =G15-IFERROR(E15,C15) | J15: =H15-IFERROR(F15,D15)
A16: US-1.4 | B16: Login | G16: {=IFERROR(INDEX('WBS and Estimates'!$P:$P,MATCH(A16,'WBS and Estimates'!$B:$B,0)),0)} | H16: {=IFERROR(INDEX('WBS and Estimates'!$Q:$Q,MATCH(A16,'WBS and Estimates'!$B:$B,0)),0)} | I16: =G16-IFERROR(E16,C16) | J16: =H16-IFERROR(F16,D16)
A17: US-1.5 | B17: Reset password | G17: {=IFERROR(INDEX('WBS and Estimates'!$P:$P,MATCH(A17,'WBS and Estimates'!$B:$B,0)),0)} | H17: {=IFERROR(INDEX('WBS and Estimates'!$Q:$Q,MATCH(A17,'WBS and Estimates'!$B:$B,0)),0)} | I17: =G17-IFERROR(E17,C17) | J17: =H17-IFERROR(F17,D17)
A18: US-1.6 | B18: Logout | G18: {=IFERROR(INDEX('WBS and Estimates'!$P:$P,MATCH(A18,'WBS and Estimates'!$B:$B,0)),0)} | H18: {=IFERROR(INDEX('WBS and Estimates'!$Q:$Q,MATCH(A18,'WBS and Estimates'!$B:$B,0)),0)} | I18: =G18-IFERROR(E18,C18) | J18: =H18-IFERROR(F18,D18)
A19: US-1.7 | B19: 2FA setup | G19: {=IFERROR(INDEX('WBS and Estimates'!$P:$P,MATCH(A19,'WBS and Estimates'!$B:$B,0)),0)} | H19: {=IFERROR(INDEX('WBS and Estimates'!$Q:$Q,MATCH(A19,'WBS and Estimates'!$B:$B,0)),0)} | I19: =G19-IFERROR(E19,C19) | J19: =H19-IFERROR(F19,D19)
A20: US-2.1 | B20: View profile info | G20: {=IFERROR(INDEX('WBS and Estimates'!$P:$P,MATCH(A20,'WBS and Estimates'!$B:$B,0)),0)} | H20: {=IFERROR(INDEX('WBS and Estimates'!$Q:$Q,MATCH(A20,'WBS and Estimates'!$B:$B,0)),0)} | I20: =G20-IFERROR(E20,C20) | J20: =H20-IFERROR(F20,D20)
... A29: US-3.5 | B29: KYC initiate / upload ID / verify | G29: {=IFERROR(INDEX('WBS and Estimates'!$P:$P,MATCH(A29,'WBS and Estimates'!$B:$B,0)),0)} | H29: {=IFERROR(INDEX('WBS and Estimates'!$Q:$Q,MATCH(A29,'WBS and Estimates'!$B:$B,0)),0)} | I29: =G29-IFERROR(E29,C29) | J29: =H29-IFERROR(F29,D29)
